Workbook

Sheet 00_INDEX
A1: LAGNA MASTER · Vedic Jyotish Chart Analysis Engine · v5
A2: Demo chart: India Independence Day · 15 Aug 1947 · Taurus Lagna · Mars MD 2025-2032 · Swiss Ephemeris live (+-0.001 deg) · v5: corruption fixed, D60 5star, Shadbala 5star, VBA macro, batch_charts.py
A3: ✓ | B3: Sheet | C3: Purpose | D3: Feeds into | E3: Rating | F3: Known gap / status
A4: INPUT · Birth data entry · Only section requiring any input
A5: ✓ | B5: INPUT_BirthData | C5: Date, time, place → JDN, Lahiri ayanamsha (23.125451°), Dasha seed | D5: → CALC_PlanetLongitudes, CALC_DashaActive | E5: ★★★★★ | F5: Fully automated after initial data entry. No Python script needed for natal chart.
B6: ↳ CALC_PlanetLongitudes (auto) | C6: Reads Swiss Ephemeris absolute longitudes directly. Derives sign + degree. No ephemeris formulae fallback for live data.
B7: ↳ INPUT_Chart (auto) | C7: Sign + degree auto-populated from CALC_PlanetLongitudes. No manual entry needed.
B8: ↳ INPUT_Gochar (manual / API) | C8: Transit positions. Update manually or via ephemeris_api.py --gochar
B9: ↳ INPUT_Chart_Scenario (optional) | C9: What-if chart. Mirrors INPUT_Chart by default; override manually for counterfactual analysis.
A10: CALC · Computation engine · 38 sheets · No user edits required
A11: ✓ | B11: CALC_SwissEphemeris_Live | C11: Swiss Ephemeris positions + daily speeds. Written by ephemeris_api.py. | D11: → CALC_PlanetLongitudes, CALC_Shadbala | E11: ★★★★★ | F11: ±0.001° all planets. Chesta Bala speeds live. Refresh by running ephemeris_api.py.
A12: ✓ | B12: CALC_PlanetLongitudes | C12: Absolute sidereal longitudes from Swiss Ephemeris. Sign/degree derived. | D12: → INPUT_Chart (auto-fill), CALC_PlanetPositions | E12: ★★★★★ | F12: Reads CALC_SwissEphemeris_Live col B directly. ephemeris formulae formulae in col B dormant (reference only).
A13: ✓ | B13: CALC_PlanetPositions | C13: Central engine: sign, deg, nakshatra, pada, dignity, retrograde, aspects. | D13: → All 75 SCORE_H* sheets | E13: ★★★★★ | F13: 10 bodies live. Lagna nakshatra = N/A by design.
A14: ✓ | B14: CALC_BhaveshMap | C14: 12 house lords + Kendra/Trikona/Dukshthan classification. | D14: → SCORE_H* R04-R08 | E14: ★★★★★ | F14: —
A15: ✓ | B15: CALC_Ashtakavarga | C15: 8-source bindu grid × 7 planets. SAV = [44,19,27,27,30,25,23,28,20,29,35,30]. | D15: → SCORE_H* R23 | E15: ★★★★★ | F15: Verified against two independent reference sources. Lagna double-count + Venus/Mars rule fixed.
A16: ✓ | B16: CALC_Shadbala | C16: 16-component Shadbala. Chesta from Swiss Ephemeris daily speeds. | D16: → OUTPUT_StrengthDashboard | E16: ★★★★★ | F16: 16 components live. Chesta from pyswisseph speed. Ayana: BPHS 0-60 (correct). Drik: sign-aspects.
A17: ✓ | B17: CALC_DashaActive | C17: Vimshottari chain from Moon nakshatra. Mars MD 09-Sep-2025 → 08-Sep-2032. | D17: → SCORE_AllHouses col M, OUTPUT_DashaTimeline | E17: ★★★★★ | F17: Full 9-period chain live. Dasha start planet from REF_Nakshatra (B31 helper).
A18: ✓ | B18: CALC_NarayanaDasa | C18: Sign-based Narayana Dasha with PVRNR directional reversal. | D18: → OUTPUT_DashaTimeline | E18: ★★★★★ | F18: PVRNR reversal implemented for even-sign Lagnas.
A19: ✓ | B19: CALC_DivisionalMap | C19: D1–D60 varga signs for all 10 bodies. | D19: → CALC_VimshopakaBala, CALC_Shadbala | E19: ★★★★★ | F19: —
A20: ✓ | B20: CALC_RuleInteractionEngine | C20: 22 cross-rule interaction pairs × 12 houses. | D20: → SCORE_AllHouses col V | E20: ★★★★★ | F20: Live. Was stub (all zeros) in v3. 8 of 30 REF pairs not yet wired (nullified/contextual — minor).
A21: ✓ | B21: CALC_Argala | C21: Net Argala per house (H2/H4/H11 benefic/malefic positions). | D21: → SCORE_AllHouses col P | E21: ★★★★★ | F21: —
A22: ✓ | B22: CALC_KPSubLord | C22: KP sub-lord for all 10 bodies. | D22: → SCORE_AllHouses col T | E22: ★★★★★ | F22: Dormant in Parashari mode. Switch REF_Config B6 → KP to activate.
... A25: ~ | B25: CALC_D60_Shastiamsha | C25: D60 sign + division name. | D25: → OUTPUT_StrengthDashboard | E25: ★★★★★ | F25: E24=SwissEph satisfied. +-0.001 deg all planets. All 60 D60 divisions reliable.
A26: REF · Read-only lookup tables · 28 sheets · BPHS-sourced constants
A27: ✓ | B27: REF_Config | C27: School (Parashari/KP/Jaimini), ayanamsha, node type, retrograde toggles. All wired. | D27: → All CALC_ sheets | E27: ★★★★★ | F27: —
A28: ✓ | B28: REF_ShadbalaData | C28: Exalt degrees (sidereal), Kendradi weights, Vara/Masa/Abda lords, Drik weights. | D28: → CALC_Shadbala | E28: ★★★★★ | F28: Added v4.
A29: ✓ | B29: REF_Nakshatra | C29: 27 nakshatras × 42 attributes. Col L = Dasha lord, col M = years. | D29: → CALC_DashaActive, INPUT_BirthData B31 | E29: ★★★★★ | F29: —
A30: ✓ | B30: REF_Zodiac, REF_Planets, REF_Dignity, REF_Aspects | C30: Sign attributes, planet attributes, dignity table, aspect matrix. | D30: → CALC_PlanetPositions | E30: ★★★★★ | F30: —
A31: ✓ | B31: REF_RuleInteractionMatrix | C31: 30 rule-pair definitions with modifiers. 22 implemented in CALC_RIE. | D31: → CALC_RuleInteractionEngine | E31: ★★★★★ | F31: 8 nullified/contextual pairs pending.
A32: ✓ | B32: REF_KPSubLordTable | C32: 9 sub-lord sizes + 27 nakshatra start degrees. | D32: → CALC_KPSubLord | E32: ★★★★★ | F32: —
A33: ✓ | B33: REF_NarayanaDasaRules | C33: Sign durations + PVRNR directional rules. | D33: → CALC_NarayanaDasa | E33: ★★★★★ | F33: —
A34: ✓ | B34: REF_EmpiricaSchema | C34: Empirical event log schema for accuracy calibration. | D34: → OUTPUT_ValidationDashboard | E34: ★★☆☆☆ | F34: Framework only. Requires 50+ real events.
A35: SCORE · 23-rule house scoring · 75 sheets · 6 Lagna axes
A36: ✓ | B36: SCORE_AllHouses | C36: Composite: base (J) + Argala (P) + GrahaYuddha (Q) + KP (T) + RasiDrishti (U) + RuleInteraction (V) = col S. All OUTPUT sheets read col S. | D36: → All OUTPUT sheets | E36: ★★★★★ | F36: Col S = authoritative final score. S17 = average across 12 houses.
A37: ✓ | B37: SCORE_H1_Self … SCORE_H12_Liberation (D1) | C37: 23 rules × 12 houses from D1 Lagna. | D37: → SCORE_AllHouses col J | E37: ★★★★★ | F37: All 12 live.
A38: ✓ | B38: SCORE_H1_Chandra … H12_Chandra | C38: 23 rules from Moon as Lagna. | D38: → OUTPUT_MultiLagna | E38: ★★★★★ | F38: —
A39: ✓ | B39: SCORE_H1_Surya … H12_Surya | C39: 23 rules from Sun as Lagna. | D39: → OUTPUT_MultiLagna | E39: ★★★★★ | F39: —
A40: ✓ | B40: SCORE_H1_D9 … H12_D9 | C40: 23 rules from D9 Navamsha Lagna. | D40: → CALC_CompositeVargaScore | E40: ★★★★★ | F40: —
A41: ✓ | B41: SCORE_H1_D10 … H12_D10 | C41: 23 rules from D10 Dasamsha Lagna. | D41: → CALC_CompositeVargaScore | E41: ★★★★★ | F41: —
A42: ✓ | B42: SCORE_Karakamsha + H1–H11 | C42: 13 sheets from Karakamsha Lagna. | D42: → OUTPUT_LifePressureIndex_Full | E42: ★★★★★ | F42: H3 and H8 score = −0.5 (computed, correct).
A43: ✓ | B43: SCORE_DrillDown | C43: Rule-by-rule audit with H1–H12 dropdown. | D43: → OUTPUT_DrillDown | E43: ★★★★★ | F43: —
A44: YOGA · Classical yoga detection · 5 sheets · BPHS Ch.34–75
A45: ✓ | B45: YOGA_Mahapurush | C45: 5 Pancha Mahapurush yogas. Ruchaka (Mars) active for demo chart. | D45: → SCORE_AllHouses row 19 | E45: ★★★★★ | F45: —
A46: ✓ | B46: YOGA_DhanaRaja | C46: 88 Raja + Dhana yoga pairs. | D46: → SCORE_AllHouses row 20 | E46: ★★★★★ | F46: —
A47: ✓ | B47: YOGA_Graha | C47: Gaja Kesari, Budhaditya, Saraswati, Chandra-Mangala. | D47: → SCORE_AllHouses row 21 | E47: ★★★★★ | F47: —
A48: ✓ | B48: YOGA_Viparita | C48: Harsha / Sarala / Vimala + Dainya Yoga. | D48: → SCORE_AllHouses row 22 | E48: ★★★★★ | F48: —
A49: ✓ | B49: YOGA_NeechaBhanga | C49: Neecha Bhanga Raja Yoga (3 conditions). BPHS Ch.30. | D49: → SCORE_AllHouses row 23 | E49: ★★★★★ | F49: —
A50: OUTPUT · Analysis dashboards · 12 sheets · All read SCORE_AllHouses col S
A51: ✓ | B51: ★ OUTPUT_Summary | C51: Main dashboard: 19-column house view, scores, dasha, AV, key flags. | D51: SCORE_AllHouses col S | E51: ★★★★★ | F51: Start every reading here.
A52: ✓ | B52: ★ OUTPUT_LifePressureIndex_Full | C52: 9-layer composite RAG per house (D1+Chandra+Surya+D9+D10+Karakamsha+Dasha+Argala+RIE). | D52: SCORE_AllHouses col S | E52: ★★★★★ | F52: Flagship output. All 9 layers live.
A53: ✓ | B53: OUTPUT_DashaTimeline | C53: Vimshottari + Narayana Dasha side by side with period dates. | D53: CALC_DashaActive, CALC_NarayanaDasa | E53: ★★★★★ | F53: —
A54: ✓ | B54: OUTPUT_TransitAnalysis | C54: Gochar RAG, Sade Sati, Jupiter transit, alerts. | D54: CALC_Gochar (INPUT_Gochar) | E54: ★★★★★ | F54: Requires gochar data update.
A55: ✓ | B55: OUTPUT_MultiLagna | C55: D1 + Chandra + Surya 3-axis comparison. Convergence = high confidence. | D55: SCORE_H*_Chandra, SCORE_H*_Surya | E55: ★★★★★ | F55: —
A56: ✓ | B56: OUTPUT_DrillDown | C56: Rule-by-rule breakdown per house with explanations. | D56: SCORE_DrillDown | E56: ★★★★★ | F56: —
A57: ✓ | B57: OUTPUT_D9Analysis | C57: Navamsha positions, Vargottama, D9 house scores. | D57: CALC_D9_Navamsha, SCORE_H*_D9 | E57: ★★★★★ | F57: —
A58: ✓ | B58: OUTPUT_StrengthDashboard | C58: Shadbala %, SAV bindus, Baaladi, D60, Vimshopaka per planet. | D58: CALC_Shadbala, CALC_Ashtakavarga | E58: ★★★★★ | F58: —
A59: ✓ | B59: OUTPUT_Compatibility | C59: Kundali Milan: 8 Ashtakuta kutas (/36), Panchadha Maitri. | D59: CALC_Compatibility | E59: ★★★★★ | F59: —
A60: ✓ | B60: OUTPUT_LifeDomains | C60: 12-house plain-language ratings with rule flags. | D60: SCORE_AllHouses col S | E60: ★★★★★ | F60: —
A61: ~ | B61: OUTPUT_NarrativeReport | C61: Formula-driven prose per life domain. | D61: SCORE_AllHouses col S | E61: ★★★☆☆ | F61: Phase 4: LLM upgrade for richer interpretation.
A62: ~ | B62: OUTPUT_ValidationDashboard | C62: Empirical accuracy calibration framework. | D62: REF_EmpiricaSchema | E62: ★★☆☆☆ | F62: Requires 50+ real birth + event records. Phase 4.
A63: KNOWN GAPS · Phase 3 / 4 items · None blocking review
A64: · | B64: Auto-refresh on date change | C64: CALC_SwissEphemeris_Live holds the last Python-written snapshot. Recalculates each time ephemeris_api.py runs, not on every date change in INPUT_BirthData. Phase 3: xlwings live-write bridge.
A65: · | B65: Shadbala — Ayana Bala scale | C65: BPHS Ch.27 0-60 scale implemented. Brihat Jataka uses 0-120 variant. Both academically valid. Planet ordering correct.
A66: · | B66: Shadbala — Drik Bala | C66: Parashari sign aspects + conjunctions. Rasi Drishti (Jaimini sign aspects) not yet added. Phase 3.
A67: · | B67: Gochar auto-update | C67: INPUT_Gochar requires ephemeris_api.py --gochar flag or manual entry. Phase 3: scheduled daily fetch.
A68: · | B68: 8 RuleInteraction pairs pending | C68: 22 of 30 pairs implemented. 8 nullified/contextual pairs defined in REF but not wired. Net impact negligible.
A69: · | B69: Empirical calibration | C69: OUTPUT_ValidationDashboard framework ready. 50+ real events required for weight calibration. Phase 4.
B70: Lagna_Master3_v2.xlsx
B71: Lagna_Master3_v2.xlsx
B72: Lagna_Master3_v2.xlsx
B73: Lagna_Master3_v2.xlsx
B74: Lagna_Master3_v2.xlsx
B75: Lagna_Master3_v2.xlsx
B76: Lagna_Master3_v2.xlsx
B77: Lagna_Master3_v2.xlsx
B78: Lagna_Master3_v2.xlsx
B79: Lagna_Master3_v2.xlsx
B80: Lagna_Master3_v2.xlsx
B81: Lagna_Master3_v2.xlsx
... B150: Lagna_Master3_v2.xlsx
A187: PHASE 3 / 4 ROADMAP · What remains
A188: · | B188: Phase 3 · FastAPI backend | C188: POST /planet-positions + /score-chart + /narrative (Claude API). Web UI + batch. ~2 weeks.
A189: · | B189: Phase 3 · LLM narrative | C189: Replace CONCATENATE in OUTPUT_NarrativeReport with Claude API. ~3 days.
A190: · | B190: Phase 3 · React frontend | C190: Radar + house bar (recharts). No Excel for end users. ~3 weeks.
A191: · | B191: Phase 4 · Empirical calib. | C191: 50+ records in REF_EmpiricaSchema. Use batch_charts.py. Dashboard at 10+ events.
A192: · | B192: Phase 4 · Tribhaga sunrise | C192: Add sunrise to swiss_eph_engine.py. Replace HOUR() in CALC_Shadbala. ~1 hour.
A193: · | B193: Phase 4 · 8 RuleInteraction | C193: 22/30 pairs done. 8 contextual/nullified pending in CALC_RuleInteractionEngine.
A194: · | B194: Why not xlwings? | C194: Mac: AppleScript + running Excel + COM. ~200MB, crashes on large workbooks. Shell macro is simpler, zero deps.
A195: · | B195: Batch 50+ charts | C195: python3 batch_charts.py charts.csv -- ~1 chart/second. Full script in NOTES_VBAMacro.

Sheet INPUT_BirthData
A1: INPUT_BirthData — Manual Entry + Formula Sheet | L1: =HYPERLINK("#'00_INDEX'!A1","<- Index") -> <- Index
A2: Blue cells = enter manually. Black cells = auto-calculated. Do NOT edit black cells — they contain formulas.
A4: Section A — Core birth data (enter these 5 cells)
A5: Date of birth | B5: 17394 | C5: ← Enter | D5: Format: enter as DD/MM/YYYY. Cell format → Date
A6: Time of birth (local) | B6: 0 | C6: ← Enter | D6: Enter as HH:MM e.g. 08:30 — Cell format → Time (HH:MM)
A7: City of birth | B7: New Delhi | C7: ← Enter | D7: e.g. Mumbai, Delhi, Chennai
A8: Country of birth | B8: India | C8: ← Enter | D8: e.g. India
A9: UTC offset (hours) | B9: 5.5 | C9: ← Enter | D9: +5.5 = IST. Pre-1947 Mumbai = +4.85, Calcutta = +5.88, Madras = +5.35
A10: Ayanamsha system | B10: Lahiri | C10: ← Enter | D10: Lahiri = recommended for Vedic. Raman = alternative. KP = Krishnamurti
A11: Time confidence | B11: Exact | C11: ← Enter | D11: Exact / ±15min / ±1hr / Unknown — affects reliability of Lagna
A13: Section B — Location coordinates (look up from Google Maps or geocoder)
A14: Latitude | B14: 28.6139 | C14: ← Enter | D14: Degrees North. Mumbai = 18.9750. Delhi = 28.6139. Chennai = 13.0827
A15: Longitude | B15: 77.209 | C15: ← Enter | D15: Degrees East. Mumbai = 72.8258. Delhi = 77.2090. Chennai = 80.2707
A17: Section C — Auto-calculated from Sections A + B
A18: UTC birth date-time | B18: =IFERROR(IF(B5="← Enter","← Enter date first",TEXT(B5+IF(B6="← Enter",0,TIMEVALUE(TEXT(B6,"HH:MM")))-B9/24,"DD-MMM-YYYY HH:MM")),"Check date format") -> 14-Aug-1947 18:30 | C18: AUTO | D18: Date + local time − UTC offset. This is what ephemeris tools use.
A19: Julian Day Number (JDN) | B19: =IFERROR(IF(B5="← Enter","← Enter date",INT(365.25*(IF(MONTH(B5)<=2,YEAR(B5)-1,YEAR(B5))+4716))+INT(30.6001*(IF(MONTH(B5)<=2,MONTH(B5)+13,MONTH(B5)+1)))+DAY(B5)-1524.5),"—") -> 2432425.5 | C19: AUTO | D19: Continuous count from 1 Jan 4713 BC noon. Input format for Swiss Ephemeris.
A20: Ayanamsha value at birth | B20: 23.125451 | C20: AUTO | D20: Linear approx — accurate to ±0.05°. Use API for exact value.
A21: Chart Confidence | B21: =IFERROR(IF(AND(B11="Exact",COUNTIF(CALC_PlanetLongitudes!$H$7:$H$16,"<>")=0),"GREEN - High confidence",IF(OR(B11="Unknown",COUNTIF(CALC_PlanetLongitudes!$H$7:$H$16,"<>")>=3),"RED - Low confidence","AMBER - Verify boundary planets")),"—") -> RED - Low confidence | C21: =IFERROR(IF(E24="API","← API (ephemeris API ±0.0001°)","← Manual entry"),"← Manual entry") -> ← Manual entry | D21: GREEN = Exact time + no boundary planets. AMBER = minor uncertainty. RED = Unknown time or 3+ boundary planets.
A22: 🔄 Refresh chart | B22: Run: python3 swiss_eph_engine.py -- same folder, Terminal. See NOTES_VBAMacro for VBA button. | C22: Terminal / VBA macro | D22: Replaces localhost:5050. Swiss Ephemeris writes +-0.001 deg directly. VBA: Alt+F11 -> paste Sub from NOTES_VBAMacro -> assign to B22.
A23: Server: python3 ephemeris API_lagna_v3.py --server │ One-shot: python3 ephemeris API_lagna_v3.py --gochar │ Credentials: python3 ephemeris API_lagna_v3.py --save-credentials
A24: Moon total longitude (0°–360°) | B24: =IFERROR((MATCH(INPUT_Chart!$C$7,{"Aries","Taurus","Gemini","Cancer","Leo","Virgo","Libra","Scorpio","Sagittarius","Capricorn","Aquarius","Pisces"},0)-1)*30+INPUT_Chart!$D$7,0) -> 93.9835 | C24: AUTO from INPUT_Chart | D24: Enter from your chart tool. e.g. Moon at 15° Taurus = 30+15 = 45.0000° | E24: SwissEph
A25: Moon Nakshatra | B25: =IFERROR(INDEX(REF_Nakshatra!$B$6:$B$32,MATCH((MATCH(INPUT_Chart!$C$7,{"Aries","Taurus","Gemini","Cancer","Leo","Virgo","Libra","Scorpio","Sagittarius","Capricorn","Aquarius","Pisces"},0)-1)*30+INPUT_Chart!$D$7,REF_Nakshatra!$H$6:$H$32,1)),"Enter Moon sign+degree in INPUT_Chart") -> Pushya | C25: AUTO | D25: Derived from Moon longitude. Each Nakshatra = 13°20' = 13.3333° | E25: 17-Mar-2026 19:18:26
A26: Moon Nakshatra Pada | B26: =IFERROR(MIN(4,INT(((MATCH(INPUT_Chart!$C$7,{"Aries","Taurus","Gemini","Cancer","Leo","Virgo","Libra","Scorpio","Sagittarius","Capricorn","Aquarius","Pisces"},0)-1)*30+INPUT_Chart!$D$7-INDEX(REF_Nakshatra!$H$6:$H$32,MATCH((MATCH(INPUT_Chart!$C$7,{"Aries","Taurus","Gemini","Cancer","Leo","Virgo","Libra","Scorpio","Sagittarius","Capricorn","Aquarius","Pisces"},0)-1)*30+INPUT_Chart!$D$7,REF_Nakshatra!$H$6:$H$32,1)))/(40/12))+1),"Enter Moon sign+degree in INPUT_Chart") -> 1 | C26: AUTO | D26: Pada 1–4 within the Nakshatra (each = 3°20'). Maps to Navamsha sign.
A27: Sunrise UTC (for Tribhaga) | B27: =IFERROR(_xludf.let(moon_lon,B24,nak_pos,MOD(moon_lon,(40/3)),pada_pos,MOD(nak_pos,(40/12)),IF(OR(pada_pos<0.5,(40/12)-pada_pos<0.5),"⚠ VERIFY: Moon within 0.5° of pada boundary (ephemeris formulae ±0.3° risk)","✓ Moon pada clear of boundary")),"Enter Moon position") -> Enter Moon position | C27: Written by ephemeris API_lagna_v4.py | D27: Written by ephemeris API_lagna_v4.py via panchang API. Used by CALC_Shadbala Tribhaga Bala (col H) to replace HOUR() approximation. RESOLVES Issue #14 when v4 script has been run.
A28: Nakshatra fraction remaining | B28: =IFERROR(ROUND(1-((MATCH(INPUT_Chart!$C$7,{"Aries","Taurus","Gemini","Cancer","Leo","Virgo","Libra","Scorpio","Sagittarius","Capricorn","Aquarius","Pisces"},0)-1)*30+INPUT_Chart!$D$7-INDEX(REF_Nakshatra!$H$6:$H$32,MATCH((MATCH(INPUT_Chart!$C$7,{"Aries","Taurus","Gemini","Cancer","Leo","Virgo","Libra","Scorpio","Sagittarius","Capricorn","Aquarius","Pisces"},0)-1)*30+INPUT_Chart!$D$7,REF_Nakshatra!$H$6:$H$32,1)))/(40/3),4),"—") -> 0.9512 | D28: e.g. 0.5000 = Moon is halfway through its Nakshatra at birth → 50% of first Dasha remains
A29: Starting Dasha duration (years) | B29: =IFERROR(INDEX(REF_Nakshatra!$M$6:$M$32,MATCH((MATCH(INPUT_Chart!$C$7,{"Aries","Taurus","Gemini","Cancer","Leo","Virgo","Libra","Scorpio","Sagittarius","Capricorn","Aquarius","Pisces"},0)-1)*30+INPUT_Chart!$D$7,REF_Nakshatra!$H$6:$H$32,1)),"—") -> 19 | D29: Total years in the starting Mahadasha (e.g. Moon = 10, Venus = 20)
A30: Years remaining at birth | B30: =IFERROR(ROUND(B28*B29,2),"—") -> 18.07 | D30: How many years of the first Dasha are left from birth date forward
A31: Dasha starting planet | B31: =IFERROR(INDEX(REF_Nakshatra!$L$6:$L$32,MATCH($B$25,REF_Nakshatra!$B$6:$B$32,0)),"—") -> Saturn | C31: AUTO from B25 | D31: Nakshatra lord → Vimshottari Dasha start planet
A32: Section E — Vimshottari Dasha timeline (from birth date)
A33: Mahadasha planet | B33: Start date | C33: End date | D33: Years
A34: =IFERROR(INDEX({"Ketu","Venus","Sun","Moon","Mars","Rahu","Jupiter","Saturn","Mercury"},MOD(MATCH(B$31,{"Ketu","Venus","Sun","Moon","Mars","Rahu","Jupiter","Saturn","Mercury"},0)-1+0,9)+1),"—") -> Saturn | B34: =IFERROR(IF(ISNUMBER(B5),B5,DATEVALUE(TEXT(B5,"DD/MM/YYYY"))),"—") -> 17394 | C34: =IFERROR(B34+D34*365.25,"—") -> 23994.068 | D34: =IFERROR(B30,"—") -> 18.07
A35: =IFERROR(INDEX({"Ketu","Venus","Sun","Moon","Mars","Rahu","Jupiter","Saturn","Mercury"},MOD(MATCH(B$31,{"Ketu","Venus","Sun","Moon","Mars","Rahu","Jupiter","Saturn","Mercury"},0)-1+1,9)+1),"—") -> Mercury | B35: =IFERROR(C34,"—") -> 23994.068 | C35: =IFERROR(B35+D35*365.25,"—") -> 30203.318 | D35: =IFERROR(INDEX({7,20,6,10,7,18,16,19,17},MATCH(A35,{"Ketu","Venus","Sun","Moon","Mars","Rahu","Jupiter","Saturn","Mercury"},0)),"—") -> 17
A36: =IFERROR(INDEX({"Ketu","Venus","Sun","Moon","Mars","Rahu","Jupiter","Saturn","Mercury"},MOD(MATCH(B$31,{"Ketu","Venus","Sun","Moon","Mars","Rahu","Jupiter","Saturn","Mercury"},0)-1+2,9)+1),"—") -> Ketu | B36: =IFERROR(C35,"—") -> 30203.318 | C36: =IFERROR(B36+D36*365.25,"—") -> 32760.068 | D36: =IFERROR(INDEX({7,20,6,10,7,18,16,19,17},MATCH(A36,{"Ketu","Venus","Sun","Moon","Mars","Rahu","Jupiter","Saturn","Mercury"},0)),"—") -> 7
A37: =IFERROR(INDEX({"Ketu","Venus","Sun","Moon","Mars","Rahu","Jupiter","Saturn","Mercury"},MOD(MATCH(B$31,{"Ketu","Venus","Sun","Moon","Mars","Rahu","Jupiter","Saturn","Mercury"},0)-1+3,9)+1),"—") -> Venus | B37: =IFERROR(C36,"—") -> 32760.068 | C37: =IFERROR(B37+D37*365.25,"—") -> 40065.068 | D37: =IFERROR(INDEX({7,20,6,10,7,18,16,19,17},MATCH(A37,{"Ketu","Venus","Sun","Moon","Mars","Rahu","Jupiter","Saturn","Mercury"},0)),"—") -> 20
A38: =IFERROR(INDEX({"Ketu","Venus","Sun","Moon","Mars","Rahu","Jupiter","Saturn","Mercury"},MOD(MATCH(B$31,{"Ketu","Venus","Sun","Moon","Mars","Rahu","Jupiter","Saturn","Mercury"},0)-1+4,9)+1),"—") -> Sun | B38: =IFERROR(C37,"—") -> 40065.068 | C38: =IFERROR(B38+D38*365.25,"—") -> 42256.568 | D38: =IFERROR(INDEX({7,20,6,10,7,18,16,19,17},MATCH(A38,{"Ketu","Venus","Sun","Moon","Mars","Rahu","Jupiter","Saturn","Mercury"},0)),"—") -> 6
A39: =IFERROR(INDEX({"Ketu","Venus","Sun","Moon","Mars","Rahu","Jupiter","Saturn","Mercury"},MOD(MATCH(B$31,{"Ketu","Venus","Sun","Moon","Mars","Rahu","Jupiter","Saturn","Mercury"},0)-1+5,9)+1),"—") -> Moon | B39: =IFERROR(C38,"—") -> 42256.568 | C39: =IFERROR(B39+D39*365.25,"—") -> 45909.068 | D39: =IFERROR(INDEX({7,20,6,10,7,18,16,19,17},MATCH(A39,{"Ketu","Venus","Sun","Moon","Mars","Rahu","Jupiter","Saturn","Mercury"},0)),"—") -> 10
A40: =IFERROR(INDEX({"Ketu","Venus","Sun","Moon","Mars","Rahu","Jupiter","Saturn","Mercury"},MOD(MATCH(B$31,{"Ketu","Venus","Sun","Moon","Mars","Rahu","Jupiter","Saturn","Mercury"},0)-1+6,9)+1),"—") -> Mars | B40: =IFERROR(C39,"—") -> 45909.068 | C40: =IFERROR(B40+D40*365.25,"—") -> 48465.818 | D40: =IFERROR(INDEX({7,20,6,10,7,18,16,19,17},MATCH(A40,{"Ketu","Venus","Sun","Moon","Mars","Rahu","Jupiter","Saturn","Mercury"},0)),"—") -> 7
A41: =IFERROR(INDEX({"Ketu","Venus","Sun","Moon","Mars","Rahu","Jupiter","Saturn","Mercury"},MOD(MATCH(B$31,{"Ketu","Venus","Sun","Moon","Mars","Rahu","Jupiter","Saturn","Mercury"},0)-1+7,9)+1),"—") -> Rahu | B41: =IFERROR(C40,"—") -> 48465.818 | C41: =IFERROR(B41+D41*365.25,"—") -> 55040.318 | D41: =IFERROR(INDEX({7,20,6,10,7,18,16,19,17},MATCH(A41,{"Ketu","Venus","Sun","Moon","Mars","Rahu","Jupiter","Saturn","Mercury"},0)),"—") -> 18
A42: =IFERROR(INDEX({"Ketu","Venus","Sun","Moon","Mars","Rahu","Jupiter","Saturn","Mercury"},MOD(MATCH(B$31,{"Ketu","Venus","Sun","Moon","Mars","Rahu","Jupiter","Saturn","Mercury"},0)-1+8,9)+1),"—") -> Jupiter | B42: =IFERROR(C41,"—") -> 55040.318 | C42: =IFERROR(B42+D42*365.25,"—") -> 60884.318 | D42: =IFERROR(INDEX({7,20,6,10,7,18,16,19,17},MATCH(A42,{"Ketu","Venus","Sun","Moon","Mars","Rahu","Jupiter","Saturn","Mercury"},0)),"—") -> 16
A47: Section F — Computed Planet Positions (from CALC_PlanetLongitudes)
A48: Planet signs and degrees auto-computed below. ⚠ = near sign boundary (±3°), verify manually.
A49: Lagna | B49: =IFERROR(CALC_PlanetLongitudes!$E$7,"—") -> Taurus | C49: =IFERROR(ROUND(CALC_PlanetLongitudes!$F$7,1),0) -> 7.7 | D49: =IFERROR(CALC_PlanetLongitudes!$H$7,"·") -> · | E49: =IFERROR(CALC_PlanetLongitudes!$I$7,"") -> Ascendant from GMST + longitude + latitude. Requires accurate birth TIME. Error <0.5° with exact time; each 4 minutes = 1° error.
A50: Sun | B50: =IFERROR(CALC_PlanetLongitudes!$E$8,"—") -> Cancer | C50: =IFERROR(ROUND(CALC_PlanetLongitudes!$F$8,1),0) -> 28 | D50: =IFERROR(CALC_PlanetLongitudes!$H$8,"·") -> · | E50: =IFERROR(CALC_PlanetLongitudes!$I$8,"") -> Meeus Ch.25. Accuracy ±0.01°. Equation of centre (2 terms). Very reliable.
A51: Moon | B51: =IFERROR(CALC_PlanetLongitudes!$E$9,"—") -> Cancer | C51: =IFERROR(ROUND(CALC_PlanetLongitudes!$F$9,1),0) -> 4 | D51: =IFERROR(CALC_PlanetLongitudes!$H$9,"·") -> · | E51: =IFERROR(CALC_PlanetLongitudes!$I$9,"") -> Meeus Ch.47 (abridged, 12 terms). Accuracy ±0.3°. Moon moves ~13°/day — time accuracy critical.
A52: Mars | B52: =IFERROR(CALC_PlanetLongitudes!$E$10,"—") -> Gemini | C52: =IFERROR(ROUND(CALC_PlanetLongitudes!$F$10,1),0) -> 7.5 | D52: =IFERROR(CALC_PlanetLongitudes!$H$10,"·") -> · | E52: =IFERROR(CALC_PlanetLongitudes!$I$10,"") -> Meeus Ch.33 (5 terms + Jupiter perturbation). Accuracy ±1°.
A53: Mercury | B53: =IFERROR(CALC_PlanetLongitudes!$E$11,"—") -> Cancer | C53: =IFERROR(ROUND(CALC_PlanetLongitudes!$F$11,1),0) -> 13.7 | D53: =IFERROR(CALC_PlanetLongitudes!$H$11,"·") -> · | E53: =IFERROR(CALC_PlanetLongitudes!$I$11,"") -> Meeus Ch.33 (6 terms + Venus perturbation). Accuracy ±2°. Verify if ⚠ near boundary.
A54: Jupiter | B54: =IFERROR(CALC_PlanetLongitudes!$E$12,"—") -> Libra | C54: =IFERROR(ROUND(CALC_PlanetLongitudes!$F$12,1),0) -> 25.9 | D54: =IFERROR(CALC_PlanetLongitudes!$H$12,"·") -> · | E54: =IFERROR(CALC_PlanetLongitudes!$I$12,"") -> Meeus Ch.33 (4 terms + Saturn perturbation). Accuracy ±0.5°.
A55: Venus | B55: =IFERROR(CALC_PlanetLongitudes!$E$13,"—") -> Cancer | C55: =IFERROR(ROUND(CALC_PlanetLongitudes!$F$13,1),0) -> 22.6 | D55: =IFERROR(CALC_PlanetLongitudes!$H$13,"·") -> · | E55: =IFERROR(CALC_PlanetLongitudes!$I$13,"") -> Meeus Ch.33 (4 terms + Mercury perturbation). Accuracy ±2°. Verify if ⚠ near boundary.
A56: Saturn | B56: =IFERROR(CALC_PlanetLongitudes!$E$14,"—") -> Cancer | C56: =IFERROR(ROUND(CALC_PlanetLongitudes!$F$14,1),0) -> 20.5 | D56: =IFERROR(CALC_PlanetLongitudes!$H$14,"·") -> · | E56: =IFERROR(CALC_PlanetLongitudes!$I$14,"") -> Meeus Ch.33 (5 terms + Jupiter perturbation). Accuracy ±0.5°.
A57: Rahu | B57: =IFERROR(CALC_PlanetLongitudes!$E$15,"—") -> Taurus | C57: =IFERROR(ROUND(CALC_PlanetLongitudes!$F$15,1),0) -> 5.1 | D57: =IFERROR(CALC_PlanetLongitudes!$H$15,"·") -> · | E57: =IFERROR(CALC_PlanetLongitudes!$I$15,"") -> Mean node + 4 correction terms. True node ±0.5°. Always retrograde (counter-clockwise).
A58: Ketu | B58: =IFERROR(CALC_PlanetLongitudes!$E$16,"—") -> Scorpio | C58: =IFERROR(ROUND(CALC_PlanetLongitudes!$F$16,1),0) -> 5.1 | D58: =IFERROR(CALC_PlanetLongitudes!$H$16,"·") -> · | E58: =IFERROR(CALC_PlanetLongitudes!$I$16,"") -> Always exactly opposite Rahu (South Node = Rahu + 180°).

Sheet INPUT_Chart
A1: INPUT_Chart · Planet Positions · AUTO from CALC_PlanetLongitudes | L1: =HYPERLINK("#'00_INDEX'!A1","<- Index") -> <- Index
A2: ⬇ Enter birth data in INPUT_BirthData — planet positions auto-fill here. ✎ You can override any Sign or Degree cell manually — type directly into col C or D and your value takes precedence. Blue cells = designed for manual entry.
A3: =IFERROR(IF(COUNTIF(CALC_PlanetLongitudes!$H$7:$H$16,"<>")>0,"BOUNDARY ALERT: "&COUNTIF(CALC_PlanetLongitudes!$H$7:$H$16,"<>")&" planet(s) near sign boundary - verify with third-party software",""),"") -> BOUNDARY ALERT: 10 planet(s) near sign boundary - verify with third-party software
A4: Planet / Point | B4: Valid Signs | C4: Sign Placed | D4: Degree (0-29) | E4: Sanskrit Name | F4: Notes
A5: Lagna (Ascendant) | B5: Aries,Taurus,Gemini,Cancer,Leo,Virgo,Libra,Scorpio,Sagittarius,Capricorn,Aquarius,Pisces | C5: =IFERROR(CALC_PlanetLongitudes!$E$7,"—") -> Taurus | D5: =IFERROR(CALC_PlanetLongitudes!$F$7,"—") -> 7.7286 | E5: Mesh | F5: Rising sign — most important input
A6: Sun / Surya | B6: Aries,Taurus,Gemini,Cancer,Leo,Virgo,Libra,Scorpio,Sagittarius,Capricorn,Aquarius,Pisces | C6: =IFERROR(CALC_PlanetLongitudes!$E$8,"—") -> Cancer | D6: =IFERROR(CALC_PlanetLongitudes!$F$8,"—") -> 27.989 | E6: Surya | F6: Soul, father, authority
A7: Moon / Chandramaa | B7: Aries,Taurus,Gemini,Cancer,Leo,Virgo,Libra,Scorpio,Sagittarius,Capricorn,Aquarius,Pisces | C7: =IFERROR(CALC_PlanetLongitudes!$E$9,"—") -> Cancer | D7: =IFERROR(CALC_PlanetLongitudes!$F$9,"—") -> 3.9835 | E7: Chandramaa | F7: Mind, mother, emotions
A8: Mars / Mangal | B8: Aries,Taurus,Gemini,Cancer,Leo,Virgo,Libra,Scorpio,Sagittarius,Capricorn,Aquarius,Pisces | C8: =IFERROR(CALC_PlanetLongitudes!$E$10,"—") -> Gemini | D8: =IFERROR(CALC_PlanetLongitudes!$F$10,"—") -> 7.4562 | E8: Mangal | F8: Energy, siblings, courage
A9: Mercury / Budh | B9: Aries,Taurus,Gemini,Cancer,Leo,Virgo,Libra,Scorpio,Sagittarius,Capricorn,Aquarius,Pisces | C9: =IFERROR(CALC_PlanetLongitudes!$E$11,"—") -> Cancer | D9: =IFERROR(CALC_PlanetLongitudes!$F$11,"—") -> 13.6743 | E9: Budh | F9: Intellect, communication
A10: Jupiter / Brihaspati | B10: Aries,Taurus,Gemini,Cancer,Leo,Virgo,Libra,Scorpio,Sagittarius,Capricorn,Aquarius,Pisces | C10: =IFERROR(CALC_PlanetLongitudes!$E$12,"—") -> Libra | D10: =IFERROR(CALC_PlanetLongitudes!$F$12,"—") -> 25.8777 | E10: Brihaspati | F10: Wisdom, children, fortune
A11: Venus / Shukra | B11: Aries,Taurus,Gemini,Cancer,Leo,Virgo,Libra,Scorpio,Sagittarius,Capricorn,Aquarius,Pisces | C11: =IFERROR(CALC_PlanetLongitudes!$E$13,"—") -> Cancer | D11: =IFERROR(CALC_PlanetLongitudes!$F$13,"—") -> 22.5612 | E11: Shukra | F11: Love, luxury, relationships
A12: Saturn / Shani | B12: Aries,Taurus,Gemini,Cancer,Leo,Virgo,Libra,Scorpio,Sagittarius,Capricorn,Aquarius,Pisces | C12: =IFERROR(CALC_PlanetLongitudes!$E$14,"—") -> Cancer | D12: =IFERROR(CALC_PlanetLongitudes!$F$14,"—") -> 20.473 | E12: Shani | F12: Discipline, karma, longevity
A13: Rahu (N. Node) | B13: Aries,Taurus,Gemini,Cancer,Leo,Virgo,Libra,Scorpio,Sagittarius,Capricorn,Aquarius,Pisces | C13: =IFERROR(CALC_PlanetLongitudes!$E$15,"—") -> Taurus | D13: =IFERROR(CALC_PlanetLongitudes!$F$15,"—") -> 5.0697 | E13: Rahu | F13: Obsession, amplifier — no own sign
A14: Ketu (S. Node) | B14: Aries,Taurus,Gemini,Cancer,Leo,Virgo,Libra,Scorpio,Sagittarius,Capricorn,Aquarius,Pisces | C14: =IFERROR(CALC_PlanetLongitudes!$E$16,"—") -> Scorpio | D14: =IFERROR(CALC_PlanetLongitudes!$F$16,"—") -> 5.0697 | E14: Ketu | F14: Detachment — always 7 signs from Rahu
A16: Moon longitude (for Dasha) | B16: Auto-reads sign+degree from row 7 above | C16: =IFERROR("≈ "&TEXT((MATCH(C7,{"Aries","Taurus","Gemini","Cancer","Leo","Virgo","Libra","Scorpio","Sagittarius","Capricorn","Aquarius","Pisces"},0)-1)*30+D7,"0.00")&"° abs","Enter Moon sign+degree above") -> ≈ 93.98° abs | D16: Used in INPUT_BirthData Dasha calc | E16: Chandramaa | F16: Auto-computed from Moon row — no extra entry needed
A17: REFERENCE: Shubh (Benefic) and Ashubh (Malefic) planets change based on Lagna — see REF_ShubhAshubh sheet

Sheet INPUT_Gochar
A1: INPUT_Gochar · Today's Transit Positions · Enter for Gochar overlay | L1: =HYPERLINK("#'00_INDEX'!A1","<- Index") -> <- Index
A2: Enter today's sidereal (Lahiri) planet positions for transit analysis. Source: reference software > Today's Panchang, ephemeris API, or ephemeris API API. Signs must match INPUT_Chart sign names exactly.
A3: Planet | B3: Transit Sign | C3: Degree | D3: Notes — transit speed
A4: Sun | B4: Pisces | C4: 2.4176 | D4: ~30 days per sign
A5: Moon | B5: Aquarius | C5: 9.365 | D5: ~2.25 days per sign — fastest
A6: Mars | B6: Aquarius | C6: 17.3107 | D6: ~6 weeks per sign; Rx ~2 months
A7: Mercury | B7: Aquarius | C7: 14.9219 | D7: ~3–4 weeks; retrograde 3× per year
A8: Jupiter | B8: Gemini | C8: 20.9244 | D8: ~1 year per sign — major timing
A9: Venus | B9: Pisces | C9: 19.179 | D9: ~3–4 weeks; Rx every 18 months
A10: Saturn | B10: Pisces | C10: 9.484 | D10: ~2.5 years per sign — most impactful
A11: Rahu | B11: Aquarius | C11: 13.9637 | D11: ~18 months per sign (always retrograde)
A12: Ketu | B12: Leo | C12: 13.9637 | D12: Always 7 signs from Rahu
A14: Analysis date | B14: =TODAY() -> 46100
B15: 17-Mar-2026 11:14

Sheet INPUT_Chart_Scenario
A1: INPUT_Chart_Scenario · What-If Chart · Change any planet position to model alternative placements | L1: =HYPERLINK("#'00_INDEX'!A1","<- Index") -> <- Index
A2: ⚡ SCENARIO MODE: Change any Sign or Degree below. Activate scenario scoring via REF_Config toggle (Scenario mode = row 18). All SCORE_H sheets with scenario formulas will re-run from this chart.
A3: =IFERROR(IF(COUNTIF(CALC_PlanetLongitudes!$H$7:$H$16,"<>")>0,"BOUNDARY ALERT: "&COUNTIF(CALC_PlanetLongitudes!$H$7:$H$16,"<>")&" planet(s) near sign boundary - verify with third-party software",""),"") -> BOUNDARY ALERT: 10 planet(s) near sign boundary - verify with third-party software
A4: Planet / Point | B4: Valid Signs | C4: Sign Placed | D4: Degree (0-29) | E4: Sanskrit Name | F4: Notes
A5: Lagna (Ascendant) | B5: Aries,Taurus,Gemini,Cancer,Leo,Virgo,Libra,Scorpio,Sagittarius,Capricorn,Aquarius,Pisces | C5: =INPUT_Chart!C5 -> Taurus | D5: =INPUT_Chart!D5 -> 7.7286 | E5: Mesh | F5: Rising sign — most important input
A6: Sun / Surya | B6: Aries,Taurus,Gemini,Cancer,Leo,Virgo,Libra,Scorpio,Sagittarius,Capricorn,Aquarius,Pisces | C6: =INPUT_Chart!C6 -> Cancer | D6: =INPUT_Chart!D6 -> 27.989 | E6: Surya | F6: Soul, father, authority
A7: Moon / Chandramaa | B7: Aries,Taurus,Gemini,Cancer,Leo,Virgo,Libra,Scorpio,Sagittarius,Capricorn,Aquarius,Pisces | C7: =INPUT_Chart!C7 -> Cancer | D7: =INPUT_Chart!D7 -> 3.9835 | E7: Chandramaa | F7: Mind, mother, emotions
A8: Mars / Mangal | B8: Aries,Taurus,Gemini,Cancer,Leo,Virgo,Libra,Scorpio,Sagittarius,Capricorn,Aquarius,Pisces | C8: =INPUT_Chart!C8 -> Gemini | D8: =INPUT_Chart!D8 -> 7.4562 | E8: Mangal | F8: Energy, siblings, courage
A9: Mercury / Budh | B9: Aries,Taurus,Gemini,Cancer,Leo,Virgo,Libra,Scorpio,Sagittarius,Capricorn,Aquarius,Pisces | C9: =INPUT_Chart!C9 -> Cancer | D9: =INPUT_Chart!D9 -> 13.6743 | E9: Budh | F9: Intellect, communication
A10: Jupiter / Brihaspati | B10: Aries,Taurus,Gemini,Cancer,Leo,Virgo,Libra,Scorpio,Sagittarius,Capricorn,Aquarius,Pisces | C10: =INPUT_Chart!C10 -> Libra | D10: =INPUT_Chart!D10 -> 25.8777 | E10: Brihaspati | F10: Wisdom, children, fortune
A11: Venus / Shukra | B11: Aries,Taurus,Gemini,Cancer,Leo,Virgo,Libra,Scorpio,Sagittarius,Capricorn,Aquarius,Pisces | C11: =INPUT_Chart!C11 -> Cancer | D11: =INPUT_Chart!D11 -> 22.5612 | E11: Shukra | F11: Love, luxury, relationships
A12: Saturn / Shani | B12: Aries,Taurus,Gemini,Cancer,Leo,Virgo,Libra,Scorpio,Sagittarius,Capricorn,Aquarius,Pisces | C12: =INPUT_Chart!C12 -> Cancer | D12: =INPUT_Chart!D12 -> 20.473 | E12: Shani | F12: Discipline, karma, longevity
A13: Rahu (N. Node) | B13: Aries,Taurus,Gemini,Cancer,Leo,Virgo,Libra,Scorpio,Sagittarius,Capricorn,Aquarius,Pisces | C13: =INPUT_Chart!C13 -> Taurus | D13: =INPUT_Chart!D13 -> 5.0697 | E13: Rahu | F13: Obsession, amplifier — no own sign
A14: Ketu (S. Node) | B14: Aries,Taurus,Gemini,Cancer,Leo,Virgo,Libra,Scorpio,Sagittarius,Capricorn,Aquarius,Pisces | C14: =INPUT_Chart!C14 -> Scorpio | D14: =INPUT_Chart!D14 -> 5.0697 | E14: Ketu | F14: Detachment — always 7 signs from Rahu
A16: Moon longitude (for Dasha) | B16: Auto-reads sign+degree from row 7 above | C16: =IFERROR("≈ "&TEXT((MATCH(C7,{"Aries","Taurus","Gemini","Cancer","Leo","Virgo","Libra","Scorpio","Sagittarius","Capricorn","Aquarius","Pisces"},0)-1)*30+D7,"0.00")&"° abs","Enter Moon sign+degree above") -> ≈ 93.98° abs | D16: Used in INPUT_BirthData Dasha calc | E16: Chandramaa | F16: Auto-computed from Moon row — no extra entry needed
A17: REFERENCE: Shubh (Benefic) and Ashubh (Malefic) planets change based on Lagna — see REF_ShubhAshubh sheet

Sheet REF_Zodiac
A1: REF_Zodiac — Complete Jyotish Zodiac Reference · Sources: BPHS, Saravali, Phaladeepika | Q1: =HYPERLINK("#'00_INDEX'!A1","<- Index") -> <- Index
A2: READ-ONLY reference table — never edit directly. All CALC_ sheets look up values here via INDEX/MATCH on the sign name. Blue = scoring flags used by SCORE_AllHouses.
A3: Group | B3: Attribute | C3: Sanskrit | D3: Aries | E3: Taurus | F3: Gemini | G3: Cancer | H3: Leo | I3: Virgo | J3: Libra | K3: Scorpio | L3: Sagittarius | M3: Capricorn | N3: Aquarius | O3: Pisces
A4: Identity | B4: Sanskrit / Rashi | C4: Rashi | D4: Mesh | E4: Vrishabh | F4: Mithun | G4: Kark | H4: Simh | I4: Kanya | J4: Tula | K4: Vrishchik | L4: Dhanu | M4: Makar | N4: Kumbh | O4: Meen
B5: Sign number | C5: Rashi Krama | D5: 1 | E5: 2 | F5: 3 | G5: 4 | H5: 5 | I5: 6 | J5: 7 | K5: 8 | L5: 9 | M5: 10 | N5: 11 | O5: 12
B6: Symbol | C6: Pratik | D6: Ram | E6: Bull | F6: Twins | G6: Crab | H6: Lion | I6: Virgin | J6: Scales | K6: Scorpion | L6: Archer | M6: Sea-goat | N6: Water-bearer | O6: Fish
A7: Lordship | B7: Ruling planet | C7: Swami / Adhipati | D7: Mars | E7: Venus | F7: Mercury | G7: Moon | H7: Sun | I7: Mercury | J7: Venus | K7: Mars | L7: Jupiter | M7: Saturn | N7: Saturn | O7: Jupiter
B8: Ruling planet (Skt) | C8: Graha Swami | D8: Mangal | E8: Shukra | F8: Budh | G8: Chandramaa | H8: Surya | I8: Budh | J8: Shukra | K8: Mangal | L8: Brihaspati | M8: Shani | N8: Shani | O8: Brihaspati
B9: Exaltation planet | C9: Uchcha Graha | D9: Sun | E9: Moon | F9: — | G9: Jupiter | H9: — | I9: Mercury | J9: Saturn | K9: — | L9: — | M9: Mars | N9: — | O9: Venus
B10: Exaltation degree | C10: Uchcha Amsha | D10: 10° | E10: 3° | F10: — | G10: 5° | H10: — | I10: 15° | J10: 20° | K10: — | L10: — | M10: 28° | N10: — | O10: 27°
B11: Debilitation planet | C11: Neecha Graha | D11: Saturn | E11: — | F11: — | G11: Mars | H11: — | I11: Venus | J11: Sun | K11: — | L11: — | M11: Jupiter | N11: — | O11: Mercury
B12: Mooltrikona sign of | C12: Mooltrikona | D12: Mars (0–18°) | E12: Venus (0–15°) | F12: Mercury (0–15°) | G12: — | H12: Sun (0–20°) | I12: Mercury (16–20°) | J12: Saturn (0–20°) | K12: — | L12: Jupiter (0–10°) | M12: — | N12: — | O12: —
A13: Nature | B13: Element / Tattva | C13: Tattva | D13: Fire | E13: Earth | F13: Air | G13: Water | H13: Fire | I13: Earth | J13: Air | K13: Water | L13: Fire | M13: Earth | N13: Air | O13: Water
B14: Modality | C14: Chara/Sthir/Dwi | D14: Movable / Char | E14: Fixed / Sthir | F14: Dual / Dwiswabhav | G14: Movable / Char | H14: Fixed / Sthir | I14: Dual / Dwiswabhav | J14: Movable / Char | K14: Fixed / Sthir | L14: Dual / Dwiswabhav | M14: Movable / Char | N14: Fixed / Sthir | O14: Dual / Dwiswabhav
B15: Gender | C15: Strī/Purusha | D15: Masculine | E15: Feminine | F15: Masculine | G15: Feminine | H15: Masculine | I15: Feminine | J15: Masculine | K15: Feminine | L15: Masculine | M15: Feminine | N15: Masculine | O15: Feminine
B16: Sign type | C16: Rashi Prakriti | D16: Odd / Vishama | E16: Even / Sama | F16: Odd / Vishama | G16: Even / Sama | H16: Odd / Vishama | I16: Even / Sama | J16: Odd / Vishama | K16: Even / Sama | L16: Odd / Vishama | M16: Even / Sama | N16: Odd / Vishama | O16: Even / Sama
A17: Temperament | B17: Temperament | C17: Swabhava | D17: Cruel | E17: Gentle | F17: Gentle | G17: Gentle | H17: Cruel | I17: Gentle | J17: Gentle | K17: Cruel | L17: Gentle | M17: Cruel | N17: Cruel | O17: Gentle
B18: Body type | C18: Deha Prakriti | D18: Biped | E18: Quadruped | F18: Biped | G18: Aquatic | H18: Quadruped | I18: Biped | J18: Biped | K18: Insect / Reptile | L18: Biped (half) / Quadruped (half) | M18: Aquatic / Quadruped | N18: Biped | O18: Aquatic
B19: Fertility | C19: Santan Shakti | D19: Barren | E19: Fruitful | F19: Barren | G19: Fruitful | H19: Barren | I19: Barren | J19: Semi-fruitful | K19: Fruitful | L19: Semi-fruitful | M19: Semi-fruitful | N19: Barren | O19: Fruitful
B20: Voice quality | C20: Vak Bala | D20: Strong voice | E20: Strong voice | F20: Dual voice | G20: Mute / Silent | H20: Strong voice | I20: Dual voice | J20: Dual voice | K20: Mute / Silent | L20: Strong voice | M20: Mute / Silent | N20: Strong voice | O20: Mute / Silent
A21: Dosha / Guna | B21: Ayurvedic dosha | C21: Tridosha | D21: Pitta | E21: Vata / Kapha | F21: Vata / Pitta | G21: Kapha | H21: Pitta / Kapha | I21: Vata / Pitta | J21: Vata / Kapha | K21: Kapha / Pitta | L21: Pitta / Vata | M21: Vata / Kapha | N21: Vata | O21: Kapha
B22: Triguna | C22: Guna | D22: Rajas | E22: Tamas | F22: Rajas | G22: Sattva | H22: Sattva | I22: Tamas | J22: Rajas | K22: Tamas | L22: Sattva | M22: Tamas | N22: Tamas | O22: Sattva
B23: Body substance | C23: Dhatu / Jeev / Mool | D23: Dhatu (minerals) | E23: Dhatu (minerals) | F23: Jeev (living) | G23: Jeev (living) | H23: Jeev (living) | I23: Jeev (living) | J23: Jeev (living) | K23: Jeev (living) | L23: Jeev (living) | M23: Jeev (living) | N23: Dhatu (minerals) | O23: Mool (plants)
A24: Social | B24: Varna (caste) | C24: Varna | D24: Kshatriya | E24: Vaishya | F24: Shudra | G24: Brahmin | H24: Kshatriya | I24: Vaishya | J24: Shudra | K24: Brahmin | L24: Kshatriya | M24: Vaishya | N24: Shudra | O24: Brahmin
A25: Directional | B25: Direction | C25: Disha | D25: East / Purva | E25: South / Dakshina | F25: West / Paschima | G25: North / Uttara | H25: East / Purva | I25: South / Dakshina | J25: West / Paschima | K25: North / Uttara | L25: East / Purva | M25: South / Dakshina | N25: West / Paschima | O25: North / Uttara
A26: Physical | B26: Colour | C26: Rang | D26: Red / Blood red | E26: White / Off-white | F26: Green | G26: Pale / Pinkish | H26: Golden / Wheatish | I26: Multi-coloured / Spotted | J26: Black / Variegated | K26: Brown / Reddish | L26: Yellow / Golden | M26: Variegated / Dark | N26: Blue / Black | O26: Off-white / Sea green
B27: Body part (Kalapurusha) | C27: Kalapurusha Anga | D27: Head / Skull | E27: Face / Neck / Throat | F27: Shoulders / Arms / Hands | G27: Chest / Heart / Lungs | H27: Stomach / Back / Spine | I27: Waist / Lower abdomen / Intestines | J27: Kidneys / Lower back / Navel | K27: Genitals / Rectum / Bladder | L27: Thighs / Hips / Liver | M27: Knees / Joints / Bones | N27: Ankles / Calves / Circulatory system | O27: Feet / Lymphatic system / Immune system
A28: Technical | B28: Rising direction | C28: Udaya Prakar | D28: Shirshodaya (head first) | E28: Prishtodaya (back first) | F28: Shirshodaya | G28: Prishtodaya | H28: Shirshodaya | I28: Shirshodaya | J28: Shirshodaya | K28: Prishtodaya | L28: Shirshodaya | M28: Prishtodaya | N28: Shirshodaya | O28: Ubhayodaya (both ways)
B29: Strength period | C29: Bala Kaal | D29: Night | E29: Day | F29: Night | G29: Night | H29: Day | I29: Day | J29: Day | K29: Night | L29: Day | M29: Night | N29: Day | O29: Night
B30: Seasonal strength | C30: Ritu Bala | D30: Vasanta (Spring) | E30: Grishma (Summer) | F30: Grishma (Summer) | G30: Varsha (Rains) | H30: Varsha (Rains) | I30: Sharad (Autumn) | J30: Sharad (Autumn) | K30: Hemanta (Early winter) | L30: Hemanta (Early winter) | M30: Shishira (Winter) | N30: Shishira (Winter) | O30: Vasanta (Spring)
A31: Classification | B31: Natural house type | C31: Bhav Prakar | D31: Kendra | E31: Dhan / 2nd | F31: Upachaya | G31: Kendra / Sukha | H31: Trikon | I31: Upachaya / Roga | J31: Kendra / Kalatra | K31: Randhra / Ayu | L31: Trikon / Bhagya | M31: Kendra / Karma | N31: Labha | O31: Vyaya
B32: House group | C32: Bhav Varga | D32: Angular | E32: Succedent | F32: Cadent | G32: Angular | H32: Succedent | I32: Cadent | J32: Angular | K32: Succedent | L32: Cadent | M32: Angular | N32: Succedent | O32: Cadent
A33: Technical | B33: Nakshatras spanning | C33: Nakshatra Span | D33: Ashwini, Bharani, Krittika (1) | E33: Krittika (2-4), Rohini, Mrigashira (1-2) | F33: Mrigashira (3-4), Ardra, Punarvasu (1-3) | G33: Punarvasu (4), Pushya, Ashlesha | H33: Magha, Purva Phalguni, Uttara Phalguni (1) | I33: Uttara Phalguni (2-4), Hasta, Chitra (1-2) | J33: Chitra (3-4), Swati, Vishakha (1-3) | K33: Vishakha (4), Anuradha, Jyeshtha | L33: Mula, Purva Ashadha, Uttara Ashadha (1) | M33: Uttara Ashadha (2-4), Shravana, Dhanishtha (1-2) | N33: Dhanishtha (3-4), Shatabhisha, Purva Bhadrapada (1-3) | O33: Purva Bhadrapada (4), Uttara Bhadrapada, Revati
A34: Karakatva | B34: Primary Karak planet | C34: Mukhya Karak | D34: Mars (energy, self) | E34: Venus (beauty, wealth) | F34: Mercury (communication) | G34: Moon (mind, mother) | H34: Sun (soul, authority) | I34: Mercury (analysis, health) | J34: Venus (relationships, balance) | K34: Mars / Saturn (transformation) | L34: Jupiter (dharma, expansion) | M34: Saturn (career, discipline) | N34: Saturn / Rahu (gains, groups) | O34: Jupiter (liberation, isolation)
A35: Scoring flags | B35: Dukshthan (6/8/12)? | C35: Dukh Sthana | D35: No | E35: No | F35: No | G35: No | H35: No | I35: Yes (6th) | J35: No | K35: Yes (8th) | L35: No | M35: No | N35: No | O35: Yes (12th)
B36: Kendra (1/4/7/10)? | C36: Kendra | D36: Yes (1st) | E36: No | F36: No | G36: Yes (4th) | H36: No | I36: No | J36: Yes (7th) | K36: No | L36: No | M36: Yes (10th) | N36: No | O36: No
B37: Trikon (1/5/9)? | C37: Trikon | D37: Yes (1st) | E37: No | F37: No | G37: No | H37: Yes (5th) | I37: No | J37: No | K37: No | L37: Yes (9th) | M37: No | N37: No | O37: No
B38: Upachaya (3/6/10/11)? | C38: Upachaya | D38: No | E38: No | F38: Yes (3rd) | G38: No | H38: No | I38: Yes (6th) | J38: No | K38: No | L38: No | M38: Yes (10th) | N38: Yes (11th) | O38: No
A39: Source: Brihat Parashara Hora Shastra (BPHS) Ch.3-4 · Saravali Ch.2 · Phaladeepika Ch.1 · Cross-checked with Jagannatha Hora software output

Sheet REF_Zodiac_Lookup
A1: REF_Zodiac_Lookup — Formula patterns for CALC_ sheets | L1: =HYPERLINK("#'00_INDEX'!A1","<- Index") -> <- Index
A2: Copy these formula patterns into CALC_PlanetPositions or any sheet that needs to look up a sign's properties. Replace B5 with the cell containing the sign name.
A4: Attribute wanted | B4: Formula to use | C4: Returns | D4: Notes
A5: Element / Tattva | B5: Aries | C5: Fire / Earth / Air / Water | D5: Replace B5 with any cell containing a sign name
A6: Ruling planet | B6: =IFERROR(INDEX(REF_Zodiac!$D$7:$O$7,MATCH(B5,REF_Zodiac!$D$3:$O$3,0)),"") -> Mars | C6: Mars / Venus / Mercury… | D6: Use for Bhavesh (house lord) identification
A7: Modality | B7: =IFERROR(INDEX(REF_Zodiac!$D$14:$O$14,MATCH(B5,REF_Zodiac!$D$3:$O$3,0)),"") -> Movable / Char | C7: Movable / Fixed / Dual | D7: Used in Chara/Sthira Karak assessments
A8: Exaltation planet | B8: =IFERROR(INDEX(REF_Zodiac!$D$9:$O$9,MATCH(B5,REF_Zodiac!$D$3:$O$3,0)),"") -> Sun | C8: Sun / Moon / Mars… | D8: Check if a planet placed here is exalted
A9: Temperament | B9: =IFERROR(INDEX(REF_Zodiac!$D$17:$O$17,MATCH(B5,REF_Zodiac!$D$3:$O$3,0)),"") -> Cruel | C9: Cruel / Gentle | D9: Cruel signs (1/5/8/10/11) reduce benefic effects
A10: Dukshthan? | B10: =IFERROR(INDEX(REF_Zodiac!$D$35:$O$35,MATCH(B5,REF_Zodiac!$D$3:$O$3,0)),"") -> No | C10: Yes (6th) / No | D10: Used in Bhavesh_Durbal Rule #15 check
A11: Kendra? | B11: =IFERROR(INDEX(REF_Zodiac!$D$36:$O$36,MATCH(B5,REF_Zodiac!$D$3:$O$3,0)),"") -> Yes (1st) | C11: Yes (1st) / No | D11: Kendra placement = strong position for Bhavesh_Bal
A12: Trikon? | B12: =IFERROR(INDEX(REF_Zodiac!$D$37:$O$37,MATCH(B5,REF_Zodiac!$D$3:$O$3,0)),"") -> Yes (1st) | C12: Yes (5th) / No | D12: Trikon placement = auspicious. 1/5/9 houses.
A13: Varna | B13: =IFERROR(INDEX(REF_Zodiac!$D$24:$O$24,MATCH(B5,REF_Zodiac!$D$3:$O$3,0)),"") -> Kshatriya | C13: Brahmin / Kshatriya… | D13: Used in Varna compatibility matching
A14: Direction | B14: =IFERROR(INDEX(REF_Zodiac!$D$25:$O$25,MATCH(B5,REF_Zodiac!$D$3:$O$3,0)),"") -> East / Purva | C14: East / South / West / North | D14: Directional strength (Dig Bala) calculations
A15: Body part | B15: =IFERROR(INDEX(REF_Zodiac!$D$27:$O$27,MATCH(B5,REF_Zodiac!$D$3:$O$3,0)),"") -> Head / Skull | C15: Head / Neck / Arms… | D15: Medical astrology — afflictions to this house affect this body part
A16: Nakshatras spanning | B16: =IFERROR(INDEX(REF_Zodiac!$D$33:$O$33,MATCH(B5,REF_Zodiac!$D$3:$O$3,0)),"") -> Ashwini, Bharani, Krittika (1) | C16: Ashwini, Bharani, Krittika (1) | D16: Cross-reference with REF_Nakshatra for sub-lord calculations
A19: INDEX(REF_Zodiac!$D$row:$O$row, MATCH(sign_cell, REF_Zodiac!$D$3:$O$3, 0))

Sheet REF_Planets
A1: REF_Planets — Complete Jyotish Planet Reference · Sources: BPHS Ch.3, Saravali Ch.1, Phaladeepika Ch.2 | M1: =HYPERLINK("#'00_INDEX'!A1","<- Index") -> <- Index
A2: READ-ONLY — all CALC_ sheets look up values here via INDEX/MATCH on the planet name. Rahu/Ketu are shadow nodes: no own signs in classical sense, always retrograde, amplify whatever they conjoin.
A3: Section | B3: Attribute | C3: Sanskrit | D3: Sun | E3: Moon | F3: Mars | G3: Mercury | H3: Jupiter | I3: Venus | J3: Saturn | K3: Rahu | L3: Ketu
A4: Identity | B4: Planet (English) | C4: Graha | D4: Sun | E4: Moon | F4: Mars | G4: Mercury | H4: Jupiter | I4: Venus | J4: Saturn | K4: Rahu | L4: Ketu
B5: Sanskrit name | C5: Sanskrit | D5: Surya | E5: Chandramaa | F5: Mangal | G5: Budh | H5: Brihaspati | I5: Shukra | J5: Shani | K5: Rahu | L5: Ketu
B6: Also known as | C6: Upanaam | D6: Aditya / Ravi | E6: Soma / Indu | F6: Kuja / Angaraka | G6: Soumya | H6: Guru / Devaguru | I6: Bhrigu / Sita | J6: Manda / Yama | K6: Swarbhanu (head) | L6: Swarbhanu (tail)
B7: Planet type | C7: Graha Prakar | D7: Luminaries | E7: Luminaries | F7: Inner planets | G7: Inner planets | H7: Outer planets | I7: Inner planets | J7: Outer planets | K7: Shadow node | L7: Shadow node
B8: Dasha order # | C8: Dasha Krama | D8: 3 | E8: 4 | F8: 7 | G8: 6 | H8: 5 | I8: 2 | J8: 8 | K8: 1 | L8: 9
B9: Dasha years | C9: Dasha Varsha | D9: 6 | E9: 10 | F9: 7 | G9: 17 | H9: 16 | I9: 20 | J9: 19 | K9: 18 | L9: 7
B10: Orbital speed | C10: Gati | D10: ~1°/day | E10: ~13°/day | F10: ~0.5°/day | G10: ~1.5°/day | H10: ~0.08°/day | I10: ~1.2°/day | J10: ~0.03°/day | K10: ~0.05°/day (mean) | L10: ~0.05°/day (mean)
A11: Lordship | B11: Own sign #1 | C11: Swarashi #1 | D11: Leo | E11: Cancer | F11: Aries | G11: Gemini | H11: Sagittarius | I11: Taurus | J11: Capricorn | K11: Aquarius | L11: Scorpio
B12: Own sign #2 | C12: Swarashi #2 | D12: — | E12: — | F12: Scorpio | G12: Virgo | H12: Pisces | I12: Libra | J12: Aquarius | K12: — | L12: —
B13: Exaltation sign | C13: Uchcha Rashi | D13: Aries | E13: Taurus | F13: Capricorn | G13: Virgo | H13: Cancer | I13: Pisces | J13: Libra | K13: Taurus | L13: Scorpio
B14: Exaltation degree | C14: Uchcha Amsha | D14: 10° | E14: 3° | F14: 28° | G14: 15° | H14: 5° | I14: 27° | J14: 20° | K14: 20° | L14: —
B15: Debilitation sign | C15: Neecha Rashi | D15: Libra | E15: Scorpio | F15: Cancer | G15: Pisces | H15: Capricorn | I15: Virgo | J15: Aries | K15: Scorpio | L15: Taurus
B16: Debilitation degree | C16: Neecha Amsha | D16: 10° | E16: 3° | F16: 28° | G16: 15° | H16: 5° | I16: 27° | J16: 20° | K16: 20° | L16: —
B17: Mooltrikona sign | C17: Mooltrikona Rashi | D17: Leo (0–20°) | E17: Taurus (4–20°) | F17: Aries (0–12°) | G17: Virgo (16–20°) | H17: Sagittarius (0–10°) | I17: Libra (0–15°) | J17: Aquarius (0–20°) | K17: — | L17: —
B18: Combust orb | C18: Asta Orb | D18: — | E18: 12° | F18: 17° | G18: 14° | H18: 11° | I18: 10° | J18: 15° | K18: — | L18: —
A19: Nature | B19: Natural nature | C19: Naisargika Swabhav | D19: Malefic | E19: Benefic (waxing) / Malefic (waning) | F19: Malefic | G19: Benefic (with benefics) / Malefic (with malefics) | H19: Benefic | I19: Benefic | J19: Malefic | K19: Malefic | L19: Malefic
B20: Gender | C20: Linga | D20: Masculine | E20: Feminine | F20: Masculine | G20: Neutral | H20: Masculine | I20: Feminine | J20: Neutral / Masculine | K20: Feminine | L20: Neutral
B21: Element / Tattva | C21: Tattva | D21: Fire | E21: Water | F21: Fire | G21: Earth | H21: Ether / Akash | I21: Water | J21: Air | K21: Air | L21: Fire
B22: Triguna | C22: Guna | D22: Sattva | E22: Sattva | F22: Tamas | G22: Rajas | H22: Sattva | I22: Rajas | J22: Tamas | K22: Tamas | L22: Tamas
B23: Varna | C23: Varna | D23: Kshatriya | E23: Vaishya | F23: Kshatriya | G23: Shudra | H23: Brahmin | I23: Brahmin | J23: Shudra | K23: Outcaste | L23: Outcaste
B24: Temperament | C24: Swabhava | D24: Steady / Fixed | E24: Changeable / Fickle | F24: Angry / Violent | G24: Humorous / Speech | H24: Benign / Mild | I24: Soft-hearted / Accommodating | J24: Subordinate / Servant | K24: Cruel / Unpredictable | L24: Cruel / Unpredictable
B25: Caste quality | C25: Jati | D25: Kshatriya | E25: Vaishya | F25: Kshatriya | G25: Shudra | H25: Brahmin | I25: Brahmin | J25: Shudra | K25: Low caste | L25: Low caste
A26: Karakatva | B26: Primary significations | C26: Mukhya Karakatva | D26: Soul, father, authority, vitality, self-confidence, government, power | E26: Mind, mother, emotions, nourishment, memory, response, sensitivity, public | F26: Bravery, aggression, courage, siblings, energy, accidents, surgery, property | G26: Speech, intelligence, analysis, communication, trade, education, writing, skin | H26: Wisdom, children, fortune, dharma, expansion, optimism, knowledge, teachers, law | I26: Harmony, love, beauty, luxury, relationships, arts, vehicles, pleasure, spouse | J26: Hard work, karma, longevity, discipline, delay, sorrow, service, old age, teeth | K26: Explosiveness, obsession, foreign, illusion, unconventional, materialistic gains, paternal grandfather | L26: Detachment, liberation, spirituality, intuition, transformation, elimination, maternal grandparents
B27: Sthir Karak for house | C27: Sthir Karak Bhav | D27: H1 (self), H9 (father), H10 (career) | E27: H4 (mother), H4 (mind / emotions) | F27: H3 (siblings / courage), H6 (enemies) | G27: H4 (education), H10 (business) | H27: H2 (wealth), H5 (children), H9 (fortune), H11 (gains) | I27: H2 (speech), H7 (spouse / marriage) | J27: H6 (service / disease), H8 (longevity), H10 (karma) | K27: H6 (obstacles), H12 (foreign / isolation) | L27: H12 (liberation / moksha)
B28: Cabinet role | C28: Rajdarbar | D28: King | E28: Queen | F28: Commander-in-chief | G28: Crown Prince / Yuvaraja | H28: Minister / Advisor | I28: Minister / Advisor (Royal) | J28: Servant | K28: — | L28: —
B29: Relationship signified | C29: Sambandh | D29: Father / Authority | E29: Mother / Public | F29: Younger siblings / Soldiers | G29: Maternal uncle / Friends | H29: Teachers / Elders / Husband (for women) | I29: Wife / Sisters / Young women | J29: Servant / Old people / Outcaste | K29: Paternal grandfather / Foreigners | L29: Maternal grandparents / Ascetics
A30: Body | B30: Body parts ruled | C30: Sharira Anga | D30: Bones (Asthi), Right eye, Heart, Stomach, Head (crown) | E30: Blood (Rakta), Left eye, Lungs, Breasts, Mind | F30: Muscles (Mamsa), Bone marrow, Blood, Bile, Head (forehead) | G30: Skin (Tvak), Nerves, Lungs, Speech organs, Hands | H30: Fat (Meda), Brain, Liver, Thighs, Ears | I30: Semen / Reproductive fluids, Skin, Genitals, Eyes (vision), Kidneys | J30: Tendons / Cartilage, Nerves (coarser), Teeth, Legs (feet / shins) | K30: Digestive system (general), Skin diseases, Nervous system disorders | L30: Feet, Spiritual body, Subtle nervous system
B31: Ayurvedic tissue | C31: Dhatu | D31: Bone (Asthi) | E31: Blood (Rakta) | F31: Muscle (Mamsa) | G31: Skin (Tvak) | H31: Fat (Meda) | I31: Semen / Shukra | J31: Nerves / Tendons | K31: Mixed / Vata | L31: Mixed / Vata
B32: Ayurvedic dosha | C32: Tridosha | D32: Pitta | E32: Vata / Kapha | F32: Pitta / Vata | G32: Vata / Pitta | H32: Kapha | I32: Kapha / Vata | J32: Vata | K32: Vata | L32: Vata / Pitta
B33: Taste / Rasa | C33: Rasa | D33: Pungent / Tikta | E33: Saline / Namkeen | F33: Bitter / Kadwa | G33: Mixed / Chatpata | H33: Sweet / Meetha | I33: Sour / Khatta | J33: Astringent / Kacha | K33: Mixed | L33: Mixed
B34: Diseases indicated | C34: Roga | D34: Heart disease, fever, eye problems, bone issues, blood pressure | E34: Mental issues, cold/cough, anaemia, menstrual disorders, water retention | F34: Accidents, wounds, burns, inflammation, blood disorders, surgery | G34: Skin diseases, nervous disorders, speech problems, respiratory issues | H34: Liver problems, obesity, diabetes, tumours, ear troubles | I34: Reproductive disorders, diabetes, STDs, kidney issues, hormonal imbalance | J34: Chronic illness, paralysis, arthritis, teeth, dental issues, cold diseases | K34: Skin diseases, nervous breakdown, obsessive disorders, poisoning | L34: Mysterious diseases, spiritual crises, leprosy, past-life karma
A35: Relationships | B35: Natural friends | C35: Naisargika Mitra | D35: Moon, Mars, Jupiter | E35: Sun, Mercury | F35: Sun, Moon, Jupiter | G35: Sun, Venus | H35: Sun, Moon, Mars | I35: Mercury, Saturn | J35: Mercury, Venus | K35: Venus, Saturn | L35: Mars, Venus
B36: Natural neutrals | C36: Naisargika Sama | D36: Mercury | E36: Mars, Jupiter, Venus, Saturn | F36: Venus, Saturn | G36: Mars, Jupiter, Saturn | H36: Saturn | I36: Jupiter, Mars | J36: Jupiter | K36: Ketu, Jupiter | L36: Rahu, Sun, Moon
B37: Natural enemies | C37: Naisargika Shatru | D37: Venus, Saturn | E37: Rahu, Ketu | F37: Mercury | G37: Moon | H37: Mercury, Venus | I37: Sun, Moon | J37: Sun, Moon, Mars | K37: Sun, Moon, Mars | L37: Saturn, Mercury
A38: Mundane | B38: Direction (Dig Bala) | C38: Disha | D38: South | E38: North | F38: South | G38: North | H38: East | I38: East | J38: West | K38: South-West | L38: North-East
B39: Dig Bala house | C39: Dig Bala Sthana | D39: H10 | E39: H4 | F39: H10 / H3 | G39: H1 | H39: H1 / H9 | I39: H4 | J39: H7 | K39: H3 | L39: H9
B40: Day/Night strength | C40: Diva / Ratri Bali | D40: Day | E40: Night | F40: Night | G40: Day | H40: Day | I40: Night | J40: Night | K40: Night | L40: Night
B41: Strong paksha | C41: Paksha Bala | D41: Shukla (waxing) | E41: Shukla (waxing) | F41: Krishna (waning) | G41: Both | H41: Shukla | I41: Shukla | J41: Krishna | K41: — | L41: —
B42: Season (Ritu) | C42: Ritu | D42: Summer / Grishma | E42: Rainy / Varsha | F42: Summer / Grishma | G42: Autumn / Sharad | H42: Early Winter / Hemanta | I42: Spring / Vasanta | J42: Winter / Shishira | K42: — | L42: —
B43: Colour | C43: Rang | D43: Orange / Copper-red | E43: White / Silvery | F43: Red / Blood red | G43: Green / Grass green | H43: Yellow / Golden | I43: White / Bright white | J43: Black / Dark blue | K43: Smoky / Dark blue | L43: Smoky / Multi-coloured
B44: Gemstone | C44: Ratna | D44: Ruby (Manik) | E44: Pearl (Moti) | F44: Red Coral (Moonga) | G44: Emerald (Panna) | H44: Yellow Sapphire (Pukhraj) | I44: Diamond / White Sapphire (Heera) | J44: Blue Sapphire (Neelam) | K44: Hessonite Garnet (Gomed) | L44: Cat's Eye (Lehsunia)
B45: Metal | C45: Dhatu | D45: Gold | E45: Silver | F45: Copper | G45: Mixed metals / Brass | H45: Gold | I45: Silver | J45: Iron / Lead | K45: Lead / Alloy | L45: Alloy / Iron
B46: Cloth / Texture | C46: Vastra | D46: Thick / Coarse | E46: New cloth / Soft | F46: Red cloth | G46: Mixed / Print | H46: Old cloth (Guru) | I46: Colourful silk | J46: Torn / Dirty | K46: Multi-coloured | L46: Variegated / Torn
B47: Location signified | C47: Sthana | D47: Temple / Government office / Open ground | E47: Well / Water body / Bedroom | F47: Fire place / Battlefield / Kitchen | G47: Learning institution / Market / Playground | H47: Temple / Treasury / Forest / River bank | I47: Bedroom / Pleasure house / Garden / Vehicle | J47: Dark place / Old building / Cemetery / Cremation ground | K47: Foreign land / Outskirts / Underground | L47: Forest / Isolated place / Moksha kshetra
A48: Scoring | B48: Special aspects | C48: Vishesh Drishti | D48: 7th only | E48: 7th only | F48: 4th, 7th, 8th (full) | G48: 7th only | H48: 5th, 7th, 9th (full) | I48: 7th only | J48: 3rd, 7th, 10th (full) | K48: 5th, 7th, 9th | L48: 5th, 7th, 9th
B49: Is shadow planet? | C49: Chhaya Graha | D49: No | E49: No | F49: No | G49: No | H49: No | I49: No | J49: No | K49: Yes (always Rx) | L49: Yes (always Rx)
B50: Always retrograde? | C50: Sadaa Vakri | D50: No | E50: No | F50: No | G50: No | H50: No | I50: No | J50: No | K50: Yes | L50: Yes
B51: Can combust others? | C51: Asta Karak | D51: Yes (combust all planets) | E51: No | F51: No | G51: No | H51: No | I51: No | J51: No | K51: No | L51: No
B52: Amplifies conjunct? | C52: Vriddhi Karak | D52: No | E52: No | F52: No | G52: No | H52: No | I52: No | J52: No | K52: Yes — amplifies the planet it conjoins | L52: Yes — spiritualises / detaches the planet it conjoins
B53: Karak for longevity? | C53: Ayu Karak | D53: No | E53: No | F53: No | G53: No | H53: No | I53: No | J53: Yes (primary) | K53: No | L53: No
B54: Raja Yoga forming? | C54: Raja Yoga Karaka | D54: When Kendra + Trikon lord | E54: When Kendra + Trikon lord | F54: Yes for Cancer/Leo Lagna (Yogakaraka) | G54: When Kendra + Trikon lord | H54: When Kendra + Trikon lord | I54: Yes for Capricorn/Aquarius Lagna (Yogakaraka) | J54: Yes for Taurus/Libra + Gemini/Virgo Lagna | K54: No | L54: No
B55: Mahadasha quality | C55: Dasha Phala | D55: Authority, health, father — strong if well-placed | E55: Mind, mother, popularity — fluctuating by sign strength | F55: Energy, ambition, conflicts — intense | G55: Business, intellect, communication — versatile | H55: Wisdom, expansion, prosperity — generally positive | I55: Comfort, love, luxury, marriage — pleasant | J55: Karma, hardship, discipline, delays — transformative | K55: Foreign travel, sudden events, obsession — unpredictable | L55: Spirituality, detachment, isolation, intuition — inward
A56: Sources: BPHS (Brihat Parashara Hora Shastra) Ch.3 — Saravali Ch.1 — Phaladeepika Ch.2 — Jataka Parijata — Hora Sara · Rahu/Ketu own signs: contested; Aq/Sc used here (BPHS convention)

Sheet REF_Planets_Lookup
A1: REF_Planets_Lookup — INDEX/MATCH formulas for CALC_ sheets | L1: =HYPERLINK("#'00_INDEX'!A1","<- Index") -> <- Index
A2: Pattern: =INDEX(REF_Planets!$D$ROW:$L$ROW, MATCH(planet_cell, REF_Planets!$D$3:$L$3, 0)) where ROW = attribute row number below. Replace planet_cell with e.g. CALC_PlanetPositions!B5
A4: Attribute | B4: Formula | C4: Returns | D4: Use in
A5: Own sign #1 | B5: =IFERROR(INDEX(REF_Planets!$D$11:$L$11,MATCH(planet_cell,REF_Planets!$D$4:$L$4,0)),"") | C5: Row 11 in REF_Planets | D5: CALC_BhaveshMap — identify lord of each house
A6: Exaltation sign | B6: =IFERROR(INDEX(REF_Planets!$D$13:$L$13,MATCH(planet_cell,REF_Planets!$D$4:$L$4,0)),"") | C6: Row 13 in REF_Planets | D6: CALC_PlanetPositions — check if planet is exalted in its current sign
A7: Debilitation sign | B7: =IFERROR(INDEX(REF_Planets!$D$15:$L$15,MATCH(planet_cell,REF_Planets!$D$4:$L$4,0)),"") | C7: Row 15 in REF_Planets | D7: CALC_PlanetPositions — check if planet is debilitated
A8: Mooltrikona sign | B8: =IFERROR(INDEX(REF_Planets!$D$17:$L$17,MATCH(planet_cell,REF_Planets!$D$4:$L$4,0)),"") | C8: Row 17 in REF_Planets | D8: CALC_PlanetPositions — dignity level between own and exalt
A9: Natural nature | B9: =IFERROR(INDEX(REF_Planets!$D$19:$L$19,MATCH(planet_cell,REF_Planets!$D$4:$L$4,0)),"") | C9: Row 19 in REF_Planets | D9: REF_ShubhAshubh — base classification before Lagna modification
A10: Dasha years | B10: =IFERROR(INDEX(REF_Planets!$D$9:$L$9,MATCH(planet_cell,REF_Planets!$D$4:$L$4,0)),"") | C10: Row 9 in REF_Planets | D10: INPUT_BirthData — Vimshottari timeline calculation
A11: Special aspects | B11: =IFERROR(INDEX(REF_Planets!$D$48:$L$48,MATCH(planet_cell,REF_Planets!$D$4:$L$4,0)),"") | C11: Row 48 in REF_Planets | D11: CALC_PlanetPositions — which houses each planet aspects
A12: Combust orb | B12: =IFERROR(INDEX(REF_Planets!$D$18:$L$18,MATCH(planet_cell,REF_Planets!$D$4:$L$4,0)),"") | C12: Row 18 in REF_Planets | D12: CALC_PlanetPositions — is a planet within Sun's orb → combusted?
A13: Natural friends | B13: =IFERROR(INDEX(REF_Planets!$D$35:$L$35,MATCH(planet_cell,REF_Planets!$D$4:$L$4,0)),"") | C13: Row 35 in REF_Planets | D13: CALC_PanchadhaMaitri — Naisargika friendship input
A14: Natural enemies | B14: =IFERROR(INDEX(REF_Planets!$D$37:$L$37,MATCH(planet_cell,REF_Planets!$D$4:$L$4,0)),"") | C14: Row 37 in REF_Planets | D14: CALC_PanchadhaMaitri — Naisargika enmity input
A15: Dig Bala house | B15: =IFERROR(INDEX(REF_Planets!$D$39:$L$39,MATCH(planet_cell,REF_Planets!$D$4:$L$4,0)),"") | C15: Row 39 in REF_Planets | D15: Future Shadbala — directional strength peak house
A16: Sthir Karak for house | B16: =IFERROR(INDEX(REF_Planets!$D$27:$L$27,MATCH(planet_cell,REF_Planets!$D$4:$L$4,0)),"") | C16: Row 27 in REF_Planets | D16: CALC_KarakMap — which planet is the fixed significator for which house
A17: Is shadow planet? | B17: =IFERROR(INDEX(REF_Planets!$D$49:$L$49,MATCH(planet_cell,REF_Planets!$D$4:$L$4,0)),"") | C17: Row 49 in REF_Planets | D17: All scoring — Rahu/Ketu need special-cased logic (no dignity, no combustion)
A18: Always retrograde? | B18: =IFERROR(INDEX(REF_Planets!$D$50:$L$50,MATCH(planet_cell,REF_Planets!$D$4:$L$4,0)),"") | C18: Row 50 in REF_Planets | D18: CALC_PlanetPositions — Rahu/Ketu are always Rx; skip retrograde bonus for them
A19: Amplifies conjunct? | B19: =IFERROR(INDEX(REF_Planets!$D$52:$L$52,MATCH(planet_cell,REF_Planets!$D$4:$L$4,0)),"") | C19: Row 52 in REF_Planets | D19: CALC_PlanetPositions — Rahu/Ketu amplify conjunct planet's effects

Sheet REF_Dignity
A1: REF_Dignity — Complete Dignity & Degree Ranges · Sources: BPHS Ch.3, Saravali Ch.1, Uttara Kalamrita Ch.2 | O1: =HYPERLINK("#'00_INDEX'!A1","<- Index") -> <- Index
A2: CALC_PlanetPositions looks up rows by planet name (col A) to resolve dignity level. Deep = within ±5° of exact degree. MLT = Mooltrikona. Neecha Bhanga conditions are in col N — check before applying debilitation penalty.
A3: Planet | B3: Sanskrit | C3: Exalt sign | D3: Exalt ° (peak) | E3: Deep exalt range (±5° of peak) | F3: Debil sign | G3: Debil ° (peak) | H3: Deep debil range (±5° of peak) | I3: Mooltrikona sign & range | J3: Own sign(s) — full range | K3: Friendly signs | L3: Neutral signs | M3: Combust orb (direct) | N3: Neecha Bhanga conditions
A4: Sun | B4: Surya | C4: Aries | D4: 10° | E4: Aries 5°–15° | F4: Libra | G4: 10° | H4: Libra 5°–15° | I4: Leo 0°–20° | J4: Leo 20°–30° (own) / 0°–20° (MLT) | K4: Aries, Cancer, Leo, Sagittarius | L4: Gemini | M4: N/A (node) | N4: • Lord of Libra (Venus) in Kendra from Lagna or Moon • Planet exalted in Libra (Saturn at 20° Libra) in Kendra • Sun in Libra with exalted planet in same sign
A5: Moon | B5: Chandramaa | C5: Taurus | D5: 3° | E5: Taurus 0°–8° | F5: Scorpio | G5: 3° | H5: Scorpio 0°–8° | I5: Taurus 4°–20° | J5: Cancer 0°–30° (Own sign) | K5: Taurus, Cancer, Leo, Libra, Sagittarius, Pisces | L5: Aries, Gemini, Virgo, Aquarius | M5: Direct: ±12.0° Rx: ±12.0° | N5: • Lord of Scorpio (Mars) in Kendra from Lagna or Moon • Jupiter exalted in Cancer in Kendra • Moon in Scorpio with Mars in Kendra from Lagna • Moon waxing (Shukla Paksha) reduces debilitation effect
A6: Mars | B6: Mangal | C6: Capricorn | D6: 28° | E6: Capricorn 23°–29° | F6: Cancer | G6: 28° | H6: Cancer 23°–29° | I6: Aries 0°–12° | J6: Aries 12°–30° (own) / 0°–12° (MLT) Scorpio 0°–30° (Own sign) | K6: Aries, Leo, Sagittarius, Scorpio, Capricorn, Pisces | L6: Taurus, Virgo, Libra, Aquarius | M6: Direct: ±17.0° Rx: ±17.0° | N6: • Lord of Cancer (Moon) in Kendra from Lagna or Moon • Jupiter exalted in Cancer in Kendra • Mars itself in Capricorn (own exaltation sign lord Saturn in Kendra)
A7: Mercury | B7: Budh | C7: Virgo | D7: 15° | E7: Virgo 10°–20° | F7: Pisces | G7: 15° | H7: Pisces 10°–20° | I7: Virgo 0°–15° | J7: Gemini 0°–30° (Own sign) Virgo 15°–30° (own) / 0°–15° (MLT) | K7: Gemini, Virgo, Libra, Aquarius | L7: Aries, Leo, Sagittarius, Capricorn | M7: Direct: ±14.0° Rx: ±12.0° | N7: • Lord of Pisces (Jupiter) in Kendra from Lagna or Moon • Venus exalted in Pisces in Kendra • Mercury in Pisces with exalted planet in Kendra from Moon
A8: Jupiter | B8: Brihaspati | C8: Cancer | D8: 5° | E8: Cancer 0°–10° | F8: Capricorn | G8: 5° | H8: Capricorn 0°–10° | I8: Sagittarius 0°–10° | J8: Sagittarius 10°–30° (own) / 0°–10° (MLT) Pisces 0°–30° (Own sign) | K8: Aries, Cancer, Leo, Scorpio, Sagittarius, Pisces | L8: Taurus, Capricorn, Aquarius | M8: Direct: ±11.0° Rx: ±8.0° | N8: • Lord of Capricorn (Saturn) in Kendra from Lagna or Moon • Mars exalted in Capricorn in Kendra • Jupiter in Capricorn aspected by exalted planet
A9: Venus | B9: Shukra | C9: Pisces | D9: 27° | E9: Pisces 22°–29° | F9: Virgo | G9: 27° | H9: Virgo 22°–29° | I9: Libra 0°–15° | J9: Taurus 0°–30° (Own sign) Libra 15°–30° (own) / 0°–15° (MLT) | K9: Taurus, Gemini, Libra, Capricorn, Aquarius, Pisces | L9: Aries, Cancer, Scorpio, Sagittarius | M9: Direct: ±10.0° Rx: ±8.0° | N9: • Lord of Virgo (Mercury) in Kendra from Lagna or Moon • Mercury exalted in Virgo in Kendra • Venus in Virgo with exalted planet conjunct or in Kendra from Moon
A10: Saturn | B10: Shani | C10: Libra | D10: 20° | E10: Libra 15°–25° | F10: Aries | G10: 20° | H10: Aries 15°–25° | I10: Aquarius 0°–20° | J10: Capricorn 0°–30° (Own sign) Aquarius 20°–30° (own) / 0°–20° (MLT) | K10: Taurus, Gemini, Virgo, Libra, Capricorn, Aquarius | L10: Sagittarius, Pisces | M10: Direct: ±15.0° Rx: ±15.0° | N10: • Lord of Aries (Mars) in Kendra from Lagna or Moon • Sun exalted in Aries in Kendra • Saturn in Aries with Mars in Kendra from Lagna or Moon
A11: Rahu | B11: Rahu | C11: Taurus | D11: 20° | E11: Taurus 15°–25° | F11: Scorpio | G11: 20° | H11: Scorpio 15°–25° | I11: None (shadow node) | J11: Aquarius 0°–30° (Own sign — BPHS convention) Gemini 0°–30° (Co-lordship — Parashari view) | K11: Taurus, Gemini, Virgo, Libra, Capricorn, Aquarius | L11: Aries, Sagittarius, Pisces | M11: N/A (node) | N11: • Disputed: Rahu neecha bhanga less clearly defined in classical texts • Some texts: lord of Taurus (Venus) in Kendra cancels [Note] Rahu always retrograde (mean node). Always 180° from Ketu. Amplifies/intensifies the planet it conjoins. Own sign assignment contested — Aquarius (BPHS) most common.
A12: Ketu | B12: Ketu | C12: Scorpio | D12: 20° | E12: Scorpio 15°–25° | F12: Taurus | G12: 20° | H12: Taurus 15°–25° | I12: None (shadow node) | J12: Scorpio 0°–30° (Own sign — BPHS convention) Pisces 0°–30° (Co-lordship — Parashari view) | K12: Aries, Cancer, Scorpio, Pisces | L12: Leo, Sagittarius, Capricorn | M12: N/A (node) | N12: • Ketu neecha bhanga less defined; Mars in Kendra generally helps [Note] Ketu always retrograde (mean node). Always 180° from Rahu. Spiritualises / detaches the planet it conjoins. Own sign assignment contested — Scorpio (BPHS) most common.
A15: Dignity Scoring Weights — used by CALC_PlanetPositions to compute planet strength modifier
A16: Dignity level | B16: Sanskrit | C16: Weight (score modifier) | D16: Applies when...
A17: Deep exaltation | B17: Paramauchcha | C17: +2.0 | D17: Within ±5° of exact exaltation degree
A18: Exaltation | B18: Uchcha | C18: +1.5 | D18: In exaltation sign, outside deep exalt range
A19: Mooltrikona | B19: Mooltrikona | C19: +1.0 | D19: Within mooltrikona degree range
A20: Own sign | B20: Swarashi | C20: +0.75 | D20: In own sign, outside mooltrikona range
A21: Friendly sign | B21: Mitra Rashi | C21: +0.5 | D21: In sign ruled by a natural friend
A22: Neutral sign | B22: Sama Rashi | C22: 0.0 | D22: In sign ruled by a neutral planet
A23: Enemy sign | B23: Shatru Rashi | C23: -0.5 | D23: In sign ruled by a natural enemy
A24: Debilitation | B24: Neecha | C24: -1.5 | D24: In debilitation sign
A25: Deep debilitation | B25: Paramaneecha | C25: -2.0 | D25: Within ±5° of exact debilitation degree
A26: Combust (direct) | B26: Asta (direct) | C26: -1.0 | D26: Within Sun's combustion orb, direct motion
A27: Combust (Rx) | B27: Asta (Vakri) | C27: -0.5 | D27: Within Sun's combustion orb, retrograde (reduced effect)
... A29: Neecha Bhanga | B29: Neecha Bhanga | C29: +1.0 | D29: Debilitation cancelled — treat as neutral or better
A33: Dignity Matrix — Sign × Planet · CALC_PlanetPositions: INDEX(matrix, MATCH(planet, header_row), MATCH(sign, header_col))
A34: Sign | B34: Sun | C34: Moon | D34: Mars | E34: Mercury | F34: Jupiter | G34: Venus | H34: Saturn | I34: Rahu | J34: Ketu
A35: Aries | B35: Exaltation | C35: Neutral sign | D35: Mooltrikona | E35: Neutral sign | F35: Friendly sign | G35: Neutral sign | H35: Debilitation | I35: Neutral sign | J35: Friendly sign
A36: Taurus | B36: Enemy sign | C36: Exaltation | D36: Neutral sign | E36: Enemy sign | F36: Neutral sign | G36: Own sign | H36: Friendly sign | I36: Exaltation | J36: Debilitation
A37: Gemini | B37: Neutral sign | C37: Neutral sign | D37: Enemy sign | E37: Own sign | F37: Enemy sign | G37: Friendly sign | H37: Friendly sign | I37: Own sign | J37: Enemy sign
A38: Cancer | B38: Friendly sign | C38: Own sign | D38: Debilitation | E38: Enemy sign | F38: Exaltation | G38: Neutral sign | H38: Enemy sign | I38: Enemy sign | J38: Friendly sign
A39: Leo | B39: Mooltrikona | C39: Friendly sign | D39: Friendly sign | E39: Neutral sign | F39: Friendly sign | G39: Enemy sign | H39: Enemy sign | I39: Enemy sign | J39: Neutral sign
A40: Virgo | B40: Enemy sign | C40: Neutral sign | D40: Neutral sign | E40: Exaltation | F40: Enemy sign | G40: Debilitation | H40: Friendly sign | I40: Friendly sign | J40: Enemy sign
A41: Libra | B41: Debilitation | C41: Friendly sign | D41: Neutral sign | E41: Friendly sign | F41: Enemy sign | G41: Mooltrikona | H41: Exaltation | I41: Friendly sign | J41: Enemy sign
A42: Scorpio | B42: Enemy sign | C42: Debilitation | D42: Own sign | E42: Enemy sign | F42: Friendly sign | G42: Neutral sign | H42: Enemy sign | I42: Debilitation | J42: Exaltation
A43: Sagittarius | B43: Friendly sign | C43: Friendly sign | D43: Friendly sign | E43: Neutral sign | F43: Mooltrikona | G43: Neutral sign | H43: Neutral sign | I43: Neutral sign | J43: Neutral sign
A44: Capricorn | B44: Enemy sign | C44: Enemy sign | D44: Exaltation | E44: Neutral sign | F44: Debilitation | G44: Friendly sign | H44: Own sign | I44: Friendly sign | J44: Neutral sign
A45: Aquarius | B45: Enemy sign | C45: Neutral sign | D45: Neutral sign | E45: Friendly sign | F45: Neutral sign | G45: Friendly sign | H45: Mooltrikona | I45: Own sign | J45: Enemy sign
A46: Pisces | B46: Enemy sign | C46: Friendly sign | D46: Friendly sign | E46: Debilitation | F46: Own sign | G46: Exaltation | H46: Neutral sign | I46: Neutral sign | J46: Own sign
A48: Note: This matrix shows sign-level dignity only. For actual score, also check degree (deep exalt/debil ±5°), combustion, and retrograde from CALC_PlanetPositions. Rahu/Ketu own signs per BPHS convention — contested in other schools.
A55: SECTION 3 — Dependency alert: SCORE_H* rules that read dignity weights (col C, rows 17-29). If you change any weight here, review these rules.
A56: Dignity level | B56: Weight (col C) | C56: Baseline | D56: Changed? | E56: SCORE_H* rules affected | F56: Action required
A57: Deep exaltation | B57: =C17 -> +2.0 | C57: +2.0 | D57: =IF(TEXT(C17,"0.00")<>TEXT(2,"0.00"),"⚠ CHANGED — review SCORE_H*","✓ unchanged") -> ✓ unchanged | E57: R02 YK bonus, R04 Bhavesh kendra, R06 YK with Bhavesh | F57: If changed: update REF_SchoolConfig weights and re-check all SCORE_H* rules that reference this dignity level.
A58: Exaltation | B58: =C18 -> +1.5 | C58: +1.5 | D58: =IF(TEXT(C18,"0.00")<>TEXT(1.5,"0.00"),"⚠ CHANGED — review SCORE_H*","✓ unchanged") -> ✓ unchanged | E58: R02 YK bonus | F58: If changed: update REF_SchoolConfig weights and re-check all SCORE_H* rules that reference this dignity level.
A59: Mooltrikona | B59: =C19 -> +1.0 | C59: +1.0 | D59: =IF(TEXT(C19,"0.00")<>TEXT(1,"0.00"),"⚠ CHANGED — review SCORE_H*","✓ unchanged") -> ✓ unchanged | E59: R02 benefic in house | F59: If changed: update REF_SchoolConfig weights and re-check all SCORE_H* rules that reference this dignity level.
A60: Own sign | B60: =C20 -> +0.75 | C60: +0.75 | D60: =IF(TEXT(C20,"0.00")<>TEXT(0.75,"0.00"),"⚠ CHANGED — review SCORE_H*","✓ unchanged") -> ✓ unchanged | E60: R02 benefic in house | F60: If changed: update REF_SchoolConfig weights and re-check all SCORE_H* rules that reference this dignity level.
A61: Friendly sign | B61: =C21 -> +0.5 | C61: +0.5 | D61: =IF(TEXT(C21,"0.00")<>TEXT(0.5,"0.00"),"⚠ CHANGED — review SCORE_H*","✓ unchanged") -> ✓ unchanged | E61: R02, R07 benefic aspects | F61: If changed: update REF_SchoolConfig weights and re-check all SCORE_H* rules that reference this dignity level.
A62: Neutral sign | B62: =C22 -> 0.0 | C62: 0.0 | D62: =IF(TEXT(C22,"0.00")<>TEXT(0,"0.00"),"⚠ CHANGED — review SCORE_H*","✓ unchanged") -> ✓ unchanged | E62: No direct rule — baseline only | F62: If changed: update REF_SchoolConfig weights and re-check all SCORE_H* rules that reference this dignity level.
A63: Enemy sign | B63: =C23 -> -0.5 | C63: -0.5 | D63: =IF(TEXT(C23,"0.00")<>TEXT(-0.5,"0.00"),"⚠ CHANGED — review SCORE_H*","✓ unchanged") -> ✓ unchanged | E63: R09 malefic in house, R16 bhavesh enemy | F63: If changed: update REF_SchoolConfig weights and re-check all SCORE_H* rules that reference this dignity level.
A64: Debilitation | B64: =C24 -> -1.5 | C64: -1.5 | D64: =IF(TEXT(C24,"0.00")<>TEXT(-1.5,"0.00"),"⚠ CHANGED — review SCORE_H*","✓ unchanged") -> ✓ unchanged | E64: R09, R11 dukshthan lord, R16, R19 combust | F64: If changed: update REF_SchoolConfig weights and re-check all SCORE_H* rules that reference this dignity level.
A65: Deep debilitation | B65: =C25 -> -2.0 | C65: -2.0 | D65: =IF(TEXT(C25,"0.00")<>TEXT(-2,"0.00"),"⚠ CHANGED — review SCORE_H*","✓ unchanged") -> ✓ unchanged | E65: R09, R19 — strongest negative modifier | F65: If changed: update REF_SchoolConfig weights and re-check all SCORE_H* rules that reference this dignity level.
A66: Combust direct | B66: =C26 -> -1.0 | C66: -1.0 | D66: =IF(TEXT(C26,"0.00")<>TEXT(-1,"0.00"),"⚠ CHANGED — review SCORE_H*","✓ unchanged") -> ✓ unchanged | E66: R19 bhavesh combust | F66: If changed: update REF_SchoolConfig weights and re-check all SCORE_H* rules that reference this dignity level.
A67: Combust Rx | B67: =C27 -> -0.5 | C67: -0.5 | D67: =IF(TEXT(C27,"0.00")<>TEXT(-0.5,"0.00"),"⚠ CHANGED — review SCORE_H*","✓ unchanged") -> ✓ unchanged | E67: R19 (reduced for retrograde combustion) | F67: If changed: update REF_SchoolConfig weights and re-check all SCORE_H* rules that reference this dignity level.
A68: Retrograde bonus | B68: =C28 -> +0.25 | C68: +0.25 | D68: =IF(TEXT(C28,"0.00")<>TEXT(0.25,"0.00"),"⚠ CHANGED — review SCORE_H*","✓ unchanged") -> ✓ unchanged | E68: R22 retrograde modifier | F68: If changed: update REF_SchoolConfig weights and re-check all SCORE_H* rules that reference this dignity level.
A69: Neecha Bhanga | B69: =C29 -> +1.0 | C69: +1.0 | D69: =IF(TEXT(C29,"0.00")<>TEXT(1,"0.00"),"⚠ CHANGED — review SCORE_H*","✓ unchanged") -> ✓ unchanged | E69: R29 — cancels debilitation penalty | F69: If changed: update REF_SchoolConfig weights and re-check all SCORE_H* rules that reference this dignity level.

Sheet REF_Nakshatra
A1: REF_Nakshatra — Complete Jyotish Nakshatra Reference · 27 Nakshatras × 42 attributes · Sources: BPHS Ch.94-96, Brihat Samhita, 27 Stars 27 Gods
A2: READ-ONLY. CALC_PlanetPositions: =INDEX(REF_Nakshatra!colA:colA, MATCH(nakshatra_name, REF_Nakshatra!B:B, 0)) · Pada Navamsha sign cycles Aries→Pisces across all 108 padas · Mool = Ganda Mool nakshatra — first pada most sensitive for birth | AS2: =HYPERLINK("#'00_INDEX'!A1","← Index") -> ← Index
A3: A — Identity | G3: B — Zodiac placement | L3: C — Dasha & Mool | P3: D — Pada breakdown (4 padas × 3 cols = 12) | AB3: E — Classical nature | AK3: F — Career indicators
B4: Name | C4: Sanskrit | D4: Symbol | E4: Meaning | F4: Deity / Devata | G4: Zodiac sign | H4: Start ° (0–360) | I4: End ° (0–360) | J4: Sign start ° | K4: Sign end ° | L4: Dasha lord | M4: Dasha years | N4: Mool Nakshatra? | O4: Ganda Mool note | P4: P1 Navamsha | Q4: P1 start ° | R4: P1 end ° | S4: P2 Navamsha | T4: P2 start ° | U4: P2 end ° | V4: P3 Navamsha | W4: P3 start ° | X4: P3 end ° | Y4: P4 Navamsha | Z4: P4 start ° | AA4: P4 end ° | AB4: Gana | AC4: Varna | AD4: Gender | AE4: Nadi | AF4: Yoni animal | AG4: Aim (Purushartha) | AH4: Guna | AI4: Activity type | AJ4: Tatva (element) | AK4: Life theme | AL4: Career fields | AM4: Career style | AN4: Strengths | AO4: Challenges | AP4: Keywords
A5: Krama | B5: Naam | C5: Sanskrit | D5: Pratik | E5: Artha | F5: Devata | G5: Rashi | H5: Aarambh Amsha | I5: Ant Amsha | J5: Rashi Aarambh | K5: Rashi Ant | L5: Dasha Swami | M5: Dasha Varsha | N5: Mool Nakshatra | O5: Ganda Mool | P5: P1 Navamsha | Q5: P1 Aarambh | R5: P1 Ant | S5: P2 Navamsha | T5: P2 Aarambh | U5: P2 Ant | V5: P3 Navamsha | W5: P3 Aarambh | X5: P3 Ant | Y5: P4 Navamsha | Z5: P4 Aarambh | AA5: P4 Ant | AB5: Gana | AC5: Varna | AD5: Linga | AE5: Nadi | AF5: Yoni | AG5: Purushartha | AH5: Guna | AI5: Karma Prakar | AJ5: Tattva | AK5: Jeevan Vishay | AL5: Vyavsaya | AM5: Karya Shaili | AN5: Shakti | AO5: Chunauti | AP5: Shabda
A6: 1 | B6: Ashwini | C6: Ashwini | D6: Horse's head | E6: The horse woman / born of a horse | F6: Ashwini Kumaras (celestial physicians) | G6: Aries | H6: 0 | I6: 13.333 | J6: 0 | K6: 13.333 | L6: Ketu | M6: 7 | N6: Yes (P1 most sensitive) | O6: 0°–3°20' Aries is Ganda Mool — moon here needs remedies | P6: Aries | Q6: 0 | R6: 3.3333 | S6: Taurus | T6: 3.3333 | U6: 6.6667 | V6: Gemini | W6: 6.6667 | X6: 10 | Y6: Cancer | Z6: 10 | AA6: 13.3333 | AB6: Deva | AC6: Vaishya | AD6: Male | AE6: Vata | AF6: Horse | AG6: Dharma | AH6: Rajas | AI6: Movable / Kshipra (swift) | AJ6: Fire | AK6: Initiating, swift healing, and the power to begin | AL6: Medicine, emergency services, surgery, equestrian sports, racing, physical therapy, athletics, veterinary science, military first response | AM6: Fast-moving, independent, prefers action over deliberation, thrives in urgent high-stakes environments | AN6: Speed, instinctive diagnosis, courage, pioneering ability, natural authority in crisis | AO6: Impatience, starting without finishing, recklessness, resistance to taking advice from others | AP6: Healer, initiator, swift, courageous, independent, restorer
A7: 2 | B7: Bharani | C7: Bharani | D7: Yoni (womb/vessel) | E7: The bearer / she who bears | F7: Yama (god of death and dharma) | G7: Aries | H7: 13.333 | I7: 26.667 | J7: 13.333 | K7: 26.667 | L7: Venus | M7: 20 | N7: No | O7: — | P7: Leo | Q7: 13.3333 | R7: 16.6667 | S7: Virgo | T7: 16.6667 | U7: 20 | V7: Libra | W7: 20 | X7: 23.3333 | Y7: Scorpio | Z7: 23.3333 | AA7: 26.6667 | AB7: Manushya | AC7: Mleccha (outcaste) | AD7: Female | AE7: Pitta | AF7: Elephant | AG7: Artha | AH7: Rajas | AI7: Fierce / Ugra | AJ7: Fire | AK7: Restraint, transformation through discipline, and the cycle of creation-death | AL7: Law, judiciary, prison services, agriculture, film and performing arts, fertility medicine, funeral services, sex work or therapy, public health | AM7: Disciplined and exacting, operates in extreme or taboo domains, works best with clear authority and boundaries | AN7: Endurance, moral discernment, ability to hold opposites, deep creative force, fearlessness about difficult truths | AO7: Excess, moral rigidity, carrying too much for others, tendency toward martyrdom or extremism | AP7: Disciplined, transformative, fertile, lawful, intense, creative
A8: 3 | B8: Krittika | C8: Krittika | D8: Razor / flame | E8: The cutters / the Pleiades | F8: Agni (fire god) | G8: Aries/Taurus | H8: 26.667 | I8: 40 | J8: 26.667 | K8: 10 | L8: Sun | M8: 6 | N8: No | O8: — | P8: Sagittarius | Q8: 26.6667 | R8: 30 | S8: Capricorn | T8: 30 | U8: 33.3333 | V8: Aquarius | W8: 33.3333 | X8: 36.6667 | Y8: Pisces | Z8: 36.6667 | AA8: 40 | AB8: Rakshasa | AC8: Brahmin | AD8: Female | AE8: Kapha | AF8: Sheep | AG8: Kama | AH8: Rajas | AI8: Mixed / Sadharan | AJ8: Fire | AK8: Sharp discernment, purification, and cutting away the non-essential | AL8: Military, cooking, metallurgy, surgery, literary criticism, fire services, priesthood, education, quality control, engineering | AM8: Direct, exacting, uncompromising in standards — works methodically and demands precision from self and others | AN8: Sharp intellect, leadership, clarity of purpose, ability to purify and refine, protective instinct | AO8: Aggression, over-criticism, difficulty with emotional sensitivity, tendency to burn bridges unnecessarily | AP8: Sharp, purifying, direct, warrior, precise, leader
A9: 4 | B9: Rohini | C9: Rohini | D9: Chariot / ox cart | E9: The red one / the growing one | F9: Brahma (creator god) | G9: Taurus | H9: 40 | I9: 53.333 | J9: 10 | K9: 23.333 | L9: Moon | M9: 10 | N9: No | O9: — | P9: Aries | Q9: 40 | R9: 43.3333 | S9: Taurus | T9: 43.3333 | U9: 46.6667 | V9: Gemini | W9: 46.6667 | X9: 50 | Y9: Cancer | Z9: 50 | AA9: 53.3333 | AB9: Manushya | AC9: Shudra | AD9: Male | AE9: Kapha | AF9: Serpent | AG9: Moksha | AH9: Rajas | AI9: Fixed / Sthira | AJ9: Earth | AK9: Cultivation, beauty, sensuality, and material abundance | AL9: Agriculture, horticulture, fashion, luxury goods, arts, music, culinary arts, real estate, interior design, cinematography, public relations, hospitality | AM9: Sensory-driven, values quality and aesthetics, builds gradually and sustainably, deeply invested in craft | AN9: Charm, artistic vision, patience, ability to nurture and grow, magnetic presence, commercial instinct | AO9: Stubbornness, possessiveness, over-indulgence, difficulty adapting to change, jealousy | AP9: Aesthetic, creative, nurturing, abundant, charming, grounded
A10: 5 | B10: Mrigashira | C10: Mrigashira | D10: Deer's head | E10: The deer's head / searching | F10: Soma (moon god) | G10: Taurus/Gemini | H10: 53.333 | I10: 66.667 | J10: 23.333 | K10: 6.667 | L10: Mars | M10: 7 | N10: No | O10: — | P10: Leo | Q10: 53.3333 | R10: 56.6667 | S10: Virgo | T10: 56.6667 | U10: 60 | V10: Libra | W10: 60 | X10: 63.3333 | Y10: Scorpio | Z10: 63.3333 | AA10: 66.6667 | AB10: Deva | AC10: Farmer | AD10: Neutral | AE10: Pitta | AF10: Serpent | AG10: Moksha | AH10: Tamas | AI10: Soft / Mridu | AJ10: Earth | AK10: Seeking, research, gentle inquiry, and the perpetual quest for beauty | AL10: Research, travel, journalism, botany, geography, textile design, photography, sales, exploration, ancient languages, archaeology, perfumery | AM10: Curious and restless, moves between fields and ideas, prefers discovery over routine, excellent networker | AN10: Versatility, refined aesthetic sense, investigative mind, charm in social situations, adaptability | AO10: Inconsistency, spreading attention too thin, difficulty committing, anxiety from over-stimulation | AP10: Curious, searching, gentle, versatile, aesthetic, restless
A11: 6 | B11: Ardra | C11: Ardra | D11: Teardrop / diamond | E11: The moist one / the storm | F11: Rudra (storm god / form of Shiva) | G11: Gemini | H11: 66.667 | I11: 80 | J11: 6.667 | K11: 20 | L11: Rahu | M11: 18 | N11: No | O11: — | P11: Sagittarius | Q11: 66.6667 | R11: 70 | S11: Capricorn | T11: 70 | U11: 73.3333 | V11: Aquarius | W11: 73.3333 | X11: 76.6667 | Y11: Pisces | Z11: 76.6667 | AA11: 80 | AB11: Manushya | AC11: Butcher | AD11: Female | AE11: Vata | AF11: Dog | AG11: Kama | AH11: Tamas | AI11: Sharp / Tikshna | AJ11: Water | AK11: Transformation through destruction, penetrating intellect, and seeing through illusion | AL11: Science, technology, statistics, surgery, demolition, investigative journalism, psychology, philosophy, database management, electrical engineering, storm research | AM11: Analytical to the point of ruthlessness, thrives under pressure, intellectually aggressive, sees patterns others miss | AN11: Deep penetrating intelligence, fearlessness in facing harsh truths, transformative capacity, stamina through crisis | AO11: Destructive tendencies, emotional volatility, can be cruel in criticism, difficulty with routine stability | AP11: Intense, analytical, transformative, stormy, penetrating, ruthless
A12: 7 | B12: Punarvasu | C12: Punarvasu | D12: Quiver of arrows | E12: Good again / the return of light | F12: Aditi (mother of gods / infinity) | G12: Gemini/Cancer | H12: 80 | I12: 93.333 | J12: 20 | K12: 3.333 | L12: Jupiter | M12: 16 | N12: No | O12: — | P12: Aries | Q12: 80 | R12: 83.3333 | S12: Taurus | T12: 83.3333 | U12: 86.6667 | V12: Gemini | W12: 86.6667 | X12: 90 | Y12: Cancer | Z12: 90 | AA12: 93.3333 | AB12: Deva | AC12: Vaishya | AD12: Male | AE12: Vata | AF12: Cat | AG12: Artha | AH12: Sattva | AI12: Movable / Kshipra | AJ12: Water | AK12: Return, renewal, philosophical optimism, and the gift of second chances | AL12: Philosophy, teaching, counselling, travel, diplomacy, publishing, international relations, spiritual guidance, real estate (buying and selling), non-profit sector | AM12: Expansive thinker, naturally optimistic, works best with freedom and variety, strong sense of ethics | AN12: Resilience, philosophical depth, generosity, ability to restore and revive, natural teaching ability | AO12: Over-optimism, difficulty finishing projects, impracticality, scattered focus | AP12: Philosophical, resilient, generous, renewed, optimistic, expansive
A13: 8 | B13: Pushya | C13: Pushya | D13: Udder of a cow / lotus | E13: The nourisher / the flower | F13: Brihaspati (Jupiter, preceptor of gods) | G13: Cancer | H13: 93.333 | I13: 106.667 | J13: 3.333 | K13: 16.667 | L13: Saturn | M13: 19 | N13: No | O13: — | P13: Leo | Q13: 93.3333 | R13: 96.6667 | S13: Virgo | T13: 96.6667 | U13: 100 | V13: Libra | W13: 100 | X13: 103.3333 | Y13: Scorpio | Z13: 103.3333 | AA13: 106.6667 | AB13: Deva | AC13: Kshatriya | AD13: Male | AE13: Pitta | AF13: Sheep | AG13: Dharma | AH13: Tamas | AI13: Fixed / Sthira | AJ13: Water | AK13: Nourishment, protection, spiritual duty, and the sustaining of life | AL13: Healthcare, nutrition, food industry, social work, religious institutions, childcare, administration, government service, banking, agriculture | AM13: Methodical, patient, service-oriented, long-term planner — reliable and steady rather than innovative | AN13: Dependability, nurturing capacity, organisational skill, spiritual commitment, integrity | AO13: Conservatism, resistance to change, over-dependence on tradition, emotional suppression | AP13: Nurturing, dutiful, stable, protective, spiritual, reliable
A14: 9 | B14: Ashlesha | C14: Ashlesha | D14: Coiled serpent | E14: The clinging / the embracer | F14: Nagas (serpent deities) | G14: Cancer | H14: 106.667 | I14: 120 | J14: 16.667 | K14: 30 | L14: Mercury | M14: 17 | N14: Yes (P4 is Mool — last pada) | O14: 16°40'–20° Cancer is Ganda Mool | P14: Sagittarius | Q14: 106.6667 | R14: 110 | S14: Capricorn | T14: 110 | U14: 113.3333 | V14: Aquarius | W14: 113.3333 | X14: 116.6667 | Y14: Pisces | Z14: 116.6667 | AA14: 120 | AB14: Rakshasa | AC14: Mleccha | AD14: Female | AE14: Kapha | AF14: Cat | AG14: Dharma | AH14: Tamas | AI14: Sharp / Tikshna | AJ14: Water | AK14: Penetrating wisdom, kundalini energy, and hidden psychological power | AL14: Toxicology, pharmacology, psychology, hypnotherapy, snakebite medicine, mysticism, diplomacy, espionage, chemistry, hidden investigations, astrology | AM14: Deeply perceptive, works behind the scenes, strategic and coiling rather than direct, reads people intuitively | AN14: Penetrating insight, strategic intelligence, healing through crisis, hypnotic presence | AO14: Manipulation, deceit, clinging to power, poisonous speech when threatened, difficulty with trust | AP14: Penetrating, strategic, hypnotic, wise, coiling, perceptive
A15: 10 | B15: Magha | C15: Magha | D15: Throne / palanquin | E15: The great one / the mighty | F15: Pitrs (ancestors / ancestral spirits) | G15: Leo | H15: 120 | I15: 133.333 | J15: 0 | K15: 13.333 | L15: Ketu | M15: 7 | N15: Yes (P1 is Mool) | O15: 0° Leo — Ganda Mool junction | P15: Aries | Q15: 120 | R15: 123.3333 | S15: Taurus | T15: 123.3333 | U15: 126.6667 | V15: Gemini | W15: 126.6667 | X15: 130 | Y15: Cancer | Z15: 130 | AA15: 133.3333 | AB15: Rakshasa | AC15: Shudra | AD15: Female | AE15: Vata | AF15: Rat | AG15: Artha | AH15: Tamas | AI15: Fierce / Ugra | AJ15: Water | AK15: Royal authority, ancestral pride, and the inheritance of legacy | AL15: Politics, royalty, CEO/leadership roles, genealogy, history, hereditary institutions, theatre, aristocracy, museums, palace administration | AM15: Authoritative, heritage-conscious, expects recognition, commands natural respect, operates with dignity | AN15: Natural leadership, regal bearing, historical awareness, capacity to inspire loyalty, strong identity | AO15: Arrogance, excessive pride, difficulty with egalitarianism, over-reliance on status | AP15: Royal, authoritative, ancestral, proud, commanding, legacy-driven
A16: 11 | B16: Purva Phalguni | C16: Purva Phalguni | D16: Front legs of a bed / fig tree | E16: The first reddish one / the first lucky star | F16: Bhaga (god of marital bliss and fortune) | G16: Leo | H16: 133.333 | I16: 146.667 | J16: 13.333 | K16: 26.667 | L16: Venus | M16: 20 | N16: No | O16: — | P16: Leo | Q16: 133.3333 | R16: 136.6667 | S16: Virgo | T16: 136.6667 | U16: 140 | V16: Libra | W16: 140 | X16: 143.3333 | Y16: Scorpio | Z16: 143.3333 | AA16: 146.6667 | AB16: Manushya | AC16: Brahmin | AD16: Female | AE16: Pitta | AF16: Rat | AG16: Kama | AH16: Rajas | AI16: Fierce / Ugra | AJ16: Water | AK16: Creative enjoyment, rest, romance, and the expression of beauty | AL16: Entertainment, performing arts, luxury brand management, marriage counselling, interior design, cosmetics, hospitality, holiday and leisure industry, fashion | AM16: Pleasure-seeking, socially magnetic, works best with creative freedom and appreciation from others | AN16: Artistic expression, charm, romantic vision, ability to bring beauty into the world, commercial sensibility | AO16: Laziness, hedonism, over-dependence on comfort, avoidance of difficult or unpleasant work | AP16: Creative, romantic, luxurious, charming, expressive, pleasure-loving
A17: 12 | B17: Uttara Phalguni | C17: Uttara Phalguni | D17: Back legs of a bed / fig tree | E17: The second reddish one / the second lucky star | F17: Aryaman (god of contracts and nobility) | G17: Leo/Virgo | H17: 146.667 | I17: 160 | J17: 26.667 | K17: 10 | L17: Sun | M17: 6 | N17: No | O17: — | P17: Sagittarius | Q17: 146.6667 | R17: 150 | S17: Capricorn | T17: 150 | U17: 153.3333 | V17: Aquarius | W17: 153.3333 | X17: 156.6667 | Y17: Pisces | Z17: 156.6667 | AA17: 160 | AB17: Manushya | AC17: Kshatriya | AD17: Female | AE17: Pitta | AF17: Cow | AG17: Moksha | AH17: Rajas | AI17: Fixed / Sthira | AJ17: Fire | AK17: Service through strength, social contracts, and patronage | AL17: Social work, NGO leadership, corporate social responsibility, philanthropy, medicine, law, military officer, public administration, civic leadership | AM17: Duty-driven, organises for others' benefit, combines creative capacity with reliable execution | AN17: Generosity, social conscience, leadership through service, steady execution, ability to unite people | AO17: Over-commitment, difficulty prioritising own needs, rigidity in adherence to duty | AP17: Service-oriented, noble, steady, generous, dutiful, social
... A32: 27 | B32: Revati | C32: Revati | D32: Fish / drum | E32: The prosperous / the wealthy | F32: Pushan (god of journeys, nourishment, and protection of flocks) | G32: Pisces | H32: 346.667 | I32: 360 | J32: 16.667 | K32: 30 | L32: Mercury | M32: 17 | N32: Yes (P4 is Mool — last pada of zodiac) | O32: 26°40'–30° Pisces — most critical Ganda Mool | P32: Sagittarius | Q32: 346.6667 | R32: 350 | S32: Capricorn | T32: 350 | U32: 353.3333 | V32: Aquarius | W32: 353.3333 | X32: 356.6667 | Y32: Pisces | Z32: 356.6667 | AA32: 360 | AB32: Deva | AC32: Shudra | AD32: Female | AE32: Kapha | AF32: Elephant | AG32: Moksha | AH32: Sattva | AI32: Soft / Mridu | AJ32: Ether/Akash | AK32: Completion, spiritual nourishment, and safe passage between worlds | AL32: Marine biology, foreign travel industry, animal care, spiritual guidance, nursing and palliative care, catering, children's education, aid and development work | AM32: Gentle, nourishing, and protective — shepherds others through transitions, operates with deep empathy and selfless care | AN32: Universal love, gentleness, psychic sensitivity, ability to provide safe passage, compassion | AO32: Over-sensitivity, difficulty with harsh worldly realities, tendency toward martyrdom, naivety | AP32: Nurturing, protective, gentle, spiritual, completing, compassionate
A33: Sources: BPHS Ch.94-96 (Nakshatra properties) · Brihat Samhita Ch.98 (Gana/Yoni/Nadi) · 27 Stars 27 Gods — Vic DiCara · Nakshatra Jyotish — BV Raman · Muhurtha Chintamani (auspicious times) · Career fields synthesised from deity + dasha lord karakatva + Gana — no modern projection

Sheet REF_Aspects
A1: REF_Aspects — Jyotish Aspect Rules & Calculator · Source: BPHS Ch.26 (Parashari) + KP partial aspects | Q1: =HYPERLINK("#'00_INDEX'!A1","<- Index") -> <- Index
A2: All planets aspect the 7th house (full, 100%). Mars: also 4th & 8th. Jupiter: also 5th & 9th. Saturn: also 3rd & 10th. Rahu/Ketu: also 5th & 9th (BPHS). Partial aspects (3rd/4th/5th/9th/10th/11th) are KP school — not used in Parashari scoring.
A3: Section 1 — Parashari Full Aspects (by relative house position from planet)
A4: Planet | B4: Sanskrit | C4: H1 | D4: H2 | E4: H3 | F4: H4 | G4: H5 | H4: H6 | I4: H7 | J4: H8 | K4: H9 | L4: H10 | M4: H11 | N4: H12 | O4: Special aspects | P4: Aspect notes
A5: Sun | B5: Surya | D5: · | E5: · | F5: · | G5: · | H5: · | I5: · | J5: FULL | K5: · | L5: · | M5: · | N5: · | O5: · | P5: 7th only | Q5: Aspects the 7th fully. Illuminates, burns, or empowers the aspected house depending on nature.
A6: Moon | B6: Chandramaa | D6: · | E6: · | F6: · | G6: · | H6: · | I6: · | J6: FULL | K6: · | L6: · | M6: · | N6: · | O6: · | P6: 7th only | Q6: Aspects the 7th fully. Mind and emotions flow to the aspected area. Strength varies with Paksha (waxing/waning).
A7: Mars | B7: Mangal | D7: · | E7: · | F7: · | G7: FULL | H7: · | I7: · | J7: FULL | K7: FULL | L7: · | M7: · | N7: · | O7: · | P7: 7th + H4, H8 | Q7: Three full aspects: 4th (home, property), 7th (partnerships), 8th (transformation, longevity). Energises and agitates.
A8: Mercury | B8: Budh | D8: · | E8: · | F8: · | G8: · | H8: · | I8: · | J8: FULL | K8: · | L8: · | M8: · | N8: · | O8: · | P8: 7th only | Q8: Aspects the 7th only. Brings intellect and communication. Neutral by nature — takes on character of conjunct planets.
A9: Jupiter | B9: Brihaspati | D9: · | E9: · | F9: · | G9: · | H9: FULL | I9: · | J9: FULL | K9: · | L9: FULL | M9: · | N9: · | O9: · | P9: 7th + H5, H9 | Q9: Three full aspects: 5th (children, intellect), 7th (partnerships), 9th (dharma, fortune). Expands and blesses.
A10: Venus | B10: Shukra | D10: · | E10: · | F10: · | G10: · | H10: · | I10: · | J10: FULL | K10: · | L10: · | M10: · | N10: · | O10: · | P10: 7th only | Q10: Aspects the 7th only. Brings harmony, beauty, and comfort. Strongest of all natural benefics in aspect.
A11: Saturn | B11: Shani | D11: · | E11: · | F11: FULL | G11: · | H11: · | I11: · | J11: FULL | K11: · | L11: · | M11: FULL | N11: · | O11: · | P11: 7th + H3, H10 | Q11: Three full aspects: 3rd (effort, courage), 7th (partnerships), 10th (career, karma). Delays, restricts, disciplines.
A12: Rahu | B12: Rahu | D12: · | E12: · | F12: · | G12: · | H12: FULL | I12: · | J12: FULL | K12: · | L12: FULL | M12: · | N12: · | O12: · | P12: 7th + H5, H9 | Q12: Three full aspects (per BPHS): 5th, 7th, 9th. Intensifies and makes unconventional. Always retrograde.
A13: Ketu | B13: Ketu | D13: · | E13: · | F13: · | G13: · | H13: FULL | I13: · | J13: FULL | K13: · | L13: FULL | M13: · | N13: · | O13: · | P13: 7th + H5, H9 | Q13: Three full aspects (per BPHS): 5th, 7th, 9th. Spiritualises, detaches, and karmically completes. Always retrograde.
A16: Section 2 — Aspect Strength Reference & Scoring Weights
A17: Strength | B17: % | C17: School | D17: Effect on house score | E17: Which planets / houses | F17: Scoring note
A18: Full | B18: 100% | C18: Parashari (primary) | D18: +1.0 if Shubh Greh, −1.0 if Ashubh Greh | E18: All planets → 7th. Mars → 4th/8th. Jupiter → 5th/9th. Saturn → 3rd/10th. Rahu/Ketu → 5th/9th. | F18: Use in SCORE_DrillDown Rule #3 (Shubh aspect) and Rule #10 (Ashubh aspect).
A19: 3/4 | B19: 75% | C19: KP / partial | D19: +0.5 if Shubh, −0.5 if Ashubh (WC — worth considering) | E19: All planets → 5th and 9th from themselves. | F19: Flag as WC (worth considering) in DrillDown. Not used in Parashari scoring.
A20: Half | B20: 50% | C20: KP / partial | D20: +0.25 if Shubh, −0.25 if Ashubh | E20: All planets → 4th and 10th from themselves. | F20: Weak — generally ignored in Parashari. Note only.
A21: Quarter | B21: 25% | C21: KP / partial | D21: Negligible | E21: All planets → 3rd and 11th from themselves. | F21: Too weak to affect Parashari scoring. Skip.
A22: None | B22: 0% | C22: All schools | D22: No effect | E22: All other relative house positions. | F22: No contribution to any rule.
A26: Section 3 — Aspect Calculator · For each planet in each of 12 Bhav positions, shows exactly which houses it aspects (Parashari full)
A27: Planet | B27: Sanskrit | C27: Planet in H1 | F27: Planet in H2 | I27: Planet in H3 | L27: Planet in H4 | O27: Planet in H5 | R27: Planet in H6 | U27: Planet in H7 | X27: Planet in H8 | AA27: Planet in H9 | AD27: Planet in H10 | AG27: Planet in H11 | AJ27: Planet in H12
C28: Parashari aspects (full) | D28: KP partial aspects | E28: Score note | F28: Parashari aspects (full) | G28: KP partial aspects | H28: Score note | I28: Parashari aspects (full) | J28: KP partial aspects | K28: Score note | L28: Parashari aspects (full) | M28: KP partial aspects | N28: Score note | O28: Parashari aspects (full) | P28: KP partial aspects | Q28: Score note | R28: Parashari aspects (full) | S28: KP partial aspects | T28: Score note | U28: Parashari aspects (full) | V28: KP partial aspects | W28: Score note | X28: Parashari aspects (full) | Y28: KP partial aspects | Z28: Score note | AA28: Parashari aspects (full) | AB28: KP partial aspects | AC28: Score note | AD28: Parashari aspects (full) | AE28: KP partial aspects | AF28: Score note | AG28: Parashari aspects (full) | AH28: KP partial aspects | AI28: Score note | AJ28: Parashari aspects (full) | AK28: KP partial aspects | AL28: Score note
A29: Sun | B29: Surya | C29: H7 | D29: H5(75%) H9(75%) H4(50%) H10(50%) H3(25%) H11(25%) | E29: 7th only | F29: H8 | G29: H6(75%) H10(75%) H5(50%) H11(50%) H4(25%) H12(25%) | H29: 7th only | I29: H9 | J29: H7(75%) H11(75%) H6(50%) H12(50%) H5(25%) H1(25%) | K29: 7th only | L29: H10 | M29: H8(75%) H12(75%) H7(50%) H1(50%) H6(25%) H2(25%) | N29: 7th only | O29: H11 | P29: H9(75%) H1(75%) H8(50%) H2(50%) H7(25%) H3(25%) | Q29: 7th only | R29: H12 | S29: H10(75%) H2(75%) H9(50%) H3(50%) H8(25%) H4(25%) | T29: 7th only | U29: H1 | V29: H11(75%) H3(75%) H10(50%) H4(50%) H9(25%) H5(25%) | W29: 7th only | X29: H2 | Y29: H12(75%) H4(75%) H11(50%) H5(50%) H10(25%) H6(25%) | Z29: 7th only | AA29: H3 | AB29: H1(75%) H5(75%) H12(50%) H6(50%) H11(25%) H7(25%) | AC29: 7th only | AD29: H4 | AE29: H2(75%) H6(75%) H1(50%) H7(50%) H12(25%) H8(25%) | AF29: 7th only | AG29: H5 | AH29: H3(75%) H7(75%) H2(50%) H8(50%) H1(25%) H9(25%) | AI29: 7th only | AJ29: H6 | AK29: H4(75%) H8(75%) H3(50%) H9(50%) H2(25%) H10(25%) | AL29: 7th only
A30: Moon | B30: Chandramaa | C30: H7 | D30: H5(75%) H9(75%) H4(50%) H10(50%) H3(25%) H11(25%) | E30: 7th only | F30: H8 | G30: H6(75%) H10(75%) H5(50%) H11(50%) H4(25%) H12(25%) | H30: 7th only | I30: H9 | J30: H7(75%) H11(75%) H6(50%) H12(50%) H5(25%) H1(25%) | K30: 7th only | L30: H10 | M30: H8(75%) H12(75%) H7(50%) H1(50%) H6(25%) H2(25%) | N30: 7th only | O30: H11 | P30: H9(75%) H1(75%) H8(50%) H2(50%) H7(25%) H3(25%) | Q30: 7th only | R30: H12 | S30: H10(75%) H2(75%) H9(50%) H3(50%) H8(25%) H4(25%) | T30: 7th only | U30: H1 | V30: H11(75%) H3(75%) H10(50%) H4(50%) H9(25%) H5(25%) | W30: 7th only | X30: H2 | Y30: H12(75%) H4(75%) H11(50%) H5(50%) H10(25%) H6(25%) | Z30: 7th only | AA30: H3 | AB30: H1(75%) H5(75%) H12(50%) H6(50%) H11(25%) H7(25%) | AC30: 7th only | AD30: H4 | AE30: H2(75%) H6(75%) H1(50%) H7(50%) H12(25%) H8(25%) | AF30: 7th only | AG30: H5 | AH30: H3(75%) H7(75%) H2(50%) H8(50%) H1(25%) H9(25%) | AI30: 7th only | AJ30: H6 | AK30: H4(75%) H8(75%) H3(50%) H9(50%) H2(25%) H10(25%) | AL30: 7th only
A31: Mars | B31: Mangal | C31: H4 H7 H8 | D31: H5(75%) H9(75%) H10(50%) H3(25%) H11(25%) | E31: Special: H4 (special), H8 (special) | F31: H5 H8 H9 | G31: H6(75%) H10(75%) H11(50%) H4(25%) H12(25%) | H31: Special: H5 (special), H9 (special) | I31: H6 H9 H10 | J31: H7(75%) H11(75%) H12(50%) H5(25%) H1(25%) | K31: Special: H6 (special), H10 (special) | L31: H7 H10 H11 | M31: H8(75%) H12(75%) H1(50%) H6(25%) H2(25%) | N31: Special: H7 (special), H11 (special) | O31: H8 H11 H12 | P31: H9(75%) H1(75%) H2(50%) H7(25%) H3(25%) | Q31: Special: H8 (special), H12 (special) | R31: H1 H9 H12 | S31: H10(75%) H2(75%) H3(50%) H8(25%) H4(25%) | T31: Special: H9 (special), H1 (special) | U31: H1 H2 H10 | V31: H11(75%) H3(75%) H4(50%) H9(25%) H5(25%) | W31: Special: H10 (special), H2 (special) | X31: H2 H3 H11 | Y31: H12(75%) H4(75%) H5(50%) H10(25%) H6(25%) | Z31: Special: H11 (special), H3 (special) | AA31: H3 H4 H12 | AB31: H1(75%) H5(75%) H6(50%) H11(25%) H7(25%) | AC31: Special: H12 (special), H4 (special) | AD31: H1 H4 H5 | AE31: H2(75%) H6(75%) H7(50%) H12(25%) H8(25%) | AF31: Special: H1 (special), H5 (special) | AG31: H2 H5 H6 | AH31: H3(75%) H7(75%) H8(50%) H1(25%) H9(25%) | AI31: Special: H2 (special), H6 (special) | AJ31: H3 H6 H7 | AK31: H4(75%) H8(75%) H9(50%) H2(25%) H10(25%) | AL31: Special: H3 (special), H7 (special)
A32: Mercury | B32: Budh | C32: H7 | D32: H5(75%) H9(75%) H4(50%) H10(50%) H3(25%) H11(25%) | E32: 7th only | F32: H8 | G32: H6(75%) H10(75%) H5(50%) H11(50%) H4(25%) H12(25%) | H32: 7th only | I32: H9 | J32: H7(75%) H11(75%) H6(50%) H12(50%) H5(25%) H1(25%) | K32: 7th only | L32: H10 | M32: H8(75%) H12(75%) H7(50%) H1(50%) H6(25%) H2(25%) | N32: 7th only | O32: H11 | P32: H9(75%) H1(75%) H8(50%) H2(50%) H7(25%) H3(25%) | Q32: 7th only | R32: H12 | S32: H10(75%) H2(75%) H9(50%) H3(50%) H8(25%) H4(25%) | T32: 7th only | U32: H1 | V32: H11(75%) H3(75%) H10(50%) H4(50%) H9(25%) H5(25%) | W32: 7th only | X32: H2 | Y32: H12(75%) H4(75%) H11(50%) H5(50%) H10(25%) H6(25%) | Z32: 7th only | AA32: H3 | AB32: H1(75%) H5(75%) H12(50%) H6(50%) H11(25%) H7(25%) | AC32: 7th only | AD32: H4 | AE32: H2(75%) H6(75%) H1(50%) H7(50%) H12(25%) H8(25%) | AF32: 7th only | AG32: H5 | AH32: H3(75%) H7(75%) H2(50%) H8(50%) H1(25%) H9(25%) | AI32: 7th only | AJ32: H6 | AK32: H4(75%) H8(75%) H3(50%) H9(50%) H2(25%) H10(25%) | AL32: 7th only
A33: Jupiter | B33: Brihaspati | C33: H5 H7 H9 | D33: H4(50%) H10(50%) H3(25%) H11(25%) | E33: Special: H5 (special), H9 (special) | F33: H6 H8 H10 | G33: H5(50%) H11(50%) H4(25%) H12(25%) | H33: Special: H6 (special), H10 (special) | I33: H7 H9 H11 | J33: H6(50%) H12(50%) H5(25%) H1(25%) | K33: Special: H7 (special), H11 (special) | L33: H8 H10 H12 | M33: H7(50%) H1(50%) H6(25%) H2(25%) | N33: Special: H8 (special), H12 (special) | O33: H1 H9 H11 | P33: H8(50%) H2(50%) H7(25%) H3(25%) | Q33: Special: H9 (special), H1 (special) | R33: H2 H10 H12 | S33: H9(50%) H3(50%) H8(25%) H4(25%) | T33: Special: H10 (special), H2 (special) | U33: H1 H3 H11 | V33: H10(50%) H4(50%) H9(25%) H5(25%) | W33: Special: H11 (special), H3 (special) | X33: H2 H4 H12 | Y33: H11(50%) H5(50%) H10(25%) H6(25%) | Z33: Special: H12 (special), H4 (special) | AA33: H1 H3 H5 | AB33: H12(50%) H6(50%) H11(25%) H7(25%) | AC33: Special: H1 (special), H5 (special) | AD33: H2 H4 H6 | AE33: H1(50%) H7(50%) H12(25%) H8(25%) | AF33: Special: H2 (special), H6 (special) | AG33: H3 H5 H7 | AH33: H2(50%) H8(50%) H1(25%) H9(25%) | AI33: Special: H3 (special), H7 (special) | AJ33: H4 H6 H8 | AK33: H3(50%) H9(50%) H2(25%) H10(25%) | AL33: Special: H4 (special), H8 (special)
A34: Venus | B34: Shukra | C34: H7 | D34: H5(75%) H9(75%) H4(50%) H10(50%) H3(25%) H11(25%) | E34: 7th only | F34: H8 | G34: H6(75%) H10(75%) H5(50%) H11(50%) H4(25%) H12(25%) | H34: 7th only | I34: H9 | J34: H7(75%) H11(75%) H6(50%) H12(50%) H5(25%) H1(25%) | K34: 7th only | L34: H10 | M34: H8(75%) H12(75%) H7(50%) H1(50%) H6(25%) H2(25%) | N34: 7th only | O34: H11 | P34: H9(75%) H1(75%) H8(50%) H2(50%) H7(25%) H3(25%) | Q34: 7th only | R34: H12 | S34: H10(75%) H2(75%) H9(50%) H3(50%) H8(25%) H4(25%) | T34: 7th only | U34: H1 | V34: H11(75%) H3(75%) H10(50%) H4(50%) H9(25%) H5(25%) | W34: 7th only | X34: H2 | Y34: H12(75%) H4(75%) H11(50%) H5(50%) H10(25%) H6(25%) | Z34: 7th only | AA34: H3 | AB34: H1(75%) H5(75%) H12(50%) H6(50%) H11(25%) H7(25%) | AC34: 7th only | AD34: H4 | AE34: H2(75%) H6(75%) H1(50%) H7(50%) H12(25%) H8(25%) | AF34: 7th only | AG34: H5 | AH34: H3(75%) H7(75%) H2(50%) H8(50%) H1(25%) H9(25%) | AI34: 7th only | AJ34: H6 | AK34: H4(75%) H8(75%) H3(50%) H9(50%) H2(25%) H10(25%) | AL34: 7th only
A35: Saturn | B35: Shani | C35: H3 H7 H10 | D35: H5(75%) H9(75%) H4(50%) H11(25%) | E35: Special: H3 (special), H10 (special) | F35: H4 H8 H11 | G35: H6(75%) H10(75%) H5(50%) H12(25%) | H35: Special: H4 (special), H11 (special) | I35: H5 H9 H12 | J35: H7(75%) H11(75%) H6(50%) H1(25%) | K35: Special: H5 (special), H12 (special) | L35: H1 H6 H10 | M35: H8(75%) H12(75%) H7(50%) H2(25%) | N35: Special: H6 (special), H1 (special) | O35: H2 H7 H11 | P35: H9(75%) H1(75%) H8(50%) H3(25%) | Q35: Special: H7 (special), H2 (special) | R35: H3 H8 H12 | S35: H10(75%) H2(75%) H9(50%) H4(25%) | T35: Special: H8 (special), H3 (special) | U35: H1 H4 H9 | V35: H11(75%) H3(75%) H10(50%) H5(25%) | W35: Special: H9 (special), H4 (special) | X35: H2 H5 H10 | Y35: H12(75%) H4(75%) H11(50%) H6(25%) | Z35: Special: H10 (special), H5 (special) | AA35: H3 H6 H11 | AB35: H1(75%) H5(75%) H12(50%) H7(25%) | AC35: Special: H11 (special), H6 (special) | AD35: H4 H7 H12 | AE35: H2(75%) H6(75%) H1(50%) H8(25%) | AF35: Special: H12 (special), H7 (special) | AG35: H1 H5 H8 | AH35: H3(75%) H7(75%) H2(50%) H9(25%) | AI35: Special: H1 (special), H8 (special) | AJ35: H2 H6 H9 | AK35: H4(75%) H8(75%) H3(50%) H10(25%) | AL35: Special: H2 (special), H9 (special)
A36: Rahu | B36: Rahu | C36: H5 H7 H9 | D36: H4(50%) H10(50%) H3(25%) H11(25%) | E36: Special: H5 (special), H9 (special) | F36: H6 H8 H10 | G36: H5(50%) H11(50%) H4(25%) H12(25%) | H36: Special: H6 (special), H10 (special) | I36: H7 H9 H11 | J36: H6(50%) H12(50%) H5(25%) H1(25%) | K36: Special: H7 (special), H11 (special) | L36: H8 H10 H12 | M36: H7(50%) H1(50%) H6(25%) H2(25%) | N36: Special: H8 (special), H12 (special) | O36: H1 H9 H11 | P36: H8(50%) H2(50%) H7(25%) H3(25%) | Q36: Special: H9 (special), H1 (special) | R36: H2 H10 H12 | S36: H9(50%) H3(50%) H8(25%) H4(25%) | T36: Special: H10 (special), H2 (special) | U36: H1 H3 H11 | V36: H10(50%) H4(50%) H9(25%) H5(25%) | W36: Special: H11 (special), H3 (special) | X36: H2 H4 H12 | Y36: H11(50%) H5(50%) H10(25%) H6(25%) | Z36: Special: H12 (special), H4 (special) | AA36: H1 H3 H5 | AB36: H12(50%) H6(50%) H11(25%) H7(25%) | AC36: Special: H1 (special), H5 (special) | AD36: H2 H4 H6 | AE36: H1(50%) H7(50%) H12(25%) H8(25%) | AF36: Special: H2 (special), H6 (special) | AG36: H3 H5 H7 | AH36: H2(50%) H8(50%) H1(25%) H9(25%) | AI36: Special: H3 (special), H7 (special) | AJ36: H4 H6 H8 | AK36: H3(50%) H9(50%) H2(25%) H10(25%) | AL36: Special: H4 (special), H8 (special)
A37: Ketu | B37: Ketu | C37: H5 H7 H9 | D37: H4(50%) H10(50%) H3(25%) H11(25%) | E37: Special: H5 (special), H9 (special) | F37: H6 H8 H10 | G37: H5(50%) H11(50%) H4(25%) H12(25%) | H37: Special: H6 (special), H10 (special) | I37: H7 H9 H11 | J37: H6(50%) H12(50%) H5(25%) H1(25%) | K37: Special: H7 (special), H11 (special) | L37: H8 H10 H12 | M37: H7(50%) H1(50%) H6(25%) H2(25%) | N37: Special: H8 (special), H12 (special) | O37: H1 H9 H11 | P37: H8(50%) H2(50%) H7(25%) H3(25%) | Q37: Special: H9 (special), H1 (special) | R37: H2 H10 H12 | S37: H9(50%) H3(50%) H8(25%) H4(25%) | T37: Special: H10 (special), H2 (special) | U37: H1 H3 H11 | V37: H10(50%) H4(50%) H9(25%) H5(25%) | W37: Special: H11 (special), H3 (special) | X37: H2 H4 H12 | Y37: H11(50%) H5(50%) H10(25%) H6(25%) | Z37: Special: H12 (special), H4 (special) | AA37: H1 H3 H5 | AB37: H12(50%) H6(50%) H11(25%) H7(25%) | AC37: Special: H1 (special), H5 (special) | AD37: H2 H4 H6 | AE37: H1(50%) H7(50%) H12(25%) H8(25%) | AF37: Special: H2 (special), H6 (special) | AG37: H3 H5 H7 | AH37: H2(50%) H8(50%) H1(25%) H9(25%) | AI37: Special: H3 (special), H7 (special) | AJ37: H4 H6 H8 | AK37: H3(50%) H9(50%) H2(25%) H10(25%) | AL37: Special: H4 (special), H8 (special)
A41: Section 4 — Formula patterns for CALC_PlanetPositions
A42: Question | B42: Formula / approach
A43: Does planet P aspect house H? | J43: Check the static reference table (Section 1) — scan row for planet, check if H{n} col = FULL
A44: Get all houses aspected by planet in BhavN | B44: Read from calculator (Section 3): row = planet, column group = Bhav position × 3 + base offset | J44: Each planet-Bhav group has 3 cols. Parashari aspects in col 1 of each group.
A45: Check if house H is aspected by Shubh planet | B45: Loop planets list → for each Shubh planet → check if H in their aspected houses list → flag | J45: Used in SCORE_DrillDown Rule #3: Shubh Greh aspecting house = +1 Bhav Bal (WC)
A46: Check if house H is aspected by Ashubh planet | B46: Same pattern but for Ashubh planets from REF_ShubhAshubh | J46: Used in SCORE_DrillDown Rule #10: Ashubh Greh aspecting house = −1 Bhav Durbal
A47: Check if Bhavesh (house lord) is aspected by Shubh | B47: Get Bhavesh position from CALC_BhaveshMap → check aspect calculator for that Bhav | J47: Used in Rule #7: Bhavesh aspected by Shubh = +1 Bhavesh Bal (WC)

Sheet REF_Houses
A1: REF_Houses — Complete Bhava Reference · 12 houses × 39 attributes · Sources: BPHS Ch.11-12, Saravali Ch.2, Uttara Kalamrita Ch.4, Phala Deepika Ch.3
A2: READ-ONLY. CALC_BhaveshMap: =INDEX(REF_Houses!$B$6:$B$17, house_num) · Scoring flags (Group G, cols 27-39) feed SCORE_DrillDown rules directly. Kendra=H1/4/7/10 · Trikon=H1/5/9 · Dukshthan=H6/8/12 · Upachaya=H3/6/10/11 · Markesh=H2/H7 | AS2: =HYPERLINK("#'00_INDEX'!A1","← Index") -> ← Index
A3: A — Identity | F3: B — Classification | N3: C — Significations | S3: D — Sthir Karakas | V3: E — Bhavat Bhavam | X3: F — Natural sign | AA3: G — Scoring flags
B4: Name | C4: Sanskrit | D4: Short name | E4: Symbol | F4: Kendra? | G4: Trikon? | H4: Dukshthan? | I4: Upachaya? | J4: Markesh? | K4: Apoklima? | L4: Purushartha | M4: Odd/Even | N4: Primary meaning | O4: Secondary | P4: Relationships | Q4: Body parts | R4: Life domain | S4: Primary Karak | T4: Secondary Karak | U4: Karak note | V4: Bhavat Bhavam H# | W4: Bhavat meaning | X4: Natural sign | Y4: Natural lord | Z4: Element | AA4: Is Kendra | AB4: Is Trikon | AC4: Is Dukshthan | AD4: Is Upachaya | AE4: Is Markesh | AF4: Duksh lord harms | AG4: Shubh here good | AH4: Ashubh harms here | AI4: Strong lord good | AJ4: Weak lord bad | AK4: Raja Yoga house | AL4: Dhana Yoga house | AM4: Moksha house | AN4: Scoring note
A5: Krama | B5: Naam | C5: Sanskrit | D5: Sankhep | E5: Pratik | F5: Kendra | G5: Trikon | H5: Dukh | I5: Upachaya | J5: Marak | K5: Apoklima | L5: Purushath | M5: Vishama/Sama | N5: Mukhya Artha | O5: Goun Artha | P5: Sambandh | Q5: Sharira Anga | R5: Jeevan Kshetra | S5: Mukhya Karak | T5: Goun Karak | U5: Karak Vivek | V5: Bhavat | W5: Bhavat Artha | X5: Naisargik Rashi | Y5: Swami | Z5: Tattva | AA5: Kendra | AB5: Trikon | AC5: Dukh | AD5: Upachaya | AE5: Marak | AF5: Dukh Prabhu | AG5: Shubh Sthiti | AH5: Ashubh Sthiti | AI5: Bal Bhavesh | AJ5: Dur Bhavesh | AK5: Raja Yoga | AL5: Dhana Yoga | AM5: Moksha | AN5: Vivran
A6: 1 | B6: Self / Lagna | C6: Tanu Bhava | D6: Lagna | E6: Body, vitality, identity | F6: Yes | G6: Yes | H6: · | I6: · | J6: · | K6: · | L6: Dharma | M6: Odd (1st) | N6: Self, physical body, personality, appearance, vitality, character, overall life direction, first impressions, the soul's vehicle | O6: Head, complexion, height, constitution, longevity (along with H8), self-confidence, early childhood, new beginnings, fame, status | P6: Self — no relationship signified, but Lagnesh rules all life themes | Q6: Head, brain, face, hair, skull, right eye (in some traditions) | R6: Identity, health, vitality, overall fortune | S6: Sun (soul, vitality, self-expression) | T6: — | U6: Lagnesh (lord of H1) is the most important planet in the chart | V6: H1 | W6: H1 from H1 = itself — self-referential house; reinforces core identity | X6: Aries | Y6: Mars | Z6: Fire | AA6: Yes | AB6: Yes | AC6: · | AD6: · | AE6: · | AF6: · | AG6: Yes | AH6: Yes | AI6: Yes | AJ6: Yes | AK6: Yes | AL6: · | AM6: · | AN6: Kendra + Trikon overlap → maximum weight in all scoring rules
A7: 2 | B7: Wealth / Dhana | C7: Dhana Bhava | D7: Dhana | E7: Treasure chest | F7: · | G7: · | H7: · | I7: · | J7: Yes | K7: · | L7: Artha | M7: Even (2nd) | N7: Accumulated wealth, family, speech, values and ethics, self-esteem, food habits, right eye, face, early childhood memories | O7: Savings, fixed assets, family lineage, mother tongue, oral traditions, honesty, what one eats, possessions, precious metals, gemstones | P7: Family (kutumb) — close family unit, not extended | Q7: Face, right eye, teeth, tongue, throat, neck, vocal cords | R7: Wealth, family values, speech | S7: Jupiter (wealth, expansion) | T7: Mercury (speech, communication) | U7: Jupiter as Dhana Karak; Mercury for Vak (speech) Karak | V7: H3 | W7: H2 from H2 = H3 — younger siblings echo through the wealth house | X7: Taurus | Y7: Venus | Z7: Earth | AA7: · | AB7: · | AC7: · | AD7: · | AE7: Yes | AF7: · | AG7: Yes | AH7: Yes | AI7: Yes | AJ7: Yes | AK7: · | AL7: Yes | AM7: · | AN7: Markesh: Bhavesh rules death/endings. Maraka planets in H2 reduce vitality.
A8: 3 | B8: Courage / Parakrama | C8: Parakrama Bhava | D8: Parakrama | E8: Sword / arm | F8: · | G8: · | H8: · | I8: Yes | J8: · | K8: Yes | L8: Kama | M8: Odd (3rd) | N8: Courage, initiative, siblings (especially younger), communication, short journeys, skills, hobbies, neighbours | O8: Writing, media, social media, arms and hands, left ear, sports, self-employment, contracts, early education, mental agility | P8: Younger siblings, neighbours, colleagues | Q8: Arms, hands, shoulders, upper chest, right ear, nervous system | R8: Courage, communication, skills, siblings | S8: Mars (courage, siblings, energy) | T8: Mercury (communication, writing) | U8: Mars is primary Karak; Mercury for all communication significations | V8: H5 | W8: H3 from H3 = H5 — effort and creativity are linked | X8: Gemini | Y8: Mercury | Z8: Air | AA8: · | AB8: · | AC8: · | AD8: Yes | AE8: · | AF8: · | AG8: Yes | AH8: · | AI8: Yes | AJ8: Yes | AK8: · | AL8: · | AM8: · | AN8: Upachaya: improves with age. Malefics here can be beneficial (Mars in H3 = courage).
A9: 4 | B9: Home / Sukha | C9: Sukha Bhava | D9: Sukha | E9: House / chariot | F9: Yes | G9: · | H9: · | I9: · | J9: · | K9: · | L9: Moksha | M9: Even (4th) | N9: Mother, home and homeland, happiness, emotional security, property and real estate, vehicles, education, heart | O9: Inner peace, domestic comfort, roots, agricultural land, wells and water bodies, chests and buried treasure, end of life (along with H12), foundational beliefs | P9: Mother, maternal figures, domestic partners | Q9: Chest, lungs, breasts, heart, stomach | R9: Home, happiness, property, mother | S9: Moon (mother, emotions, nourishment) | T9: Mercury (education, vehicles) | U9: Moon is primary Karak for mother and happiness; Mercury for academic education | V9: H7 | W9: H4 from H4 = H7 — home and partnership mirror each other | X9: Cancer | Y9: Moon | Z9: Water | AA9: Yes | AB9: · | AC9: · | AD9: · | AE9: · | AF9: · | AG9: Yes | AH9: Yes | AI9: Yes | AJ9: Yes | AK9: Yes | AL9: · | AM9: Yes | AN9: Kendra of Moksha. Saturn and Mars in H4 classically harm domestic happiness.
A10: 5 | B10: Intellect / Putra | C10: Putra Bhava | D10: Putra | E10: Child / scroll | F10: · | G10: Yes | H10: · | I10: · | J10: · | K10: · | L10: Dharma | M10: Odd (5th) | N10: Children, intellect, creativity, romance, speculation, past-life merit (Purva Punya), higher education, mantras | O10: Stock market, gambling, games of chance, political power, counselling, sports, artistic performance, stomach, love affairs | P10: Children, students, lovers (pre-marriage), disciples | Q10: Stomach, upper abdomen, liver (in some traditions), spine | R10: Creativity, children, intelligence, fortune | S10: Jupiter (children, wisdom, fortune) | T10: — | U10: Jupiter is the primary Sthir Karak for H5 — its placement is critical | V10: H9 | W10: H5 from H5 = H9 — creativity and dharma are reflections of each other | X10: Leo | Y10: Sun | Z10: Fire | AA10: · | AB10: Yes | AC10: · | AD10: · | AE10: · | AF10: · | AG10: Yes | AH10: Yes | AI10: Yes | AJ10: Yes | AK10: Yes | AL10: · | AM10: · | AN10: Trikon of Dharma. H5 lord with H9 or H1 lord = powerful Raja Yoga.
A11: 6 | B11: Conflicts / Shatru | C11: Shatru / Ari Bhava | D11: Shatru | E11: Sword / debt | F11: · | G11: · | H11: Yes | I11: Yes | J11: · | K11: Yes | L11: Artha | M11: Even (6th) | N11: Enemies, debts, diseases, litigation, obstacles, service, daily work habits, pets and small animals | O11: Maternal uncle, step-mother, competition, court cases, accidents, hospital stays, digestive disorders, tenants | P11: Enemies (open), maternal uncle, servants, employees | Q11: Lower abdomen, intestines, appendix, kidneys (along with H7) | R11: Health challenges, enemies, debts, service | S11: Mars (enemies, conflicts, energy for overcoming) | T11: Saturn (service, discipline, chronic illness) | U11: Strong H6 Bhavesh = ability to defeat enemies. Malefics in H6 can be good. | V11: H11 | W11: H6 from H6 = H11 — gains come through overcoming obstacles | X11: Virgo | Y11: Mercury | Z11: Earth | AA11: · | AB11: · | AC11: Yes | AD11: Yes | AE11: · | AF11: Yes | AG11: · | AH11: · | AI11: · | AJ11: · | AK11: · | AL11: · | AM11: · | AN11: Dukshthan + Upachaya: malefics here improve with time. H6 lord powerful = enemies defeated.
A12: 7 | B12: Partnerships / Kalatra | C12: Kalatra Bhava | D12: Kalatra | E12: Two figures / scales | F12: Yes | G12: · | H12: · | I12: · | J12: Yes | K12: · | L12: Kama | M12: Odd (7th) | N12: Spouse, marriage, business partnerships, legal contracts, open enemies, the public | O12: Sexual relationships, desire, trade partnerships, diplomacy, kidneys, the foreign land, long journeys, lower back | P12: Spouse (primary), business partner, open rivals | Q12: Lower back, kidneys, bladder, groins, navel area | R12: Marriage, partnerships, public dealings | S12: Venus (marriage, desire, harmony) | T12: Jupiter (husband for female charts) | U12: Venus primary Karak for marriage; Jupiter as husband Karak in female charts | V12: H1 | W12: H7 from H7 = H1 — the partner mirrors the self | X12: Libra | Y12: Venus | Z12: Air | AA12: Yes | AB12: · | AC12: · | AD12: · | AE12: Yes | AF12: · | AG12: Yes | AH12: Yes | AI12: Yes | AJ12: Yes | AK12: Yes | AL12: · | AM12: · | AN12: Kendra + Markesh. Strong benefics here bless marriage; Markesh placement weakens longevity.
A13: 8 | B13: Longevity / Ayu | C13: Ayu / Randhra Bhava | D13: Ayu | E13: Serpent / cycle | F13: · | G13: · | H13: Yes | I13: · | J13: · | K13: Yes | L13: Moksha | M13: Even (8th) | N13: Longevity, transformation, inheritance, occult sciences, hidden matters, sudden events, research, the subconscious | O13: Death and rebirth, chronic disease, sexual organs, in-laws' wealth, taxes, insurance, mysticism, past lives | P13: In-laws (spouse's family), hidden enemies | Q13: Genitals, excretory organs, urethra, anus, lower spine | R13: Longevity, transformation, hidden matters, inheritance | S13: Saturn (longevity, chronic conditions, karma) | T13: — | U13: Saturn is the primary Ayu Karak. H8 is one of the most complex houses to interpret. | V13: H3 | W13: H8 from H8 = H3 — longevity connects to courage and willpower | X13: Scorpio | Y13: Mars | Z13: Water | AA13: · | AB13: · | AC13: Yes | AD13: · | AE13: · | AF13: Yes | AG13: · | AH13: · | AI13: · | AJ13: Yes | AK13: · | AL13: · | AM13: Yes | AN13: Worst Dukshthan. Viparita Raja Yoga: H8 lord in H6/H8/H12 = unexpected rise.
A14: 9 | B14: Fortune / Bhagya | C14: Bhagya / Dharma Bhava | D14: Bhagya | E14: Temple / teacher | F14: · | G14: Yes | H14: · | I14: · | J14: · | K14: · | L14: Dharma | M14: Odd (9th) | N14: Fortune, father, guru, dharma, higher wisdom, long journeys, spirituality, higher education, law, philosophy | O14: Grandchildren, elder siblings (in some traditions), publishing, ethics, religion, foreign travel, luck, cross-cultural exchanges, pilgrimage | P14: Father, guru/teacher, grandchildren | Q14: Thighs, hips, right leg | R14: Fortune, dharma, father, spirituality | S14: Jupiter (dharma, wisdom, fortune, teacher) | T14: Sun (father, authority, soul's dharma) | U14: Jupiter and Sun share Karak status — H9 is the most auspicious Trikon | V14: H5 | W14: H9 from H9 = H5 — dharma and creativity mirror each other | X14: Sagittarius | Y14: Jupiter | Z14: Fire | AA14: · | AB14: Yes | AC14: · | AD14: · | AE14: · | AF14: · | AG14: Yes | AH14: Yes | AI14: Yes | AJ14: Yes | AK14: Yes | AL14: · | AM14: · | AN14: Strongest Trikon. H9 lord with H1/H5/H10 lord = powerful Raja Yoga.
A15: 10 | B15: Career / Karma | C15: Karma / Rajya Bhava | D15: Karma | E15: Crown / mountain peak | F15: Yes | G15: · | H15: · | I15: Yes | J15: · | K15: · | L15: Artha | M15: Even (10th) | N15: Career, profession, public status, authority, government, actions in the world, reputation, one's karma / life work | O15: Father's profession, employer, knees, spine, honours and awards, long-term goals, public image | P15: Employer, authority figures, father's professional life | Q15: Knees, kneecap, spine (along with H1) | R15: Career, reputation, public life, authority | S15: Sun (authority, leadership, soul's purpose) | T15: Saturn (karma, discipline, career through effort) | U15: Mercury (business/intellect) and Jupiter (advisory roles) also serve as secondary Karakas. Four planets share H10 Karak status. | V15: H7 | W15: H10 from H10 = H7 — career and partnerships support each other | X15: Capricorn | Y15: Saturn | Z15: Earth | AA15: Yes | AB15: · | AC15: · | AD15: Yes | AE15: · | AF15: · | AG15: Yes | AH15: Yes | AI15: Yes | AJ15: Yes | AK15: Yes | AL15: · | AM15: · | AN15: Strongest Kendra + Upachaya. Planets here gain Dig Bala (Mercury/Jupiter). Saturn aspects own house.
A16: 11 | B16: Gains / Labha | C16: Labha Bhava | D16: Labha | E16: Overflowing vessel | F16: · | G16: · | H16: · | I16: Yes | J16: · | K16: · | L16: Kama | M16: Odd (11th) | N16: Income, gains, fulfilment of desires, elder siblings, friends, social networks, aspirations, recovery from illness | O16: Left ear, left arm, ankles, collective efforts, humanitarian causes, technology, political connections, profits from all sources | P16: Elder siblings, friends, social circle, patrons | Q16: Left leg, ankles, calves, left ear, left arm | R16: Income, gains, desires, social connections | S16: Jupiter (expansion, gains, abundance) | T16: — | U16: Jupiter governs all forms of gain. Strong H11 with Jupiter = consistent income. | V16: H9 | W16: H11 from H11 = H9 — gains and fortune are mirrors | X16: Aquarius | Y16: Saturn | Z16: Air | AA16: · | AB16: · | AC16: · | AD16: Yes | AE16: · | AF16: · | AG16: Yes | AH16: · | AI16: Yes | AJ16: Yes | AK16: · | AL16: Yes | AM16: · | AN16: Upachaya: improves over time. All planets gain strength in H11. Malefics here can bring income.
A17: 12 | B17: Liberation / Vyaya | C17: Vyaya / Moksha Bhava | D17: Vyaya | E17: Empty vessel / door | F17: · | G17: · | H17: Yes | I17: · | J17: · | K17: Yes | L17: Moksha | M17: Even (12th) | N17: Expenses, losses, isolation, foreign lands, liberation (moksha), spirituality, the subconscious, hospitals, prisons, ashrams | O17: Sleep, dreams, left eye, feet, secret enemies, exile, long-distance travel (especially overseas), surrender, bed pleasures, behind-the-scenes activity | P17: Hidden enemies, secret lovers, spiritual guides | Q17: Feet, left eye, lymphatic system | R17: Spirituality, losses, foreign lands, liberation | S17: Saturn (karma, isolation, endings, moksha) | T17: Ketu (liberation, detachment, past-life completion) | U17: Ketu is the natural Moksha Karak. Saturn governs the experiences that lead to liberation. | V17: H11 | W17: H12 from H12 = H11 — liberation and gains are inversely linked | X17: Pisces | Y17: Jupiter | Z17: Water | AA17: · | AB17: · | AC17: Yes | AD17: · | AE17: · | AF17: Yes | AG17: · | AH17: · | AI17: · | AJ17: Yes | AK17: · | AL17: · | AM17: Yes | AN17: Dukshthan of Moksha. Viparita RY: H12 lord in H6/H8/H12 = unexpected spiritual rise.
A18: Sources: BPHS Ch.11-12 (Bhava significations + Karakas) · Saravali Ch.2 · Uttara Kalamrita Ch.4 · Phala Deepika Ch.3 (Classification) · Jataka Parijata Ch.2 (Bhavat Bhavam) · Scoring flags (Group G) derived from classical rules: Kendra lords form RY with Trikon lords; Dukshthan lords act as malefics; Upachaya houses improve with strong malefics over time.

Sheet REF_NaisargikaFriendship
A1: REF_NaisargikaFriendship — Permanent Planetary Friendship Matrix · Source: BPHS Ch.3 (Graha Maitri Chakra) | P1: =HYPERLINK("#'00_INDEX'!A1","<- Index") -> <- Index
A2: Read as: row planet views column planet. F = Mitra (Friend) · N = Sama (Neutral) · E = Shatru (Enemy) · Relationships are NOT always reciprocal — 22 asymmetric pairs exist. This feeds CALC_PanchadhaMaitri which combines with Tatkalik to get the 5-fold result.
A3: Section 1 — Naisargika (Permanent) Friendship Matrix · Row views Column | L3: Section 2 — Asymmetric Pairs (22 total) · Why the relationship differs by direction
A4: Planet (row views →) | B4: Sanskrit | C4: Sun | D4: Moon | E4: Mars | F4: Mercury | G4: Jupiter | H4: Venus | I4: Saturn | L4: Planet A views B | M4: A→B | N4: B→A | O4: Why it differs (classical reasoning)
A5: Sun | B5: Surya | C5: — | D5: Friend | E5: Friend | F5: Neutral * | G5: Friend | H5: Enemy | I5: Enemy | L5: Moon ↔ Venus | M5: Moon→N | N5: Venus→E | O5: Moon is neutral to Venus; Venus dislikes Moon (Moon's water cools Venus's pleasures) — enemy.
A6: Moon | B6: Chandramaa | C6: Friend | D6: — | E6: Neutral * | F6: Friend * | G6: Neutral * | H6: Neutral * | I6: Neutral * | L6: Moon ↔ Saturn | M6: Moon→N | N6: Saturn→E | O6: Moon is neutral to Saturn; Saturn opposes Moon (cold darkness vs nurturing emotion) — enemy.
A7: Mars | B7: Mangal | C7: Friend | D7: Friend * | E7: — | F7: Enemy * | G7: Friend | H7: Neutral | I7: Neutral * | L7: Mars ↔ Moon | M7: Mars→F | N7: Moon→N | O7: Moon (sensitive) sees Mars (aggressive) as neutral; Mars respects Moon as its queen and considers it a friend.
A8: Mercury | B8: Budh | C8: Friend * | D8: Enemy * | E8: Neutral * | F8: — | G8: Neutral * | H8: Friend | I8: Neutral * | L8: Mars ↔ Mercury | M8: Mars→E | N8: Mercury→N | O8: Mars considers Mercury an enemy (opposite natures: aggression vs intellect); Mercury sees Mars as neutral.
A9: Jupiter | B9: Brihaspati | C9: Friend | D9: Friend * | E9: Friend | F9: Enemy * | G9: — | H9: Enemy * | I9: Neutral | L9: Mars ↔ Saturn | M9: Mars→N | N9: Saturn→E | O9: Mars sees Saturn as neutral (both dry/hot in different ways); Saturn actively opposes Mars — enemy.
A10: Venus | B10: Shukra | C10: Enemy | D10: Enemy * | E10: Neutral | F10: Friend | G10: Neutral * | H10: — | I10: Friend | L10: Mercury ↔ Sun | M10: Mercury→F | N10: Sun→N | O10: Sun sees Mercury as neutral (too fast, erratic); Mercury reveres Sun as king and considers it a friend.
A11: Saturn | B11: Shani | C11: Enemy | D11: Enemy * | E11: Enemy * | F11: Friend * | G11: Neutral | H11: Friend | I11: — | L11: Mercury ↔ Moon | M11: Mercury→E | N11: Moon→F | O11: Mercury considers Moon an enemy (unstable mind blocks clear intellect); Moon considers Mercury a friend.
L12: Mercury ↔ Saturn | M12: Mercury→N | N12: Saturn→F | O12: Mercury sees Saturn as neutral; Saturn values Mercury's analytical mind — friend.
A13: F = Friend (Mitra) · N = Neutral (Sama) · E = Enemy (Shatru) · * = Asymmetric pair (reverse relationship differs) · — = Self | L13: Jupiter ↔ Moon | M13: Jupiter→F | N13: Moon→N | O13: Jupiter considers Moon a friend; Moon sees Jupiter as neutral (does not actively reciprocate devotion).
L14: Jupiter ↔ Mercury | M14: Jupiter→E | N14: Mercury→N | O14: Jupiter considers Mercury an enemy; Mercury sees Jupiter as neutral (technical vs philosophical).
L15: Jupiter ↔ Venus | M15: Jupiter→E | N15: Venus→N | O15: Jupiter views Venus as an enemy (dharma vs desire); Venus sees Jupiter as neutral (does not oppose wisdom).
A16: Section 3 — Panchadha Maitri: Combining Naisargika + Tatkalik → 5-fold Result · BPHS Ch.15
A17: Tatkalik (temporary) friendship: planets in houses 2/3/4/10/11/12 from each other = temporary friends. Planets in 1/5/6/7/8/9 from each other = temporary enemies. Combine with Naisargika below to get the working Panchadha relationship.
A18: ↓ Naisargika / Tatkalik → | B18: Tatkalik F (Temp Friend) | C18: Tatkalik N (Neutral) | D18: Tatkalik E (Temp Enemy)
A19: Naisargika F (Permanent Friend) | B19: Adhi Mitra | C19: Mitra | D19: Sama
A20: Naisargika N (Neutral) | B20: Mitra | C20: Sama | D20: Shatru
A21: Naisargika E (Enemy) | B21: Sama | C21: Shatru | D21: Adhi Shatru
A22: 5-fold levels in descending order of strength: Adhi Mitra > Mitra > Sama > Shatru > Adhi Shatru · Panchadha Maitri governs ALL inter-planetary strength modifiers in Shadbala.
A25: Section 4 — Scoring Weights for CALC_PanchadhaMaitri
A26: Panchadha level | B26: Sanskrit | C26: Weight | D26: Used in SCORE_AllHouses | E26: Interpretation
A27: Adhi Mitra | B27: Great Friend | C27: +1.0 | D27: When Bhavesh or Karak is with/aspected by its Adhi Mitra → full Bhavesh_Bal bonus | E27: Best possible inter-planetary support. Planet performs at maximum potential.
A28: Mitra | B28: Friend | C28: +0.5 | D28: Bhavesh or Karak with/aspected by Mitra → partial Bhavesh_Bal bonus | E28: Supportive relationship. Planet functions well with mild amplification.
A29: Sama | B29: Neutral | C29: 0.0 | D29: No modification to Bhavesh_Bal or Karak_Bal | E29: Neither helped nor harmed. Planet's own strength is the deciding factor.
A30: Shatru | B30: Enemy | C30: -0.5 | D30: Bhavesh or Karak with/aspected by Shatru → partial Bhavesh_Durbal penalty | E30: Undermining relationship. Planet's significations are subtly blocked.
A31: Adhi Shatru | B31: Bitter Enemy | C31: -1.0 | D31: Bhavesh or Karak with/aspected by Adhi Shatru → full Bhavesh_Durbal penalty | E31: Worst inter-planetary conflict. Strong affliction to the aspected planet's significations.

Sheet REF_ShubhAshubh
A1: REF — Functional Benefic / Malefic by Lagna | N1: =HYPERLINK("#'00_INDEX'!A1","<- Index") -> <- Index
A2: Natural benefics (Jupiter, Venus, Mercury, Moon) become malefic when they own a Kendra AND a Dukshthan. Natural malefics (Sun, Mars, Saturn) can become benefic as Kendra lords for certain Lagnas (Yogakaraka).
A4: Planet | B4: Aries | C4: Taurus | D4: Gemini | E4: Cancer | F4: Leo | G4: Virgo | H4: Libra | I4: Scorpio | J4: Sagittarius | K4: Capricorn | L4: Aquarius | M4: Pisces
A5: Sun | B5: Neutral | C5: Malefic | D5: Malefic | E5: Benefic | F5: Benefic | G5: Neutral | H5: Malefic | I5: Neutral | J5: Benefic | K5: Malefic | L5: Neutral | M5: Neutral
A6: Moon | B6: Benefic | C6: Yogakaraka | D6: Neutral | E6: Benefic | F6: Neutral | G6: Malefic | H6: Benefic | I6: Neutral | J6: Benefic | K6: Neutral | L6: Malefic | M6: Benefic
A7: Mars | B7: Benefic | C7: Malefic | D7: Malefic | E7: Yogakaraka | F7: Yogakaraka | G7: Malefic | H7: Malefic | I7: Benefic | J7: Malefic | K7: Yogakaraka | L7: Yogakaraka | M7: Malefic
A8: Mercury | B8: Neutral | C8: Benefic | D8: Benefic | E8: Malefic | F8: Malefic | G8: Benefic | H8: Benefic | I8: Malefic | J8: Malefic | K8: Benefic | L8: Benefic | M8: Malefic
A9: Jupiter | B9: Benefic | C9: Malefic | D9: Malefic | E9: Benefic | F9: Benefic | G9: Malefic | H9: Malefic | I9: Benefic | J9: Benefic | K9: Malefic | L9: Malefic | M9: Benefic
A10: Venus | B10: Malefic | C10: Benefic | D10: Benefic | E10: Malefic | F10: Malefic | G10: Yogakaraka | H10: Benefic | I10: Yogakaraka | J10: Malefic | K10: Benefic | L10: Benefic | M10: Malefic
A11: Saturn | B11: Malefic | C11: Yogakaraka | D11: Yogakaraka | E11: Malefic | F11: Malefic | G11: Benefic | H11: Benefic | I11: Malefic | J11: Benefic | K11: Benefic | L11: Yogakaraka | M11: Malefic
A12: Rahu | B12: Malefic | C12: Malefic | D12: Neutral | E12: Malefic | F12: Malefic | G12: Neutral | H12: Neutral | I12: Malefic | J12: Neutral | K12: Malefic | L12: Neutral | M12: Malefic
A13: Ketu | B13: Malefic | C13: Malefic | D13: Neutral | E13: Malefic | F13: Malefic | G13: Neutral | H13: Neutral | I13: Malefic | J13: Neutral | K13: Malefic | L13: Neutral | M13: Malefic
A15: ⬇ LIVE LAGNA VERIFICATION
A16: Active Lagna: | B16: =INPUT_Chart!C5 -> Taurus | C16: Active column in this table: | D16: =IF(INPUT_Chart!C5="Aries","B",IF(INPUT_Chart!C5="Taurus","C",IF(INPUT_Chart!C5="Gemini","D",IF(INPUT_Chart!C5="Cancer","E",IF(INPUT_Chart!C5="Leo","F",IF(INPUT_Chart!C5="Virgo","G",IF(INPUT_Chart!C5="Libra","H",IF(INPUT_Chart!C5="Scorpio","I",IF(INPUT_Chart!C5="Sagittarius","J",IF(INPUT_Chart!C5="Capricorn","K",IF(INPUT_Chart!C5="Aquarius","L","M — Pisces"))))))))))) -> C
A17: All 60 SCORE_H* sheets read functional nature from this table via INDEX(REF_ShubhAshubh, MATCH(planet,A:A,0), MATCH(INPUT_Chart!$C$5,row4,0)). When Lagna changes, all SCORE_H* sheets re-read automatically — design is sound. This row provides a live sanity check.

Sheet REF_DivisionalRules
A1: REF_DivisionalRules · Varga Chart Arithmetic | L1: =HYPERLINK("#'00_INDEX'!A1","<- Index") -> <- Index
A2: Each Varga divides every sign into N equal parts. The part-number + starting sign produces the output sign. D9 Navamsha is most important; D10 for career; others noted below.
A3: Varga | B3: Name | C3: Divisions | D3: Each part | E3: Excel formula (sign=1–12 deg=0–29) | F3: Use in Jyotish
A4: D1 | B4: Rashi — birth chart | C4: 1 | D4: 30° | E4: sign_number (= MATCH(sign, signs_array, 0)) | F4: Foundation. All existing Lagna analysis uses D1.
A5: D9 | B5: Navamsha | C5: 9 | D5: 3°20' | E5: MOD( CHOOSE(sign, 0,9,6,3, 0,9,6,3, 0,9,6,3) + INT(deg / 3.333) , 12) + 1 | F5: Marriage · dharma · inner nature. Already in CALC_PlanetPositions col H.
A6: D10 | B6: Dashamsha | C6: 10 | D6: 3° | E6: MOD( (sign-1)*10 + INT(deg/3) , 12) + 1 [odd→Aries, even→Capricorn] | F6: Career · profession · public status.
A7: D12 | B7: Dwadashamsha | C7: 12 | D7: 2°30' | E7: MOD( (sign-1)*12 + INT(deg/2.5) , 12) + 1 | F7: Parents · ancestors · family karma.
A8: D7 | B8: Saptamsha | C8: 7 | D8: 4°17' | E8: MOD( (sign-1)*7 + INT(deg*7/30) , 12) + 1 | F8: Children · progeny.
A9: D3 | B9: Drekkana | C9: 3 | D9: 10° | E9: MOD( (sign-1)*3 + INT(deg/10) , 12) + 1 | F9: Siblings · courage · communication.
A10: D60 | B10: Shastiamsha | C10: 60 | D10: 30' | E10: MOD( INT(deg*2) + (sign-1) , 60) + 1 (60-sign cycle) | F10: Karmic residue — most sensitive Varga.
A12: D9 Navamsha: starting sign per D1 sign (Parashari method)
A13: 1 | B13: Aries | C13: Aries | D13: 0 | E13: CHOOSE index for Aries = 0 (0=Aries, 3=Cancer, 6=Libra, 9=Capricorn)
A14: 2 | B14: Taurus | C14: Capricorn | D14: 9 | E14: CHOOSE index for Taurus = 9 (0=Aries, 3=Cancer, 6=Libra, 9=Capricorn)
A15: 3 | B15: Gemini | C15: Libra | D15: 6 | E15: CHOOSE index for Gemini = 6 (0=Aries, 3=Cancer, 6=Libra, 9=Capricorn)
A16: 4 | B16: Cancer | C16: Cancer | D16: 3 | E16: CHOOSE index for Cancer = 3 (0=Aries, 3=Cancer, 6=Libra, 9=Capricorn)
A17: 5 | B17: Leo | C17: Aries | D17: 0 | E17: CHOOSE index for Leo = 0 (0=Aries, 3=Cancer, 6=Libra, 9=Capricorn)
A18: 6 | B18: Virgo | C18: Capricorn | D18: 9 | E18: CHOOSE index for Virgo = 9 (0=Aries, 3=Cancer, 6=Libra, 9=Capricorn)
A19: 7 | B19: Libra | C19: Libra | D19: 6 | E19: CHOOSE index for Libra = 6 (0=Aries, 3=Cancer, 6=Libra, 9=Capricorn)
A20: 8 | B20: Scorpio | C20: Cancer | D20: 3 | E20: CHOOSE index for Scorpio = 3 (0=Aries, 3=Cancer, 6=Libra, 9=Capricorn)
A21: 9 | B21: Sagittarius | C21: Aries | D21: 0 | E21: CHOOSE index for Sagittarius = 0 (0=Aries, 3=Cancer, 6=Libra, 9=Capricorn)
A22: 10 | B22: Capricorn | C22: Capricorn | D22: 9 | E22: CHOOSE index for Capricorn = 9 (0=Aries, 3=Cancer, 6=Libra, 9=Capricorn)
A23: 11 | B23: Aquarius | C23: Libra | D23: 6 | E23: CHOOSE index for Aquarius = 6 (0=Aries, 3=Cancer, 6=Libra, 9=Capricorn)
A24: 12 | B24: Pisces | C24: Cancer | D24: 3 | E24: CHOOSE index for Pisces = 3 (0=Aries, 3=Cancer, 6=Libra, 9=Capricorn)

Sheet REF_DashaSequence
A1: REF_DashaSequence · Vimshottari Dasha 120-Year Cycle · BPHS Ch.47 | L1: =HYPERLINK("#'00_INDEX'!A1","<- Index") -> <- Index
A2: Fixed 9-planet order totalling 120 years. Starting Dasha = lord of Moon's Nakshatra at birth. Antardasha duration = (Maha_years × Antar_years) / 120.
B3: Planet | C3: Years | D3: Cumulative | E3: Nakshatras that trigger this Dasha | F3: Life theme
A4: 1 | B4: Ketu | C4: 7 | D4: 7 | E4: Ashwini(1) · Magha(10) · Mula(19) | F4: Karmic reckoning · isolation · past-life debts · sudden detachment
A5: 2 | B5: Venus | C5: 20 | D5: 27 | E5: Bharani(2) · Purva Phalguni(11) · Purva Ashadha(20) | F5: Luxury · love · arts · material abundance · 20 yrs = longest Dasha
A6: 3 | B6: Sun | C6: 6 | D6: 33 | E6: Krittika(3) · Uttara Phalguni(12) · Uttara Ashadha(21) | F6: Authority · vitality · government · father · soul purpose
A7: 4 | B7: Moon | C7: 10 | D7: 43 | E7: Rohini(4) · Hasta(13) · Shravana(22) | F7: Mind · emotions · public life · mother · travel · popularity
A8: 5 | B8: Mars | C8: 7 | D8: 50 | E8: Mrigashira(5) · Chitra(14) · Dhanishtha(23) | F8: Action · courage · siblings · property · conflict
A9: 6 | B9: Rahu | C9: 18 | D9: 68 | E9: Ardra(6) · Swati(15) · Shatabhisha(24) | F9: Ambition · foreign · technology · sudden rise or disruption
A10: 7 | B10: Jupiter | C10: 16 | D10: 84 | E10: Punarvasu(7) · Vishakha(16) · Purva Bhadrapada(25) | F10: Wisdom · expansion · children · dharma · fortune
A11: 8 | B11: Saturn | C11: 19 | D11: 103 | E11: Pushya(8) · Anuradha(17) · Uttara Bhadrapada(26) | F11: Discipline · karma · delays · service · longevity
A12: 9 | B12: Mercury | C12: 17 | D12: 120 | E12: Ashlesha(9) · Jyeshtha(18) · Revati(27) | F12: Intellect · communication · business · analysis
A14: Antardasha order: same 9-planet sequence starting from the Maha planet itself. Duration = (Maha_yrs × Antar_yrs) / 120. Example: Saturn/Venus = (19 × 20) / 120 = 3.17 years.

Sheet REF_PushkaraNavamsha
A1: REF_PushkaraNavamsha · Blessed Navamsha Padas · Uttara Kalamrita | L1: =HYPERLINK("#'00_INDEX'!A1","<- Index") -> <- Index
A2: Lookup: col A = sign where planet sits, col B = pada number. SCORE_H rule R21 does: COUNTIFS(col A, bhavesh_sign, col B, bhavesh_pada) > 0 → Pushkara bonus +0.5. Source: Uttara Kalamrita Ch.4 & Phaladeepika Ch.27.
A3: Sign (col A) | B3: Pada (col B) | C3: Nakshatra | D3: Nak # | E3: Degrees in sign | F3: Notes
A4: Taurus | B4: 2 | C4: Ashwini | D4: 1 | E4: 3°20'–6°40' Aries→D9 Tau | F4: Stable growth energy
A5: Leo | B5: 2 | C5: Bharani | D5: 2 | E5: 16°40'–20° Aries→D9 Leo | F5: Creative royal force
A6: Leo | B6: 1 | C6: Krittika (Aries) | D6: 3 | E6: 26°40'–30° Aries→D9 Leo | F6: Solar purity (Aries portion)
A7: Scorpio | B7: 3 | C7: Rohini | D7: 4 | E7: 10°–13°20' Taurus→D9 Sco | F7: Deep nourishment
A8: Libra | B8: 2 | C8: Mrigashira (Tau) | D8: 5 | E8: 3°20'–6°40' Taurus→D9 Lib | F8: Harmonious beauty
A9: Pisces | B9: 4 | C9: Mrigashira (Gem) | D9: 5 | E9: 16°40'–20° Gemini→D9 Pis | F9: Devotional grace
A10: Cancer | B10: 1 | C10: Punarvasu | D10: 7 | E10: 0°–3°20' Gemini→D9 Can | F10: Protective restoration
A11: Aquarius | B11: 3 | C11: Pushya | D11: 8 | E11: 6°40'–10° Cancer→D9 Aqu | F11: Humanitarian strength
A12: Cancer | B12: 4 | C12: Ashlesha | D12: 9 | E12: 10°–13°20' Cancer→D9 Can | F12: Occult healing
A13: Capricorn | B13: 2 | C13: Magha | D13: 10 | E13: 3°20'–6°40' Leo→D9 Cap | F13: Ancestral power
A14: Leo | B14: 1 | C14: Purva Phalguni | D14: 11 | E14: 13°20'–16°40' Leo→D9 Leo | F14: Dharmic creativity
A15: Virgo | B15: 4 | C15: Uttara Phalguni | D15: 12 | E15: 26°40'–30° Virgo→D9 Vir | F15: Service, purification
... A26: Pisces | B26: 3 | C26: Revati | D26: 27 | E26: 23°20'–26°40' Pis→D9 Pis | F26: Compassionate completion

Sheet REF_Config
A1: REF_Config · Global Configuration Toggles · Phase 2+ | G1: ← Index
A2: All CALC_ sheets in Phase 2+ read toggle values from this sheet. Change here to switch school of thought, Ayanamsha, or calculation policies globally. Blue cells are user-editable. All others are READ-ONLY.
A4: SECTION 1 — Calculation School Toggles
A5: Toggle | B5: Current Value | C5: Options | D5: Affects | E5: Notes
A6: Jyotish school | B6: Parashari | C6: Parashari / KP / Jaimini / Hybrid Parashari-Jaimini | D6: All CALC_ and SCORE_ sheets | E6: Parashari = classic BPHS. KP = Krishnamurti Paddhati (sub-lord system). Jaimini = Rasi Drishti + Chara Karakas primary. Hybrid = both in parallel.
A7: Ayanamsha | B7: Lahiri | C7: Lahiri / Raman / Krishnamurti / Fagan-Bradley | D7: CALC_PlanetLongitudes | E7: Lahiri = recommended for Vedic/BPHS. Standard Indian government ayanamsha. Currently hardcoded in CALC_PlanetLongitudes — this toggle documents the choice.
A8: Retrograde policy | B8: Full strength (classical) | C8: Apply R22 modifier / Ignore retrograde / Full strength (classical) | D8: CALC_RetrogradeFix → SCORE_H* R22 | E8: Apply R22 = ±0.1 modifier (current). Ignore = no Rx effect on scores. Full strength = some classical schools treat Rx as stronger, not weaker.
A9: Yogakaraka weight | B9: 1.5x Yogakaraka weight | C9: 1.5x / 1.25x / 1.0x (no distinction) | D9: SCORE_H* R02 and R06 | E9: 1.5x = current implementation. Distinguishes Yogakaraka from plain benefic. 1.0x = classical BPHS does not numerically distinguish — treat equally.
A10: WC aspect weight | B10: 0.75 three-quarter | C10: 0.5 half-weight / 0.75 three-quarter / 1.0 full weight | D10: SCORE_H* R03, R07, R14 | E10: 0.75 = current (upgraded from 0.5 in BPHS audit). BPHS Ch.26 equates aspect to occupation — 1.0 is the classical argument.
A11: Dukshthan penalty | B11: Apply -2.0 for R15 | C11: Apply -2.0 for R15 / Apply -1.5 / Apply -1.0 (original) | D11: SCORE_H* R15 | E11: -2.0 = current (symmetric with R04 +2.0). Classical argument strong. -1.0 = original design before BPHS audit.
A12: Kartari source | B12: Saravali (post-BPHS) | C12: Saravali (post-BPHS) / Ignore Kartari Yogas | D12: SCORE_H* R08 and R12 | E12: Kartari Yogas not in BPHS directly. Saravali Ch.5 is the source. Some strict Parashari practitioners ignore them — toggle to 0 weight if preferred.
A13: Combustion orbs | B13: BPHS standard | C13: BPHS standard / Tight (−2° tighter) / Loose (+2° wider) | D13: CALC_CombustionCheck | E13: BPHS orbs: Sun combust varies by planet (6°-17°). Standard = as defined in BPHS Ch.3. Tight/Loose = school variation. Currently hardcoded in CALC_CombustionCheck.
A14: Node type (Rahu/Ketu) | B14: Mean node | C14: Mean node / True node | D14: CALC_RetrogradeFix, REF_GrahaYuddha, D9 boundary charts | E14: Mean node = ephemeris API API default (ayanamsa param does not control node type). Mean vs true = ±1.5° oscillation. For Dasha calculation: mean node sufficient. For D9 placement in boundary charts: true node may matter. Phase 3: Swiss Ephemeris provides both via swe.MEAN_NODE and swe.TRUE_NODE.
A16: SECTION 2 — How CALC_ sheets read these toggles
A17: Phase 2 CALC_ sheets read REF_Config!$B$6 for school, $B$7 for Ayanamsha etc. Currently these are documentation toggles — Phase 2 CALC_ sheets will implement IF(REF_Config!$B$6="KP", KP_formula, Parashari_formula) branching logic. The named range "School" = REF_Config!$B$6 simplifies all formula references.
A18: ✓ TOGGLE WIRING COMPLETE (as of Phase 2, 17 Mar 2026): REF_Config!B6 school toggle is now LIVE in all 71 SCORE_H* sheets. 426 formula weight multipliers replaced with school-aware IF() expressions reading REF_SchoolConfig via REF_Config!$B$6. Rules wired: R03, R04, R08, R11, R12, R15, R17, R18, R20, R21, R23. Rules unchanged (all schools agree): R01, R02, R05, R06, R07, R09, R10, R13, R14, R16, R19, R22. To switch school: change REF_Config!B6 to Parashari / KP / Jaimini. All SCORE_H* scores update immediately.
A19: SECTION 3 — Counterfactual / Scenario mode
A20: Toggle | B20: Current Value | C20: Options | D20: Effect
A21: Scenario mode | B21: Off | C21: Off / On (use INPUT_Chart_Scenario) | D21: When On: SCORE_H sheets read INPUT_Chart_Scenario instead of INPUT_Chart
A24: v5 PATCH STATUS (17 Mar 2026): Issues #2–#11 resolved. #2: CALC_RetrogradeFix cols I/J (direction + Rx orb note). #3: CALC_CombustionCheck cols H/I/J (direction, Rx-adj orb, Rx-adj status). #5: SCORE_AllHouses col R (penalty cap ≤ −3.0 flag). #6: All YOGA_ sheets col H live dasha formula. #7: REF_GrahaYuddha Phase 3 latitude note. #8: CALC_Ashtakavarga 12-house verification table. #9: CALC_SwissEphemeris boundary alert cross-ref. #10: INPUT_BirthData Moon pada boundary alert. #11: REF_Config node type toggle. Remaining open: #9/#13 Chesta Bala full (Phase 3), #14 Tribhaga sunrise (Phase 2), #20 D60 (Phase 3).

Sheet REF_ArgalaRules
A1: REF_ArgalaRules · Argala & Virodha Argala Rules · BPHS Ch.28 | I1: ← Index
A2: Argala = planetary intervention. A planet in an Argala position strengthens the house it intervenes upon. Virodha Argala = obstruction. If a planet is in both Argala AND Virodha positions, they cancel. Net Argala = Argala count − Virodha count per house. Positive = intervention; negative = obstruction; zero = neutral.
A4: SECTION 1 — Argala and Virodha house positions (counted from any reference house)
A5: H# | B5: Argala Type | C5: Argala Position | D5: Virodha Position | E5: Strength | F5: Source | G5: Classical interpretation
A6: 1 | B6: Primary Argala (Dhan) | C6: H2 from reference | D6: H12 from reference | E6: Full | F6: BPHS Ch.28 v.1-4 | G6: Planets in H2 from any house cause Argala on it. Wealth/speech house intervention. Virodha from H12 (loss house) cancels it.
A7: 2 | B7: Primary Argala (Sukha) | C7: H4 from reference | D7: H10 from reference | E7: Full | F7: BPHS Ch.28 v.5-8 | G7: Planets in H4 from any house cause Argala. Happiness/home house intervention. Virodha from H10 (action house) cancels it.
A8: 3 | B8: Primary Argala (Karma) | C8: H11 from reference | D8: H3 from reference | E8: Full | F8: BPHS Ch.28 v.9-12 | G8: Planets in H11 (gains) cause strong Argala. Desire fulfillment. Virodha from H3 (effort/courage). One of the strongest Argalas.
A9: 4 | B9: Secondary Argala (Putra) | C9: H5 from reference | D9: H9 from reference | E9: Partial | F9: BPHS Ch.28 v.13-16 | G9: Planets in H5 cause partial Argala. Intelligence/children house intervention. Virodha from H9 (dharma/fortune). Partial = 50% strength in scoring.
A10: 5 | B10: Special: Lagnesh | C10: H1 itself | D10: — | E10: Special | F10: BPHS Ch.28 v.17 | G10: The Lagnesh always causes Argala on the Lagna — special rule. No Virodha applies. This is a non-standard application.
A11: 6 | B11: Malefic Virodha | C11: — | D11: Any Argala position | E11: Modifier | F11: BPHS Ch.28 v.18-20 | G11: When a malefic planet causes Argala, the effect is mixed — it intervenes but may harm. Benefic Argala = strengthens. Malefic Argala = activates but may harm significations.
A14: SECTION 2 — Argala score modifiers (fed to CALC_Argala → SCORE_H*)
A15: Condition | B15: Score modifier | C15: BPHS basis | D15: Notes
A16: Benefic in primary Argala position | B16: +0.5 per Argala house | C16: BPHS Ch.28 | D16: Benefic in H2/H4/H11 from a house → +0.5 per position occupied
A17: Malefic in primary Argala position | B17: +0.25 (mixed — activates but may harm) | C17: BPHS Ch.28 | D17: Malefic Argala is real but the outcome is mixed — less positive than benefic
A18: Virodha cancels Argala | B18: Net = 0 if Virodha count ≥ Argala count | C18: BPHS Ch.28 | D18: Count benefic Argalas, count Virodhas, subtract. Use net value only.
A19: Secondary Argala (H5) | B19: +0.25 (half of primary) | C19: BPHS Ch.28 | D19: H5 Argala is described as secondary — half weight in scoring.

Sheet REF_ArudhaRules
A1: REF_ArudhaRules · Arudha Pada Calculation Rules · BPHS Ch.29 + Jaimini Sutra 1.1.28-32 | H1: ← Index
A2: Arudha Pada = reflection of a house in the material world. Method: count from house to its lord (distance A). Count same distance (A) from lord. That landing sign is the Arudha Pada of that house. Special rule: if Arudha falls in H1 or H7 from itself, move to H10 or H4 respectively.
A4: SECTION 1 — Arudha Pada for all 12 houses (A1–A12)
A5: H# | B5: Arudha name | C5: Sanskrit | D5: Signification | E5: Special exception | F5: Calculation note
A6: 1 | B6: AL (Arudha Lagna) | C6: Arudha Lagna | D6: Social image · how the world perceives you · public persona · body and appearance | E6: If falls on H1: use H10. If on H7: use H4. | F6: Most important Arudha. Counted from Lagna lord. AL ≠ natal Lagna except by coincidence.
A7: 2 | B7: A2 (Dhana Pada) | C7: Dhana Arudha | D7: Perceived wealth · financial reputation · how others see your prosperity | E7: — | F7: Counted from H2 lord.
A8: 3 | B8: A3 (Vikrama Pada) | C8: Vikrama Arudha | D8: Perceived courage · public communication · social initiative | E8: — | F8: Counted from H3 lord.
A9: 4 | B9: A4 (Matri Pada) | C9: Matri Arudha | D9: Perceived home life · property visible to the world · mother's public image | E9: — | F9: Counted from H4 lord.
A10: 5 | B10: A5 (Putra Pada) | C10: Putra Arudha | D10: Perceived intelligence · public creativity · children known to the world | E10: — | F10: Counted from H5 lord.
A11: 6 | B11: A6 (Shhatru Pada) | C11: Shatru Arudha | D11: Visible enemies · public disputes · health issues others are aware of | E11: — | F11: Counted from H6 lord.
A12: 7 | B12: DL (Darapada) | C12: Dara Arudha | D12: Perceived spouse · public partnership · business partner visible to all | E12: If falls on H7: use H4. | F12: Second most important Arudha. Darapada = A7 = DL.
A13: 8 | B13: A8 (Mrityu Pada) | C13: Mrityu Arudha | D13: Perceived transformations · public knowledge of crises · visible debts | E13: — | F13: Counted from H8 lord. Often kept private — public perception of hidden matters.
A14: 9 | B14: A9 (Pitri Pada) | C14: Pitri Arudha | D14: Perceived fortune · public dharma · spiritual reputation · father's image | E14: — | F14: Counted from H9 lord.
A15: 10 | B15: A10 (Karma Pada) | C15: Karma Arudha | D15: Career reputation · professional public image · what actions you are known for | E15: — | F15: Counted from H10 lord. Critical for career analysis alongside D10.
A16: 11 | B16: A11 (Labha Pada) | C16: Labha Arudha | D16: Perceived income · social network · gains visible to the world | E16: — | F16: Counted from H11 lord.
A17: 12 | B17: UL (Upapada) | C17: Upapada Lagna | D17: Marriage quality · nature of spouse · fate of the relationship · co-habitation | E17: If falls on H12: use H6. | F17: Third most important Arudha. UL = A12. Lord of UL describes spouse nature. Malefics in UL or its 7th indicate relationship challenges.
A20: SECTION 2 — Arudha calculation algorithm
A21: FORMULA: For house H with lord L: 1. Count houses from H to L (call this D). 2. Count D houses from L. The resulting sign = Arudha Pada of H. 3. Special rules: if Arudha = H1 from itself → use H10 from Lagna. If Arudha = H7 from itself → use H4 from Lagna. EXCEL FORMULA PATTERN: Arudha_house = MOD((lord_bhav + (lord_bhav - house_num) - 1), 12) + 1 Then apply special exceptions for H1/H7 landing.

Sheet REF_GrahaYuddha
A1: REF_GrahaYuddha · Planetary War (Graha Yuddha) Rules · BPHS Ch.3 v.55-70 | H1: ← Index
A2: Graha Yuddha occurs when two classical planets (Mars/Mercury/Jupiter/Venus/Saturn) are within 1° of longitude of each other. Sun and Moon do not participate in Graha Yuddha. The loser suffers a dignity penalty. Winner takes enhanced strength. Rahu/Ketu are shadow nodes — no Graha Yuddha with nodes.
A4: SECTION 1 — War trigger conditions
A5: Rule | B5: Threshold | C5: Planets involved | D5: Winner determination | E5: Loser penalty | F5: Source
A6: War trigger | B6: Within 1° longitude | C6: Mars, Mercury, Jupiter, Venus, Saturn only | D6: Planet with more northerly celestial latitude wins. If latitude equal: brighter planet wins (Venus > Jupiter > Mercury > Mars > Saturn). | E6: Losing planet: −0.5 to effective dignity modifier in scoring | F6: BPHS Ch.3 v.55-58
A7: Winner bonus | B7: Same 1° orb | C7: Same 5 classical planets | D7: — | E7: Winning planet: +0.25 bonus to effective dignity modifier | F7: BPHS Ch.3 v.59-62
A8: Node exception | B8: N/A | C8: Rahu and Ketu excluded | D8: Nodes never participate in Graha Yuddha | E8: No effect | F8: BPHS Ch.3 v.63
A9: Luminary exception | B9: N/A | C9: Sun and Moon excluded | D9: Sun and Moon do not fight — they dominate by nature | E9: No effect | F9: BPHS Ch.3 v.64
A10: Combust during war | B10: 1° orb AND combust | C10: Any classical planet near Sun | D10: Combust planet cannot win a war even if technically northernmost | E10: Full combust penalty applies; war penalty is subsumed | F10: BPHS Ch.3 v.65-68
A13: SECTION 2 — Brightness ranking (tiebreaker)
A14: Rank | B14: Planet | C14: Relative brightness | D14: War advantage | E14: Notes
A15: 1 | B15: Venus | C15: Brightest classical planet | D15: Wins if latitude equal | E15: Often visible in daylight
A16: 2 | B16: Jupiter | C16: Second brightest | D16: Wins vs Mars/Mercury/Saturn if latitude equal | E16: Giant planet, high albedo
A17: 3 | B17: Mercury | C17: Variable — can be very bright | D17: Wins vs Mars/Saturn | E17: Proximity to Sun makes it variable
A18: 4 | B18: Mars | C18: Reddish, distinctive | D18: Wins vs Saturn only | E18: At opposition can rival Jupiter
A19: 5 | B19: Saturn | C19: Dimmest classical planet | D19: Rarely wins by brightness | E19: Rings visible only by telescope
A22: SECTION 3 — CALC_GrahaYuddha implementation notes
A23: DETECTION: For each pair of classical planets, compare absolute sidereal longitudes from CALC_PlanetLongitudes. If |lon_A - lon_B| < 1.0 (or > 359.0 for wrap-around), war is triggered. LATITUDE: BPHS uses celestial latitude for winner determination. Excel cannot compute this from the ephemeris formulae simplified formulas. APPROXIMATION: Use the brightness ranking above as tiebreaker (always applicable). Phase 3 Swiss Ephemeris will provide actual latitude for precise determination. SCORE EFFECT: Losing planet's dignity modifier reduced by 0.5. Winner's dignity modifier increased by 0.25. Applied in CALC_GrahaYuddha col D and E.
A25: ISSUE #7 RESOLVED (v6) | B25: Celestial latitude from Swiss Ephemeris xx[1] now live in CALC_GrahaYuddha cols I/J/K. Primary tiebreaker = northerly latitude (BPHS Ch.3 v.55). Brightness proxy retained as fallback for equal-latitude cases only.

Sheet REF_AvasthaRules
A1: REF_AvasthaRules · Graha Avastha States · BPHS Ch.45-47 | H1: ← Index
A2: Avastha = state or condition of a planet, modifying its ability to deliver results. Two systems: Baaladi (age-based, 5 states by degree within sign) and Sayanadi (mood-based, 12 states based on odd/even sign and degree position). A planet in Sushupti (deep sleep) delivers only ~25% of its promise.
A4: SECTION 1 — Baaladi Avastha (5 age states by degree in sign)
A5: State | B5: Sanskrit | C5: Degree range (odd sign) | D5: Degree range (even sign) | E5: Delivery % | F5: Interpretation
A6: Infant (Bala) | B6: Bala | C6: 0°–6° | D6: 24°–30° | E6: 25% | F6: Planet is infant — weak, self-absorbed, delivers very little. Results of this planet's houses are severely diminished.
A7: Child (Kumar) | B7: Kumara | C7: 6°–12° | D7: 18°–24° | E7: 50% | F7: Planet is a child — growing but unreliable. Delivers about half of its promise. Inconsistent results.
A8: Adolescent (Yuva) | B8: Yuva | C8: 12°–18° | D8: 12°–18° | E8: 100% | F8: Planet is in prime — fully active and delivers all its promise. This is the optimal state. Adolescent = peak results.
A9: Old (Vridha) | B9: Vridha | C9: 18°–24° | D9: 6°–12° | E9: 50% | F9: Planet is aging — past its prime. Still delivers but with less vigour. About 50% effectiveness.
A10: Dead (Mrita) | B10: Mrita | C10: 24°–30° | D10: 0°–6° | E10: 0% | F10: Planet is dead — delivers almost nothing. Even with excellent dignity, a dead planet cannot fulfil its significations.
A13: SECTION 2 — Sayanadi Avastha (12 mood states)
A14: # | B14: State | C14: Sanskrit | D14: Trigger condition | E14: Effect | F14: Source
A15: 1 | B15: Sleeping (Sayana) | C15: Sayana | D15: Odd sign, in 1st decanate (0°-10°) | E15: Planet is asleep — distracted, cannot act. Significantly weakened. | F15: BPHS Ch.45 v.1-4
A16: 2 | B16: Awakening (Upavesh) | C16: Upavesh | D16: Odd sign, in 2nd decanate (10°-20°) | E16: Planet is stirring — half-awake. Moderate weakness. | F16: BPHS Ch.45 v.5-8
A17: 3 | B17: Netrapani | C17: Netrapani | D17: Odd sign, in 3rd decanate (20°-30°) | E17: Planet holds its own eyes — introspective. Mixed results. | F17: BPHS Ch.45 v.9-12
A18: 4 | B18: Playing (Kautuka) | C18: Kautuka | D18: Even sign, in 1st decanate (0°-10°) | E18: Planet is playful — active but unfocused. Generally positive. | F18: BPHS Ch.45 v.13-16
A19: 5 | B19: Shame (Nishcheshta) | C19: Nishcheshta | D19: Even sign, in 2nd decanate (10°-20°) | E19: Planet is immobile/powerless. One of the weakest states. | F19: BPHS Ch.45 v.17-20
A20: 6 | B20: Hungry (Kshuditha) | C20: Kshuditha | D20: In enemy sign | E20: Planet is starved — weakened by hostile environment. Malefic effect. | F20: BPHS Ch.46 v.1-6
A21: 7 | B21: Thirsty (Trashita) | C21: Trashita | D21: In watery sign aspected by malefic | E21: Planet is unsatisfied — erratic results. Moderate negative. | F21: BPHS Ch.46 v.7-12
A22: 8 | B22: Afraid (Deena) | C22: Deena | D22: Defeated in Graha Yuddha (planetary war) | E22: Planet is frightened — delivers diminished results of its houses. | F22: BPHS Ch.46 v.13-18
A23: 9 | B23: Drunk (Mudita) | C23: Mudita | D23: In friendly sign + aspected by benefic | E23: Planet is joyful — excellent results, exceeds normal promise. | F23: BPHS Ch.47 v.1-6
A24: 10 | B24: Content (Sthira) | C24: Sthira | D24: In own or exaltation sign | E24: Planet is content — delivers full results steadily and reliably. | F24: BPHS Ch.47 v.7-12
A25: 11 | B25: Severe (Kopa) | C25: Kopa | D25: Combust (within Sun's orb) | E25: Planet is burning with anger — combust reduces effectiveness strongly. | F25: BPHS Ch.47 v.13-18
A26: 12 | B26: Natural (Prakrita) | C26: Prakrita | D26: All other conditions | E26: Normal state — delivers results as per dignity and house position. | F26: BPHS Ch.47 v.19
A28: SECTION 3 — Avastha score modifiers (fed to CALC_Avasthas)
A29: System | B29: State | C29: Score modifier | D29: Applied to | E29: Notes
A30: Baaladi | B30: Yuva (Adolescent) | C30: ×1.0 (no change) | D30: All planet scores | E30: Full effectiveness — no modifier needed
A31: Baaladi | B31: Kumar/Vridha (Child/Old) | C31: ×0.5 effectiveness | D31: R02,R06 (benefic association rules) | E31: Planet delivers 50% of its signification promise
A32: Baaladi | B32: Bala (Infant) | C32: ×0.25 effectiveness | D32: R02,R06 | E32: Planet is mostly ineffective — 75% reduction
A33: Baaladi | B33: Mrita (Dead) | C33: ×0.0 (nullify) | D33: R02,R06 | E33: Dead planet delivers nothing. Dignity is irrelevant.
A34: Sayanadi | B34: Mudita/Sthira (Joyful/Content) | C34: ×1.25 bonus | D34: R02,R04,R06 | E34: Planet exceeds its normal promise
A35: Sayanadi | B35: Deena/Kopa (Afraid/Angry) | C35: ×0.5 penalty | D35: R02,R04,R06 | E35: Defeated in war or combust: halved effectiveness
A36: Sayanadi | B36: Kshuditha (Hungry) | C36: ×0.75 penalty | D36: R02,R06 | E36: In enemy sign: moderate weakness

Sheet REF_VimshopakaBala
A1: REF_VimshopakaBala · Vimshopaka Bala Weights Across 16 Vargas · BPHS Ch.6 v.1-40 | I1: ← Index
A2: Vimshopaka Bala = strength of a planet across multiple divisional charts. Two systems: Shodasavarga (16 Vargas, max score 20) and Saptavarga (7 Vargas, max score 7). A planet scores its dignity weight in each Varga, then multiplied by the Varga weight. Total Vimshopaka out of 20 (or 7) reflects overall multi-dimensional strength.
A4: SECTION 1 — Shodasavarga (16 Varga) weights · Max total = 20
A5: # | B5: Varga | C5: Division | D5: Shodasavarga weight | E5: Saptavarga weight | F5: Currently available | G5: Signification
A6: 1 | B6: D1 (Rashi) | C6: 1 | D6: 3.5 | E6: 1 | F6: Complete (Phase 1) | G6: Natal chart. Represents physical body, overall life circumstances.
A7: 2 | B7: D2 (Hora) | C7: 2 | D7: 1 | E7: 0 | F7: Not built | G7: Wealth and financial prosperity. Sun hora / Moon hora.
A8: 3 | B8: D3 (Drekkana) | C8: 3 | D8: 1 | E8: 1 | F8: CALC_DivisionalMap col F | G8: Siblings, courage, longevity. Each decanate = 10°.
A9: 4 | B9: D4 (Chaturthamsha) | C9: 4 | D9: 0.5 | E9: 0 | F9: Not built | G9: Property, fixed assets, home. Each quadrant = 7.5°.
A10: 5 | B10: D7 (Saptamsha) | C10: 7 | D10: 0.5 | E10: 1 | F10: CALC_DivisionalMap col G | G10: Children and creative progeny. 4°17' per division.
A11: 6 | B11: D9 (Navamsha) | C11: 9 | D11: 3 | E11: 2 | F11: CALC_D9_Navamsha (Complete) | G11: Marriage, dharma, inner self. Most important Varga after D1.
A12: 7 | B12: D10 (Dashamsha) | C12: 10 | D12: 1.5 | E12: 0 | F12: CALC_DivisionalMap col E (partial) | G12: Career, profession, public life.
A13: 8 | B13: D12 (Dwadashamsha) | C13: 12 | D13: 0.5 | E13: 1 | F13: CALC_DivisionalMap col H | G13: Parents, ancestry, past life karma.
A14: 9 | B14: D16 (Shodashamsha) | C14: 16 | D14: 2 | E14: 0 | F14: Not built | G14: Vehicles, comforts, happiness. Each division = 1°52.5'.
A15: 10 | B15: D20 (Vimsamsha) | C15: 20 | D15: 0.5 | E15: 0 | F15: Not built | G15: Spiritual progress, worship, religious inclinations.
A16: 11 | B16: D24 (Chaturvimsamsha) | C16: 24 | D16: 0.5 | E16: 0 | F16: Not built | G16: Education, learning, academic achievements.
A17: 12 | B17: D27 (Bhamsha) | C17: 27 | D17: 0.5 | E17: 0 | F17: Not built | G17: Strength, physical prowess, siblings.
... A21: 16 | B21: D60 (Shastiamsha) | C21: 60 | D21: 4 | E21: 2 | F21: Not built (needs precise birth time) | G21: Past life karma, most sensitive Varga. 0°30' per division. Changes every 2 minutes of birth time.
A22: — | B22: TOTAL | D22: 20 | E22: 7 | F22: Max Vimshopaka = 20 (Shodasa) or 7 (Sapta)
A24: SECTION 2 — Dignity weight in each Varga (used in Vimshopaka computation)
A25: Dignity in Varga | B25: Sanskrit | C25: Shodasavarga weight | D25: Saptavarga weight | E25: Notes
A26: Own sign / Mooltrikona | B26: Swarashi/MLT | C26: 100% of Varga weight | D26: 100% of Varga weight | E26: Planet in its own sign in any Varga gets full weight for that Varga
A27: Exaltation sign | B27: Uchcha | C27: 75% of Varga weight | D27: 75% of Varga weight | E27: Exalted in Varga gets 75% — exaltation in Varga less important than in D1
A28: Friendly sign | B28: Mitra Rashi | C28: 50% of Varga weight | D28: 50% of Varga weight | E28: In a friendly sign in the Varga
A29: Neutral sign | B29: Sama Rashi | C29: 25% of Varga weight | D29: 25% of Varga weight | E29: In a neutral sign in the Varga
A30: Enemy sign / Debilitation | B30: Shatru/Neecha | C30: 0% (no contribution) | D30: 0% (no contribution) | E30: In enemy or debilitation sign in Varga — contributes nothing to Vimshopaka

Sheet REF_NarayanaDasaRules
A1: REF_NarayanaDasaRules · Narayana Dasha (Rasi Dasha) Rules · BPHS Ch.4 + PVRNR Jaimini Sutras | J1: ← Index
A2: Narayana Dasha = sign-based Dasha. The Dasha lord is a sign, not a planet. Duration depends on the sign and the planet in or aspecting it. Most versatile Rasi Dasha — used for general life events. Source: PVRNR "Narayana Dasha" (primary modern treatment); BPHS Ch.4.
A4: SECTION 1 — Sign durations (years per sign)
A5: Sign # | B5: Sign | C5: Modality | D5: Base years | E5: Adjustment rule | F5: Reversal? | G5: Actual years | H5: Notes
A6: 1 | B6: Aries | C6: Movable | D6: 6 | E6: Count from Aries to lord Mars in Scorpio = 8 → adj to 6 per PVRNR | F6: Yes (even Lagna) | G6: 6 | H6: Kama trikon. Action, initiative.
A7: 2 | B7: Taurus | C7: Fixed | D7: 4 | E7: Count from Taurus to lord Venus in Pisces (exalt) = 11, adj to 4 | F7: No | G7: 4 | H7: Artha. Resources, beauty, stability.
A8: 3 | B8: Gemini | C8: Dual | D8: 2 | E8: Shortest Rasi Dasha. Mercury period. | F8: Yes | G8: 2 | H8: Communication, siblings, short travel.
A9: 4 | B9: Cancer | C9: Movable | D9: 10 | E9: Moon = 10-year Mahadasha mirrored here. | F9: No | G9: 10 | H9: Home, mother, emotions, mind.
A10: 5 | B10: Leo | C10: Fixed | D10: 9 | E10: Sun = 6yr (Vimshottari) but Narayana Leo=9. | F10: Yes | G10: 9 | H10: Authority, father, vitality, leadership.
A11: 6 | B11: Virgo | C11: Dual | D11: 8 | E11: Mercury second sign. | F11: No | G11: 8 | H11: Health, service, debt, enemies.
A12: 7 | B12: Libra | C12: Movable | D12: 1 | E12: Shortest non-Gemini Dasha. Venus first sign. | F12: Yes | G12: 1 | H12: Partnerships, marriage, legal.
A13: 8 | B13: Scorpio | C13: Fixed | D13: 11 | E13: Mars second sign. Long Rasi Dasha. | F13: No | G13: 11 | H13: Transformation, secrets, longevity.
A14: 9 | B14: Sagittarius | C14: Dual | D14: 5 | E14: Jupiter first sign. Dharma trikon. | F14: Yes | G14: 5 | H14: Fortune, dharma, higher learning.
A15: 10 | B15: Capricorn | C15: Movable | D15: 7 | E15: Saturn first sign. Karma/discipline. | F15: No | G15: 7 | H15: Career, status, government.
A16: 11 | B16: Aquarius | C16: Fixed | D16: 12 | E16: Longest Rasi Dasha. Saturn second sign. | F16: Yes | G16: 12 | H16: Gains, network, aspirations, liberation.
A17: 12 | B17: Pisces | C17: Dual | D17: 3 | E17: Jupiter second sign. Moksha trikon. | F17: No | G17: 3 | H17: Moksha, losses, foreign, spiritual.
A20: SECTION 2 — Sequence rules (direction of Dasha travel)
A21: Rule | B21: Condition | C21: Direction | D21: Starting sign | E21: Effect | F21: Source
A22: Odd Lagna rule | B22: Lagna in odd sign (1/3/5/7/9/11) | C22: Forward (Aries→Taurus→...→Pisces) | D22: Lagna sign | E22: Dashas proceed forward through zodiac from Lagna | F22: PVRNR Narayana Dasha Ch.1
A23: Even Lagna rule | B23: Lagna in even sign (2/4/6/8/10/12) | C23: Backward (Pisces→Aquarius→...→Aries) | D23: Lagna sign | E23: Dashas proceed backward through zodiac from Lagna | F23: PVRNR Narayana Dasha Ch.1
A24: Exception: exalted lord | B24: If sign lord is exalted in D1 | C24: Reverse the direction for that sign | D24: Affected sign | E24: A sign with exalted lord reverses its travel direction | F24: PVRNR Narayana Dasha Ch.2
A25: Exception: debilitated lord | B25: If sign lord is debilitated in D1 | C25: No reversal | D25: Affected sign | E25: Debilitation does NOT trigger reversal (common misconception) | F25: PVRNR Narayana Dasha Ch.2
A26: Sub-period (Antardasha) | B26: Within each Rasi Mahadasha | C26: Same rule as Mahadasha | D26: Current Mahadasha sign | E26: Sub-periods = same 12 signs in same direction, scaled proportionally | F26: PVRNR Narayana Dasha Ch.3
A29: SECTION 3 — Excel implementation notes for CALC_NarayanaDasa
A30: EXCEL APPROACH: 1. Determine direction: IF(MOD(MATCH(INPUT_Chart!C5,signs,0),2)=1,"Forward","Backward") 2. Starting sign = Lagna sign (Input_Chart!C5) 3. For Forward: sequence = MOD(lagna_sign_num + i - 2, 12) + 1 for i=1..12 For Backward: sequence = MOD(lagna_sign_num - i + 12, 12) + 1 for i=1..12 4. Duration = SWITCH(sign_name, "Aries",6, "Taurus",4, "Gemini",2, ... "Aquarius",12, "Pisces",3) 5. Start date of period i = birth_date + SUM(durations of periods 1 to i-1) * 365.25 6. Active period = find which period bracket contains TODAY() NOTE: Full PVRNR implementation requires checking lord exaltation for direction reversal. The CALC_NarayanaDasa sheet implements the base rule; exaltation reversal flagged separately.

Sheet REF_D60SignMap
A1: REF_D60SignMap · Shastiamsha (D60) Sign Lookup · BPHS Ch.6 v.46-86 | H1: ← Index
A2: Each sign is divided into 60 parts of 0°30' each. For odd signs: sequence starts from Aries. For even signs: starts from Scorpio. The 60 divisions have classical Sanskrit names indicating their nature. D60 is the most sensitive Varga — changes every 2 minutes of birth time. Phase 3 note: Swiss Ephemeris precision required for reliable D60.
A4: SECTION 1 — 60 Shastiamsha division names and qualities
A5: Div # | B5: Pada ° | C5: Sanskrit name | D5: Quality | E5: Classical meaning | F5: Usage notes
A6: 1 | B6: 0.0° | C6: Ghora | D6: Malefic | E6: Harmful · violence · fear | F6: Malefic — planet here struggles with its significations
A7: 2 | B7: 0.5° | C7: Rakshasa | D7: Malefic | E7: Demon nature · destructive | F7: Malefic — planet here struggles with its significations
A8: 3 | B8: 1.0° | C8: Deva | D8: Benefic | E8: Divine · auspicious · noble | F8: Strong benefic influence — planet here thrives
A9: 4 | B9: 1.5° | C9: Kubera | D9: Benefic | E9: Wealth · prosperity · divine treasurer | F9: Strong benefic influence — planet here thrives
A10: 5 | B10: 2.0° | C10: Yaksha | D10: Neutral | E10: Semi-divine · nature spirits | F10: Mixed — outcome depends on planet and house
A11: 6 | B11: 2.5° | C11: Kinnara | D11: Benefic | E11: Celestial musician · arts · beauty | F11: Strong benefic influence — planet here thrives
A12: 7 | B12: 3.0° | C12: Bhrashta | D12: Malefic | E12: Fallen · degraded · corrupt | F12: Malefic — planet here struggles with its significations
A13: 8 | B13: 3.5° | C13: Kulaghna | D13: Malefic | E13: Destroyer of lineage | F13: Malefic — planet here struggles with its significations
A14: 9 | B14: 4.0° | C14: Garala | D14: Malefic | E14: Poison · toxicity | F14: Malefic — planet here struggles with its significations
A15: 10 | B15: 4.5° | C15: Vahni | D15: Mixed | E15: Fire · purification · intensity | F15: Mixed — outcome depends on planet and house
A16: 11 | B16: 5.0° | C16: Maya | D16: Malefic | E16: Illusion · deception | F16: Malefic — planet here struggles with its significations
A17: 12 | B17: 5.5° | C17: Purishaka | D17: Malefic | E17: Impure · degraded matter | F17: Malefic — planet here struggles with its significations
... A65: 60 | B65: 29.5° | C65: Indu | D65: Benefic | E65: See #18 above | F65: Strong benefic influence — planet here thrives
A68: SECTION 2 — D60 computation formula
A69: FORMULA: For a planet at absolute sidereal longitude L (0-360°): 1. Degree within sign = MOD(L, 30) 2. D60 position = INT(degree_within_sign / 0.5) + 1 → value 1-60 3. For ODD signs (Aries,Gemini,Leo,Virgo,Sagittarius,Aquarius,Aries): D60 sign # = D60_position For EVEN signs: D60 sign # = 61 - D60_position (reverses the sequence) 4. D60 sign name = INDEX(signs_array, D60_sign_num) 5. D60 Shastiamsha name = INDEX(d60_names, D60_position) PRECISION REQUIREMENT: 0°30' per division. Birth time accurate to ±1 min gives ±1 division uncertainty. Phase 3 requires Swiss Ephemeris longitude for reliable D60.

Sheet REF_KPSubLordTable
A1: REF_KPSubLordTable · KP Sub-Lord Nakshatra Divisions · Krishnamurti Paddhati · Star Lord + Sub Lord system | J1: ← Index
A2: Each Nakshatra (13°20') is divided into 9 sub-periods proportional to Vimshottari Dasha years. Total 27 × 9 = 243 sub-divisions covering 360°. KP system: house cusp sub-lord determines whether the house promises are fulfilled. Sub-lord in a house that is a significator of the event = event promised.
A4: SECTION 1 — Sub-lord size in degrees (universal, same for every Nakshatra)
A5: Sub-lord planet | B5: Years in 120 | C5: Sub-period ° | D5: Sub-period ' | E5: From longitude (within Nak) | F5: To longitude (within Nak)
A6: Ketu | B6: 7 | C6: 0.7778° | D6: 46.67' | E6: 0.0000° | F6: 0.7778°
A7: Venus | B7: 20 | C7: 2.2222° | D7: 133.33' | E7: 0.7778° | F7: 3.0000°
A8: Sun | B8: 6 | C8: 0.6667° | D8: 40.00' | E8: 3.0000° | F8: 3.6667°
A9: Moon | B9: 10 | C9: 1.1111° | D9: 66.67' | E9: 3.6667° | F9: 4.7778°
A10: Mars | B10: 7 | C10: 0.7778° | D10: 46.67' | E10: 4.7778° | F10: 5.5556°
A11: Rahu | B11: 18 | C11: 2.0000° | D11: 120.00' | E11: 5.5556° | F11: 7.5556°
A12: Jupiter | B12: 16 | C12: 1.7778° | D12: 106.67' | E12: 7.5556° | F12: 9.3333°
A13: Saturn | B13: 19 | C13: 2.1111° | D13: 126.67' | E13: 9.3333° | F13: 11.4444°
A14: Mercury | B14: 17 | C14: 1.8889° | D14: 113.33' | E14: 11.4444° | F14: 13.3333°
A17: SECTION 2 — How KP house analysis works
A18: KP METHOD FOR HOUSE ANALYSIS: 1. Find the cusp of the house (longitude of house cusp) 2. Identify the star lord (Nakshatra lord) of that longitude 3. Identify the sub-lord (sub-division lord) of that longitude 4. The sub-lord is the KEY INDICATOR — if sub-lord is significator of the relevant houses, event promised 5. Significators = planets in the house, lords of the house, or planets aspecting the house EXAMPLE: Is marriage promised by H7? Find H7 cusp longitude → find its sub-lord → check if sub-lord significates H2 (family), H7 (partner), or H11 (fulfillment) If yes → marriage is promised. If sub-lord also significates H6/H8/H12 → complications. EXCEL IMPLEMENTATION: CALC_KPSubLord (Phase 4) will use this table to identify sub-lords for each house cusp. Requires house cusps from a full equal house or Placidus system — not available in current D1 chart.
A24: SECTION 3 — Nakshatra start longitudes with star lord and first sub-lord
A25: Nak # | B25: Nakshatra | C25: Star lord | D25: Start ° | E25: End ° | F25: First sub-lord | G25: Sub-lord start ° | H25: Notes
A26: 1 | B26: Ashwini | C26: Ketu | D26: 0.000° | E26: 13.333° | F26: Ketu | G26: 0.000° | H26: Sub-lord sequence follows Vimshottari order from star lord
A27: 2 | B27: Bharani | C27: Venus | D27: 13.333° | E27: 26.667° | F27: Venus | G27: 13.333° | H27: Sub-lord sequence follows Vimshottari order from star lord
A28: 3 | B28: Krittika | C28: Sun | D28: 26.667° | E28: 40.000° | F28: Sun | G28: 26.667° | H28: Sub-lord sequence follows Vimshottari order from star lord
A29: 4 | B29: Rohini | C29: Moon | D29: 40.000° | E29: 53.333° | F29: Moon | G29: 40.000° | H29: Sub-lord sequence follows Vimshottari order from star lord
A30: 5 | B30: Mrigashira | C30: Mars | D30: 53.333° | E30: 66.667° | F30: Mars | G30: 53.333° | H30: Sub-lord sequence follows Vimshottari order from star lord
A31: 6 | B31: Ardra | C31: Rahu | D31: 66.667° | E31: 80.000° | F31: Rahu | G31: 66.667° | H31: Sub-lord sequence follows Vimshottari order from star lord
A32: 7 | B32: Punarvasu | C32: Jupiter | D32: 80.000° | E32: 93.333° | F32: Jupiter | G32: 80.000° | H32: Sub-lord sequence follows Vimshottari order from star lord
A33: 8 | B33: Pushya | C33: Saturn | D33: 93.333° | E33: 106.667° | F33: Saturn | G33: 93.333° | H33: Sub-lord sequence follows Vimshottari order from star lord
A34: 9 | B34: Ashlesha | C34: Mercury | D34: 106.667° | E34: 120.000° | F34: Mercury | G34: 106.667° | H34: Sub-lord sequence follows Vimshottari order from star lord
A35: 10 | B35: Magha | C35: Ketu | D35: 120.000° | E35: 133.333° | F35: Ketu | G35: 120.000° | H35: Sub-lord sequence follows Vimshottari order from star lord
A36: 11 | B36: Purva Phalguni | C36: Venus | D36: 133.333° | E36: 146.667° | F36: Venus | G36: 133.333° | H36: Sub-lord sequence follows Vimshottari order from star lord
A37: 12 | B37: Uttara Phalguni | C37: Sun | D37: 146.667° | E37: 160.000° | F37: Sun | G37: 146.667° | H37: Sub-lord sequence follows Vimshottari order from star lord
... A52: 27 | B52: Revati | C52: Mercury | D52: 346.667° | E52: 360.000° | F52: Mercury | G52: 346.667° | H52: Sub-lord sequence follows Vimshottari order from star lord

Sheet CALC_KPSubLord
A1: CALC_KPSubLord · KP Sub-Lord for each planet · Active when REF_Config!B6 = "KP" · Built 17-Mar-2026
A2: KP method: each Nakshatra (13°20') is divided into 9 sub-periods in Vimshottari order from the Nakshatra star lord. Sub-lord = the planet ruling the sub-period at the planet's exact longitude. Source: REF_KPSubLordTable. Formula is Excel-native — no macros needed. Sub-lord determines KP house cuspal analysis: sub-lord's house lordship governs promise delivery.
A4: Planet | B4: Abs° (0-360) | C4: Nakshatra | D4: Nak star lord | E4: Position in Nak (°) | F4: Sub-lord | G4: Sub-lord house# | H4: KP promise? | I4: School gate
A5: Lagna | B5: =(MATCH(INPUT_Chart!$C$5,{"Aries","Taurus","Gemini","Cancer","Leo","Virgo","Libra","Scorpio","Sagittarius","Capricorn","Aquarius","Pisces"},0)-1)*30+INPUT_Chart!$D$5 -> 37.7286 | C5: =IFERROR(INDEX({"Ashwini","Bharani","Krittika","Rohini","Mrigashira","Ardra","Punarvasu","Pushya","Ashlesha","Magha","Purva Phalguni","Uttara Phalguni","Hasta","Chitra","Swati","Vishakha","Anuradha","Jyeshtha","Mula","Purva Ashadha","Uttara Ashadha","Shravana","Dhanishtha","Shatabhisha","Purva Bhadrapada","Uttara Bhadrapada","Revati"},INT(B5/(40/3))+1),"—") -> Krittika | D5: =IFERROR(INDEX({"Ketu","Venus","Sun","Moon","Mars","Rahu","Jupiter","Saturn","Mercury"},MOD(INT(B5/(40/3)),9)+1),"—") -> Sun | E5: =IFERROR(ROUND(MOD(B5,(40/3)),4),"—") -> 11.0619 | F5: =IFERROR(IF(REF_Config!$B$6<>"KP","— (KP school only)",_xludf.let(al,B5,nak,INT(al/(40/3)),pos,MOD(al,(40/3)),k,MOD(nak,9),cum,{0.7778,2.9999,3.6666,4.7777,5.5555,7.5555,9.3333,11.4444,13.3333},slot,IFERROR(MATCH(TRUE(),pos<cum,0),9),lords,{"Ketu","Venus","Sun","Moon","Mars","Rahu","Jupiter","Saturn","Mercury"},INDEX(lords,1,MOD(k+slot-1,9)+1))),"—") -> — (KP school only) | G5: =IFERROR(IF(OR(REF_Config!$B$6<>"KP",F5="—"),"—",_xludf.switch(F5,"Sun",CALC_BhaveshMap!$H$6,"Moon",CALC_BhaveshMap!$H$7,"Mars",CALC_BhaveshMap!$H$8,"Mercury",CALC_BhaveshMap!$H$9,"Jupiter",CALC_BhaveshMap!$H$10,"Venus",CALC_BhaveshMap!$H$11,"Saturn",CALC_BhaveshMap!$H$12,"Rahu",CALC_BhaveshMap!$H$13,"Ketu",CALC_BhaveshMap!$H$14,"—")),"—") -> — | H5: =IFERROR(IF(OR(REF_Config!$B$6<>"KP",G5="—"),"—",IF(ISNUMBER(MATCH(G5,{1,2,3,4,5,6,7,8,9,10,11,12},0)),IF(ISNUMBER(MATCH(G5,{1,5,9,11},0)),"✓ Benefic H","✗ Non-benefic H"),"—")),"—") -> — | I5: =IF(REF_Config!$B$6="KP","▶ KP active","◦ Switch B6 to KP") -> ◦ Switch B6 to KP
A6: Sun | B6: =CALC_PlanetPositions!$D$7 -> 117.989 | C6: =IFERROR(INDEX({"Ashwini","Bharani","Krittika","Rohini","Mrigashira","Ardra","Punarvasu","Pushya","Ashlesha","Magha","Purva Phalguni","Uttara Phalguni","Hasta","Chitra","Swati","Vishakha","Anuradha","Jyeshtha","Mula","Purva Ashadha","Uttara Ashadha","Shravana","Dhanishtha","Shatabhisha","Purva Bhadrapada","Uttara Bhadrapada","Revati"},INT(B6/(40/3))+1),"—") -> Ashlesha | D6: =IFERROR(INDEX({"Ketu","Venus","Sun","Moon","Mars","Rahu","Jupiter","Saturn","Mercury"},MOD(INT(B6/(40/3)),9)+1),"—") -> Mercury | E6: =IFERROR(ROUND(MOD(B6,(40/3)),4),"—") -> 11.3223 | F6: =IFERROR(IF(REF_Config!$B$6<>"KP","— (KP school only)",_xludf.let(al,B6,nak,INT(al/(40/3)),pos,MOD(al,(40/3)),k,MOD(nak,9),cum,{0.7778,2.9999,3.6666,4.7777,5.5555,7.5555,9.3333,11.4444,13.3333},slot,IFERROR(MATCH(TRUE(),pos<cum,0),9),lords,{"Ketu","Venus","Sun","Moon","Mars","Rahu","Jupiter","Saturn","Mercury"},INDEX(lords,1,MOD(k+slot-1,9)+1))),"—") -> — (KP school only) | G6: =IFERROR(IF(OR(REF_Config!$B$6<>"KP",F6="—"),"—",_xludf.switch(F6,"Sun",CALC_BhaveshMap!$H$6,"Moon",CALC_BhaveshMap!$H$7,"Mars",CALC_BhaveshMap!$H$8,"Mercury",CALC_BhaveshMap!$H$9,"Jupiter",CALC_BhaveshMap!$H$10,"Venus",CALC_BhaveshMap!$H$11,"Saturn",CALC_BhaveshMap!$H$12,"Rahu",CALC_BhaveshMap!$H$13,"Ketu",CALC_BhaveshMap!$H$14,"—")),"—") -> — | H6: =IFERROR(IF(OR(REF_Config!$B$6<>"KP",G6="—"),"—",IF(ISNUMBER(MATCH(G6,{1,2,3,4,5,6,7,8,9,10,11,12},0)),IF(ISNUMBER(MATCH(G6,{1,5,9,11},0)),"✓ Benefic H","✗ Non-benefic H"),"—")),"—") -> — | I6: =IF(REF_Config!$B$6="KP","▶ KP active","◦ Switch B6 to KP") -> ◦ Switch B6 to KP
A7: Moon | B7: =CALC_PlanetPositions!$D$8 -> 93.9835 | C7: =IFERROR(INDEX({"Ashwini","Bharani","Krittika","Rohini","Mrigashira","Ardra","Punarvasu","Pushya","Ashlesha","Magha","Purva Phalguni","Uttara Phalguni","Hasta","Chitra","Swati","Vishakha","Anuradha","Jyeshtha","Mula","Purva Ashadha","Uttara Ashadha","Shravana","Dhanishtha","Shatabhisha","Purva Bhadrapada","Uttara Bhadrapada","Revati"},INT(B7/(40/3))+1),"—") -> Pushya | D7: =IFERROR(INDEX({"Ketu","Venus","Sun","Moon","Mars","Rahu","Jupiter","Saturn","Mercury"},MOD(INT(B7/(40/3)),9)+1),"—") -> Saturn | E7: =IFERROR(ROUND(MOD(B7,(40/3)),4),"—") -> 0.6502 | F7: =IFERROR(IF(REF_Config!$B$6<>"KP","— (KP school only)",_xludf.let(al,B7,nak,INT(al/(40/3)),pos,MOD(al,(40/3)),k,MOD(nak,9),cum,{0.7778,2.9999,3.6666,4.7777,5.5555,7.5555,9.3333,11.4444,13.3333},slot,IFERROR(MATCH(TRUE(),pos<cum,0),9),lords,{"Ketu","Venus","Sun","Moon","Mars","Rahu","Jupiter","Saturn","Mercury"},INDEX(lords,1,MOD(k+slot-1,9)+1))),"—") -> — (KP school only) | G7: =IFERROR(IF(OR(REF_Config!$B$6<>"KP",F7="—"),"—",_xludf.switch(F7,"Sun",CALC_BhaveshMap!$H$6,"Moon",CALC_BhaveshMap!$H$7,"Mars",CALC_BhaveshMap!$H$8,"Mercury",CALC_BhaveshMap!$H$9,"Jupiter",CALC_BhaveshMap!$H$10,"Venus",CALC_BhaveshMap!$H$11,"Saturn",CALC_BhaveshMap!$H$12,"Rahu",CALC_BhaveshMap!$H$13,"Ketu",CALC_BhaveshMap!$H$14,"—")),"—") -> — | H7: =IFERROR(IF(OR(REF_Config!$B$6<>"KP",G7="—"),"—",IF(ISNUMBER(MATCH(G7,{1,2,3,4,5,6,7,8,9,10,11,12},0)),IF(ISNUMBER(MATCH(G7,{1,5,9,11},0)),"✓ Benefic H","✗ Non-benefic H"),"—")),"—") -> — | I7: =IF(REF_Config!$B$6="KP","▶ KP active","◦ Switch B6 to KP") -> ◦ Switch B6 to KP
A8: Mars | B8: =CALC_PlanetPositions!$D$9 -> 67.4562 | C8: =IFERROR(INDEX({"Ashwini","Bharani","Krittika","Rohini","Mrigashira","Ardra","Punarvasu","Pushya","Ashlesha","Magha","Purva Phalguni","Uttara Phalguni","Hasta","Chitra","Swati","Vishakha","Anuradha","Jyeshtha","Mula","Purva Ashadha","Uttara Ashadha","Shravana","Dhanishtha","Shatabhisha","Purva Bhadrapada","Uttara Bhadrapada","Revati"},INT(B8/(40/3))+1),"—") -> Ardra | D8: =IFERROR(INDEX({"Ketu","Venus","Sun","Moon","Mars","Rahu","Jupiter","Saturn","Mercury"},MOD(INT(B8/(40/3)),9)+1),"—") -> Rahu | E8: =IFERROR(ROUND(MOD(B8,(40/3)),4),"—") -> 0.7895 | F8: =IFERROR(IF(REF_Config!$B$6<>"KP","— (KP school only)",_xludf.let(al,B8,nak,INT(al/(40/3)),pos,MOD(al,(40/3)),k,MOD(nak,9),cum,{0.7778,2.9999,3.6666,4.7777,5.5555,7.5555,9.3333,11.4444,13.3333},slot,IFERROR(MATCH(TRUE(),pos<cum,0),9),lords,{"Ketu","Venus","Sun","Moon","Mars","Rahu","Jupiter","Saturn","Mercury"},INDEX(lords,1,MOD(k+slot-1,9)+1))),"—") -> — (KP school only) | G8: =IFERROR(IF(OR(REF_Config!$B$6<>"KP",F8="—"),"—",_xludf.switch(F8,"Sun",CALC_BhaveshMap!$H$6,"Moon",CALC_BhaveshMap!$H$7,"Mars",CALC_BhaveshMap!$H$8,"Mercury",CALC_BhaveshMap!$H$9,"Jupiter",CALC_BhaveshMap!$H$10,"Venus",CALC_BhaveshMap!$H$11,"Saturn",CALC_BhaveshMap!$H$12,"Rahu",CALC_BhaveshMap!$H$13,"Ketu",CALC_BhaveshMap!$H$14,"—")),"—") -> — | H8: =IFERROR(IF(OR(REF_Config!$B$6<>"KP",G8="—"),"—",IF(ISNUMBER(MATCH(G8,{1,2,3,4,5,6,7,8,9,10,11,12},0)),IF(ISNUMBER(MATCH(G8,{1,5,9,11},0)),"✓ Benefic H","✗ Non-benefic H"),"—")),"—") -> — | I8: =IF(REF_Config!$B$6="KP","▶ KP active","◦ Switch B6 to KP") -> ◦ Switch B6 to KP
A9: Mercury | B9: =CALC_PlanetPositions!$D$10 -> 103.6743 | C9: =IFERROR(INDEX({"Ashwini","Bharani","Krittika","Rohini","Mrigashira","Ardra","Punarvasu","Pushya","Ashlesha","Magha","Purva Phalguni","Uttara Phalguni","Hasta","Chitra","Swati","Vishakha","Anuradha","Jyeshtha","Mula","Purva Ashadha","Uttara Ashadha","Shravana","Dhanishtha","Shatabhisha","Purva Bhadrapada","Uttara Bhadrapada","Revati"},INT(B9/(40/3))+1),"—") -> Pushya | D9: =IFERROR(INDEX({"Ketu","Venus","Sun","Moon","Mars","Rahu","Jupiter","Saturn","Mercury"},MOD(INT(B9/(40/3)),9)+1),"—") -> Saturn | E9: =IFERROR(ROUND(MOD(B9,(40/3)),4),"—") -> 10.341 | F9: =IFERROR(IF(REF_Config!$B$6<>"KP","— (KP school only)",_xludf.let(al,B9,nak,INT(al/(40/3)),pos,MOD(al,(40/3)),k,MOD(nak,9),cum,{0.7778,2.9999,3.6666,4.7777,5.5555,7.5555,9.3333,11.4444,13.3333},slot,IFERROR(MATCH(TRUE(),pos<cum,0),9),lords,{"Ketu","Venus","Sun","Moon","Mars","Rahu","Jupiter","Saturn","Mercury"},INDEX(lords,1,MOD(k+slot-1,9)+1))),"—") -> — (KP school only) | G9: =IFERROR(IF(OR(REF_Config!$B$6<>"KP",F9="—"),"—",_xludf.switch(F9,"Sun",CALC_BhaveshMap!$H$6,"Moon",CALC_BhaveshMap!$H$7,"Mars",CALC_BhaveshMap!$H$8,"Mercury",CALC_BhaveshMap!$H$9,"Jupiter",CALC_BhaveshMap!$H$10,"Venus",CALC_BhaveshMap!$H$11,"Saturn",CALC_BhaveshMap!$H$12,"Rahu",CALC_BhaveshMap!$H$13,"Ketu",CALC_BhaveshMap!$H$14,"—")),"—") -> — | H9: =IFERROR(IF(OR(REF_Config!$B$6<>"KP",G9="—"),"—",IF(ISNUMBER(MATCH(G9,{1,2,3,4,5,6,7,8,9,10,11,12},0)),IF(ISNUMBER(MATCH(G9,{1,5,9,11},0)),"✓ Benefic H","✗ Non-benefic H"),"—")),"—") -> — | I9: =IF(REF_Config!$B$6="KP","▶ KP active","◦ Switch B6 to KP") -> ◦ Switch B6 to KP
A10: Jupiter | B10: =CALC_PlanetPositions!$D$11 -> 205.8777 | C10: =IFERROR(INDEX({"Ashwini","Bharani","Krittika","Rohini","Mrigashira","Ardra","Punarvasu","Pushya","Ashlesha","Magha","Purva Phalguni","Uttara Phalguni","Hasta","Chitra","Swati","Vishakha","Anuradha","Jyeshtha","Mula","Purva Ashadha","Uttara Ashadha","Shravana","Dhanishtha","Shatabhisha","Purva Bhadrapada","Uttara Bhadrapada","Revati"},INT(B10/(40/3))+1),"—") -> Vishakha | D10: =IFERROR(INDEX({"Ketu","Venus","Sun","Moon","Mars","Rahu","Jupiter","Saturn","Mercury"},MOD(INT(B10/(40/3)),9)+1),"—") -> Jupiter | E10: =IFERROR(ROUND(MOD(B10,(40/3)),4),"—") -> 5.8777 | F10: =IFERROR(IF(REF_Config!$B$6<>"KP","— (KP school only)",_xludf.let(al,B10,nak,INT(al/(40/3)),pos,MOD(al,(40/3)),k,MOD(nak,9),cum,{0.7778,2.9999,3.6666,4.7777,5.5555,7.5555,9.3333,11.4444,13.3333},slot,IFERROR(MATCH(TRUE(),pos<cum,0),9),lords,{"Ketu","Venus","Sun","Moon","Mars","Rahu","Jupiter","Saturn","Mercury"},INDEX(lords,1,MOD(k+slot-1,9)+1))),"—") -> — (KP school only) | G10: =IFERROR(IF(OR(REF_Config!$B$6<>"KP",F10="—"),"—",_xludf.switch(F10,"Sun",CALC_BhaveshMap!$H$6,"Moon",CALC_BhaveshMap!$H$7,"Mars",CALC_BhaveshMap!$H$8,"Mercury",CALC_BhaveshMap!$H$9,"Jupiter",CALC_BhaveshMap!$H$10,"Venus",CALC_BhaveshMap!$H$11,"Saturn",CALC_BhaveshMap!$H$12,"Rahu",CALC_BhaveshMap!$H$13,"Ketu",CALC_BhaveshMap!$H$14,"—")),"—") -> — | H10: =IFERROR(IF(OR(REF_Config!$B$6<>"KP",G10="—"),"—",IF(ISNUMBER(MATCH(G10,{1,2,3,4,5,6,7,8,9,10,11,12},0)),IF(ISNUMBER(MATCH(G10,{1,5,9,11},0)),"✓ Benefic H","✗ Non-benefic H"),"—")),"—") -> — | I10: =IF(REF_Config!$B$6="KP","▶ KP active","◦ Switch B6 to KP") -> ◦ Switch B6 to KP
A11: Venus | B11: =CALC_PlanetPositions!$D$12 -> 112.5612 | C11: =IFERROR(INDEX({"Ashwini","Bharani","Krittika","Rohini","Mrigashira","Ardra","Punarvasu","Pushya","Ashlesha","Magha","Purva Phalguni","Uttara Phalguni","Hasta","Chitra","Swati","Vishakha","Anuradha","Jyeshtha","Mula","Purva Ashadha","Uttara Ashadha","Shravana","Dhanishtha","Shatabhisha","Purva Bhadrapada","Uttara Bhadrapada","Revati"},INT(B11/(40/3))+1),"—") -> Ashlesha | D11: =IFERROR(INDEX({"Ketu","Venus","Sun","Moon","Mars","Rahu","Jupiter","Saturn","Mercury"},MOD(INT(B11/(40/3)),9)+1),"—") -> Mercury | E11: =IFERROR(ROUND(MOD(B11,(40/3)),4),"—") -> 5.8945 | F11: =IFERROR(IF(REF_Config!$B$6<>"KP","— (KP school only)",_xludf.let(al,B11,nak,INT(al/(40/3)),pos,MOD(al,(40/3)),k,MOD(nak,9),cum,{0.7778,2.9999,3.6666,4.7777,5.5555,7.5555,9.3333,11.4444,13.3333},slot,IFERROR(MATCH(TRUE(),pos<cum,0),9),lords,{"Ketu","Venus","Sun","Moon","Mars","Rahu","Jupiter","Saturn","Mercury"},INDEX(lords,1,MOD(k+slot-1,9)+1))),"—") -> — (KP school only) | G11: =IFERROR(IF(OR(REF_Config!$B$6<>"KP",F11="—"),"—",_xludf.switch(F11,"Sun",CALC_BhaveshMap!$H$6,"Moon",CALC_BhaveshMap!$H$7,"Mars",CALC_BhaveshMap!$H$8,"Mercury",CALC_BhaveshMap!$H$9,"Jupiter",CALC_BhaveshMap!$H$10,"Venus",CALC_BhaveshMap!$H$11,"Saturn",CALC_BhaveshMap!$H$12,"Rahu",CALC_BhaveshMap!$H$13,"Ketu",CALC_BhaveshMap!$H$14,"—")),"—") -> — | H11: =IFERROR(IF(OR(REF_Config!$B$6<>"KP",G11="—"),"—",IF(ISNUMBER(MATCH(G11,{1,2,3,4,5,6,7,8,9,10,11,12},0)),IF(ISNUMBER(MATCH(G11,{1,5,9,11},0)),"✓ Benefic H","✗ Non-benefic H"),"—")),"—") -> — | I11: =IF(REF_Config!$B$6="KP","▶ KP active","◦ Switch B6 to KP") -> ◦ Switch B6 to KP
A12: Saturn | B12: =CALC_PlanetPositions!$D$13 -> 110.473 | C12: =IFERROR(INDEX({"Ashwini","Bharani","Krittika","Rohini","Mrigashira","Ardra","Punarvasu","Pushya","Ashlesha","Magha","Purva Phalguni","Uttara Phalguni","Hasta","Chitra","Swati","Vishakha","Anuradha","Jyeshtha","Mula","Purva Ashadha","Uttara Ashadha","Shravana","Dhanishtha","Shatabhisha","Purva Bhadrapada","Uttara Bhadrapada","Revati"},INT(B12/(40/3))+1),"—") -> Ashlesha | D12: =IFERROR(INDEX({"Ketu","Venus","Sun","Moon","Mars","Rahu","Jupiter","Saturn","Mercury"},MOD(INT(B12/(40/3)),9)+1),"—") -> Mercury | E12: =IFERROR(ROUND(MOD(B12,(40/3)),4),"—") -> 3.8063 | F12: =IFERROR(IF(REF_Config!$B$6<>"KP","— (KP school only)",_xludf.let(al,B12,nak,INT(al/(40/3)),pos,MOD(al,(40/3)),k,MOD(nak,9),cum,{0.7778,2.9999,3.6666,4.7777,5.5555,7.5555,9.3333,11.4444,13.3333},slot,IFERROR(MATCH(TRUE(),pos<cum,0),9),lords,{"Ketu","Venus","Sun","Moon","Mars","Rahu","Jupiter","Saturn","Mercury"},INDEX(lords,1,MOD(k+slot-1,9)+1))),"—") -> — (KP school only) | G12: =IFERROR(IF(OR(REF_Config!$B$6<>"KP",F12="—"),"—",_xludf.switch(F12,"Sun",CALC_BhaveshMap!$H$6,"Moon",CALC_BhaveshMap!$H$7,"Mars",CALC_BhaveshMap!$H$8,"Mercury",CALC_BhaveshMap!$H$9,"Jupiter",CALC_BhaveshMap!$H$10,"Venus",CALC_BhaveshMap!$H$11,"Saturn",CALC_BhaveshMap!$H$12,"Rahu",CALC_BhaveshMap!$H$13,"Ketu",CALC_BhaveshMap!$H$14,"—")),"—") -> — | H12: =IFERROR(IF(OR(REF_Config!$B$6<>"KP",G12="—"),"—",IF(ISNUMBER(MATCH(G12,{1,2,3,4,5,6,7,8,9,10,11,12},0)),IF(ISNUMBER(MATCH(G12,{1,5,9,11},0)),"✓ Benefic H","✗ Non-benefic H"),"—")),"—") -> — | I12: =IF(REF_Config!$B$6="KP","▶ KP active","◦ Switch B6 to KP") -> ◦ Switch B6 to KP
A13: Rahu | B13: =CALC_PlanetPositions!$D$14 -> 35.0697 | C13: =IFERROR(INDEX({"Ashwini","Bharani","Krittika","Rohini","Mrigashira","Ardra","Punarvasu","Pushya","Ashlesha","Magha","Purva Phalguni","Uttara Phalguni","Hasta","Chitra","Swati","Vishakha","Anuradha","Jyeshtha","Mula","Purva Ashadha","Uttara Ashadha","Shravana","Dhanishtha","Shatabhisha","Purva Bhadrapada","Uttara Bhadrapada","Revati"},INT(B13/(40/3))+1),"—") -> Krittika | D13: =IFERROR(INDEX({"Ketu","Venus","Sun","Moon","Mars","Rahu","Jupiter","Saturn","Mercury"},MOD(INT(B13/(40/3)),9)+1),"—") -> Sun | E13: =IFERROR(ROUND(MOD(B13,(40/3)),4),"—") -> 8.403 | F13: =IFERROR(IF(REF_Config!$B$6<>"KP","— (KP school only)",_xludf.let(al,B13,nak,INT(al/(40/3)),pos,MOD(al,(40/3)),k,MOD(nak,9),cum,{0.7778,2.9999,3.6666,4.7777,5.5555,7.5555,9.3333,11.4444,13.3333},slot,IFERROR(MATCH(TRUE(),pos<cum,0),9),lords,{"Ketu","Venus","Sun","Moon","Mars","Rahu","Jupiter","Saturn","Mercury"},INDEX(lords,1,MOD(k+slot-1,9)+1))),"—") -> — (KP school only) | G13: =IFERROR(IF(OR(REF_Config!$B$6<>"KP",F13="—"),"—",_xludf.switch(F13,"Sun",CALC_BhaveshMap!$H$6,"Moon",CALC_BhaveshMap!$H$7,"Mars",CALC_BhaveshMap!$H$8,"Mercury",CALC_BhaveshMap!$H$9,"Jupiter",CALC_BhaveshMap!$H$10,"Venus",CALC_BhaveshMap!$H$11,"Saturn",CALC_BhaveshMap!$H$12,"Rahu",CALC_BhaveshMap!$H$13,"Ketu",CALC_BhaveshMap!$H$14,"—")),"—") -> — | H13: =IFERROR(IF(OR(REF_Config!$B$6<>"KP",G13="—"),"—",IF(ISNUMBER(MATCH(G13,{1,2,3,4,5,6,7,8,9,10,11,12},0)),IF(ISNUMBER(MATCH(G13,{1,5,9,11},0)),"✓ Benefic H","✗ Non-benefic H"),"—")),"—") -> — | I13: =IF(REF_Config!$B$6="KP","▶ KP active","◦ Switch B6 to KP") -> ◦ Switch B6 to KP
A14: Ketu | B14: =CALC_PlanetPositions!$D$15 -> 215.0697 | C14: =IFERROR(INDEX({"Ashwini","Bharani","Krittika","Rohini","Mrigashira","Ardra","Punarvasu","Pushya","Ashlesha","Magha","Purva Phalguni","Uttara Phalguni","Hasta","Chitra","Swati","Vishakha","Anuradha","Jyeshtha","Mula","Purva Ashadha","Uttara Ashadha","Shravana","Dhanishtha","Shatabhisha","Purva Bhadrapada","Uttara Bhadrapada","Revati"},INT(B14/(40/3))+1),"—") -> Anuradha | D14: =IFERROR(INDEX({"Ketu","Venus","Sun","Moon","Mars","Rahu","Jupiter","Saturn","Mercury"},MOD(INT(B14/(40/3)),9)+1),"—") -> Saturn | E14: =IFERROR(ROUND(MOD(B14,(40/3)),4),"—") -> 1.7364 | F14: =IFERROR(IF(REF_Config!$B$6<>"KP","— (KP school only)",_xludf.let(al,B14,nak,INT(al/(40/3)),pos,MOD(al,(40/3)),k,MOD(nak,9),cum,{0.7778,2.9999,3.6666,4.7777,5.5555,7.5555,9.3333,11.4444,13.3333},slot,IFERROR(MATCH(TRUE(),pos<cum,0),9),lords,{"Ketu","Venus","Sun","Moon","Mars","Rahu","Jupiter","Saturn","Mercury"},INDEX(lords,1,MOD(k+slot-1,9)+1))),"—") -> — (KP school only) | G14: =IFERROR(IF(OR(REF_Config!$B$6<>"KP",F14="—"),"—",_xludf.switch(F14,"Sun",CALC_BhaveshMap!$H$6,"Moon",CALC_BhaveshMap!$H$7,"Mars",CALC_BhaveshMap!$H$8,"Mercury",CALC_BhaveshMap!$H$9,"Jupiter",CALC_BhaveshMap!$H$10,"Venus",CALC_BhaveshMap!$H$11,"Saturn",CALC_BhaveshMap!$H$12,"Rahu",CALC_BhaveshMap!$H$13,"Ketu",CALC_BhaveshMap!$H$14,"—")),"—") -> — | H14: =IFERROR(IF(OR(REF_Config!$B$6<>"KP",G14="—"),"—",IF(ISNUMBER(MATCH(G14,{1,2,3,4,5,6,7,8,9,10,11,12},0)),IF(ISNUMBER(MATCH(G14,{1,5,9,11},0)),"✓ Benefic H","✗ Non-benefic H"),"—")),"—") -> — | I14: =IF(REF_Config!$B$6="KP","▶ KP active","◦ Switch B6 to KP") -> ◦ Switch B6 to KP
A16: HOW TO USE KP SUB-LORD ANALYSIS
A17: 1. Set REF_Config!B6 = "KP" — all col F sub-lords activate. 2. For each planet, col F = sub-lord, col G = house# the sub-lord occupies. 3. KP rule: a planet delivers the promise of its sub-lord's house lordship. Sub-lord in H1/H5/H9/H11 = benefic promise (col H = ✓). Sub-lord in H6/H8/H12 = obstructed promise. 4. Lagna sub-lord governs the entire chart's life theme. 5. This sheet feeds SCORE_AllHouses col T (KP modifier) when KP school is active. 6. Source: REF_KPSubLordTable rows 6-14 (sub-lord sizes) + rows 26-52 (Nak start lons).

Sheet REF_APIFieldMap
A1: REF_APIFieldMap · API Response → Workbook Cell Mapping · ephemeris API Astrology API v2 | H1: ← Index
A2: Maps ephemeris API API JSON field names to INPUT_Chart and INPUT_BirthData cells. Used by ephemeris API_lagna.py to auto-populate the workbook. Also documents reference software API mappings as an alternative source.
A4: SECTION 1 — ephemeris API API v2 planet_position endpoint
A5: Planet | B5: API JSON field | C5: JSON path | D5: Target sheet | E5: Target cell | F5: Notes
A6: Lagna | B6: ascendant | C6: planets.ascendant.rasi.name + degree | D6: INPUT_Chart | E6: C5:D5 | F6: Sign name + decimal degree
A7: Sun | B7: sun | C7: planets.sun.rasi.name + degrees | D7: INPUT_Chart | E7: C6:D6
A8: Moon | B8: moon | C8: planets.moon.rasi.name + degrees | D8: INPUT_Chart | E8: C7:D7 | F8: Also get total longitude for INPUT_BirthData!B24
A9: Mars | B9: mars | C9: planets.mars.rasi.name + degrees | D9: INPUT_Chart | E9: C8:D8
A10: Mercury | B10: mercury | C10: planets.mercury.rasi.name + degrees | D10: INPUT_Chart | E10: C9:D9
A11: Jupiter | B11: jupiter | C11: planets.jupiter.rasi.name + degrees | D11: INPUT_Chart | E11: C10:D10
A12: Venus | B12: venus | C12: planets.venus.rasi.name + degrees | D12: INPUT_Chart | E12: C11:D11
A13: Saturn | B13: saturn | C13: planets.saturn.rasi.name + degrees | D13: INPUT_Chart | E13: C12:D12
A14: Rahu | B14: rahu | C14: planets.rahu.rasi.name + degrees | D14: INPUT_Chart | E14: C13:D13 | F14: True node or mean node — specify mean in API params
A15: Ketu | B15: ketu | C15: planets.ketu.rasi.name + degrees | D15: INPUT_Chart | E15: C14:D14 | F15: Ketu = Rahu + 180°. API usually gives separately.
A16: Ayanamsha | B16: ayanamsha_value | C16: ayanamsha.value | D16: INPUT_BirthData | E16: B20 | F16: Cross-check against calculated value
A17: Moon total lon | B17: moon | C17: planets.moon.longitude (0-360°) | D17: INPUT_BirthData | E17: B24 | F17: Required for Nakshatra + Dasha calc
A20: SECTION 2 — API authentication and endpoint details
A21: ephemeris API API v2 DETAILS: Base URL: https://api.ephemeris API.com/v2/astrology/ Planet positions endpoint: /planet-position Auth: OAuth2 client credentials. Client ID + Secret → access_token (expires in 3600s) Required params: datetime (ISO8601 UTC), coordinates (lat,lon), ayanamsha (lahiri) Sign name format: Returns full English name ("Aries", "Taurus"...) — matches workbook format exactly. Degree format: Returns decimal degrees (e.g. 14.73) — matches INPUT_Chart col D format exactly. CREDENTIALS (in ephemeris API_lagna.py): Client ID: ced21c60-f776-44b2-845a-1e9e8bf43102 Client Secret: kceqIRYRD9ao4gEBS7nmCUoRy6LG0nScRVkSCiS8 PYTHON SCRIPT STATUS: Built. Reads INPUT_BirthData birth date/time/location → calls API → writes INPUT_Chart. REMAINING WORK: Add Moon total longitude write to INPUT_BirthData!B24. Add error handling for rate limits.

Sheet REF_RuleInteractionMatrix
A1: REF_RuleInteractionMatrix · Rule Interaction Pairs · Phase 4 — BPHS + Saravali + Classical commentary | I1: ← Index
A2: When two specific rules fire simultaneously, their combined effect is NOT simply additive. This table defines interaction outcomes. Applied by CALC_RuleInteractionEngine. Flag types: Amplified (+bonus), Mixed Promise (reduces to floor), Nullified (cancel), Contextual (outcome depends on Dasha context).
A4: SECTION 1 — Rule interaction pairs (30 documented)
